Workbook

Sheet CRN
A1: S | N | B1: INSURED NAME | C1: CATEGORY | D1: CLIENT CODE | E1: CRN | F1: CLIENT NAME | G1: CLAIM NUMBER | H1: CASE RECIPET DATE | I1: RECIPET MONTH | J1: INSURED | K1: 134 NOTICE | L1: CLAIMANT | M1: INCOME | N1: DRIVER | O1: DL | P1: RC | Q1: PERMIT | R1: SPOT | S1: COURT | T1: NOTICE | U1: RTI | V1: HOSPITAL | W1: WITNESS | X1: MEDICAL VERIFICATION | Y1: TOTAl | Z1: WT
A2: 1 | B2: Inderdeep Construction Company | C2: MACT | D2: M002 | E2: M002-1001-SS-2025 | F2: =IF(D2="", "", _xlfn.XLOOKUP(D2, CLIENT_CODE!D:D, CLIENT_CODE!B:B, "")) -> Magma HDI General Insurance Company Ltd | G2: C2264103101203-00 | H2: 45873 | I2: =IF(ISBLANK(H2), "", TEXT(H2, "mmm-yy")) -> Aug-25 | J2: 1 | K2: 0 | L2: 1 | M2: 0 | N2: 1 | O2: 0 | P2: 0 | Q2: 0 | R2: 1 | S2: 1 | T2: 0 | U2: 0 | V2: 0 | W2: 0 | X2: 0 | Y2: =IF(COUNTA(J2:T2)=0, "", SUM(J2:T2)) -> 5 | Z2: {=_xlfn._xlws.FILTER(MIS_Backend_Data!L:L,MIS_Backend_Data!L:L="WT")} -> WT
A3: 2 | B3: Chandrabhaga Shivaji Pawar VS MAGMA | C3: MACT | D3: M002 | E3: M002-1002-SS-2025 | F3: =IF(D3="", "", _xlfn.XLOOKUP(D3, CLIENT_CODE!D:D, CLIENT_CODE!B:B, "")) -> Magma HDI General Insurance Company Ltd | G3: C2264191100006-00 | H3: 45873 | I3: =IF(ISBLANK(H3), "", TEXT(H3, "mmm-yy")) -> Aug-25 | J3: 1 | K3: 0 | L3: 1 | M3: 0 | N3: 1 | O3: 0 | P3: 0 | Q3: 0 | R3: 1 | S3: 1 | T3: 0 | U3: 0 | V3: 0 | W3: 0 | X3: 0 | Y3: =IF(COUNTA(J3:T3)=0, "", SUM(J3:T3)) -> 5 | Z3: WT
A4: 3 | B4: Balu Motiram Wagh VS MAGMA | C4: MACT | D4: M002 | E4: M002-1003-SS-2025 | F4: =IF(D4="", "", _xlfn.XLOOKUP(D4, CLIENT_CODE!D:D, CLIENT_CODE!B:B, "")) -> Magma HDI General Insurance Company Ltd | G4: C2264103101217-04 | H4: 45876 | I4: =IF(ISBLANK(H4), "", TEXT(H4, "mmm-yy")) -> Aug-25 | J4: 1 | K4: 0 | L4: 1 | M4: 0 | N4: 1 | O4: 0 | P4: 0 | Q4: 0 | R4: 1 | S4: 1 | T4: 0 | U4: 0 | V4: 0 | W4: 0 | X4: 0 | Y4: =IF(COUNTA(J4:T4)=0, "", SUM(J4:T4)) -> 5 | Z4: WT
A5: 4 | B5: Salim Ajgarali Sayyad | C5: MACT | D5: F001 | E5: F001-1004-SS-2025 | F5: =IF(D5="", "", _xlfn.XLOOKUP(D5, CLIENT_CODE!D:D, CLIENT_CODE!B:B, "")) -> Generali Central Insurance Company Limited | G5: MTP-N-2526-002724 | H5: 45890 | I5: =IF(ISBLANK(H5), "", TEXT(H5, "mmm-yy")) -> Aug-25 | J5: 1 | K5: 0 | L5: 1 | M5: 1 | N5: 1 | O5: 1 | P5: 1 | Q5: 0 | R5: 1 | S5: 1 | T5: 0 | U5: 0 | V5: 0 | W5: 0 | X5: 0 | Y5: =IF(COUNTA(J5:T5)=0, "", SUM(J5:T5)) -> 8 | Z5: WT
A6: 5 | B6: NA | C6: MACT | D6: F001 | E6: F001-1005-SS-2025 | F6: =IF(D6="", "", _xlfn.XLOOKUP(D6, CLIENT_CODE!D:D, CLIENT_CODE!B:B, "")) -> Generali Central Insurance Company Limited | G6: MTP-N-2526-002725 | H6: 45890 | I6: =IF(ISBLANK(H6), "", TEXT(H6, "mmm-yy")) -> Aug-25 | J6: 1 | K6: 0 | L6: 0 | M6: 0 | N6: 0 | O6: 0 | P6: 0 | Q6: 0 | R6: 0 | S6: 0 | T6: 0 | U6: 0 | V6: 0 | W6: 0 | X6: 0 | Y6: =IF(COUNTA(J6:T6)=0, "", SUM(J6:T6)) -> 1 | Z6: WT
A7: 6 | B7: NA | C7: MACT | D7: F001 | E7: F001-1006-SS-2025 | F7: =IF(D7="", "", _xlfn.XLOOKUP(D7, CLIENT_CODE!D:D, CLIENT_CODE!B:B, "")) -> Generali Central Insurance Company Limited | G7: MTP-N-2526-002726 | H7: 45890 | I7: =IF(ISBLANK(H7), "", TEXT(H7, "mmm-yy")) -> Aug-25 | J7: 1 | K7: 0 | L7: 0 | M7: 0 | N7: 0 | O7: 0 | P7: 0 | Q7: 0 | R7: 0 | S7: 0 | T7: 0 | U7: 0 | V7: 0 | W7: 0 | X7: 0 | Y7: =IF(COUNTA(J7:T7)=0, "", SUM(J7:T7)) -> 1 | Z7: WT
A8: 7 | B8: Gajanan Wishvanath Kapuskari | C8: MACT | D8: F001 | E8: F001-1007-SS-2025 | F8: =IF(D8="", "", _xlfn.XLOOKUP(D8, CLIENT_CODE!D:D, CLIENT_CODE!B:B, "")) -> Generali Central Insurance Company Limited | G8: MTP-N-2526-002845 | H8: 45897 | I8: =IF(ISBLANK(H8), "", TEXT(H8, "mmm-yy")) -> Aug-25 | J8: 1 | K8: 0 | L8: 0 | M8: 0 | N8: 1 | O8: 1 | P8: 1 | Q8: 1 | R8: 1 | S8: 1 | T8: 0 | U8: 0 | V8: 0 | W8: 0 | X8: 0 | Y8: =IF(COUNTA(J8:T8)=0, "", SUM(J8:T8)) -> 7 | Z8: WT
A9: 8 | B9: GorakhDamu Godage | C9: MACT | D9: F001 | E9: F001-1008-SS-2025 | F9: =IF(D9="", "", _xlfn.XLOOKUP(D9, CLIENT_CODE!D:D, CLIENT_CODE!B:B, "")) -> Generali Central Insurance Company Limited | G9: MTP-N-2526-003010 | H9: 45902 | I9: =IF(ISBLANK(H9), "", TEXT(H9, "mmm-yy")) -> Sep-25 | J9: 1 | K9: 0 | L9: 1 | M9: 1 | N9: 1 | O9: 1 | P9: 1 | Q9: 0 | R9: 1 | S9: 1 | T9: 0 | U9: 0 | V9: 0 | W9: 0 | X9: 0 | Y9: =IF(COUNTA(J9:T9)=0, "", SUM(J9:T9)) -> 8 | Z9: WT
A10: 9 | B10: Sharad RaoSaheb Pathare | C10: MACT | D10: R001 | E10: R001-1009-SS-2025 | F10: =IF(D10="", "", _xlfn.XLOOKUP(D10, CLIENT_CODE!D:D, CLIENT_CODE!B:B, "")) -> Indusind General Insurance Co Ltd | G10: 2025209111 | H10: 45916 | I10: =IF(ISBLANK(H10), "", TEXT(H10, "mmm-yy")) -> Sep-25 | J10: 1 | K10: 0 | L10: 1 | M10: 0 | N10: 1 | O10: 0 | P10: 0 | Q10: 0 | R10: 1 | S10: 1 | T10: 0 | U10: 0 | V10: 0 | W10: 0 | X10: 0 | Y10: =IF(COUNTA(J10:T10)=0, "", SUM(J10:T10)) -> 5 | Z10: WT
A11: 10 | B11: Ravindra Pandurang Patil | C11: MACT | D11: F001 | E11: F001-1010-SS-2025 | F11: =IF(D11="", "", _xlfn.XLOOKUP(D11, CLIENT_CODE!D:D, CLIENT_CODE!B:B, "")) -> Generali Central Insurance Company Limited | G11: CN064878 | H11: 45916 | I11: =IF(ISBLANK(H11), "", TEXT(H11, "mmm-yy")) -> Sep-25 | J11: 0 | K11: 0 | L11: 1 | M11: 0 | N11: 1 | O11: 0 | P11: 0 | Q11: O | R11: 1 | S11: 1 | T11: 0 | U11: 0 | V11: 1 | W11: 0 | X11: 0 | Y11: =IF(COUNTA(J11:T11)=0, "", SUM(J11:T11)) -> 4 | Z11: WT
A12: 11 | B12: Navnath Jagannatrh Navgire | C12: MACT | D12: R001 | E12: R001-1011-SS-2025 | F12: =IF(D12="", "", _xlfn.XLOOKUP(D12, CLIENT_CODE!D:D, CLIENT_CODE!B:B, "")) -> Indusind General Insurance Co Ltd | G12: 2025201119 | H12: 45916 | I12: =IF(ISBLANK(H12), "", TEXT(H12, "mmm-yy")) -> Sep-25 | J12: 0 | K12: 0 | L12: 0 | M12: 0 | N12: 0 | O12: 0 | P12: 0 | Q12: 0 | R12: 0 | S12: 1 | T12: 0 | U12: 0 | V12: 0 | W12: 0 | X12: 0 | Y12: =IF(COUNTA(J12:T12)=0, "", SUM(J12:T12)) -> 1 | Z12: WT
A13: 12 | B13: Sunil Annasaheb Kulat | C13: MACT | D13: R001 | E13: R001-1012-SS-2025 | F13: =IF(D13="", "", _xlfn.XLOOKUP(D13, CLIENT_CODE!D:D, CLIENT_CODE!B:B, "")) -> Indusind General Insurance Co Ltd | G13: 2025210107 | H13: 45917 | I13: =IF(ISBLANK(H13), "", TEXT(H13, "mmm-yy")) -> Sep-25 | J13: 1 | K13: 0 | L13: 1 | M13: 0 | N13: 1 | O13: 0 | P13: 0 | Q13: 0 | R13: 1 | S13: 1 | T13: 0 | U13: 0 | V13: 0 | W13: 0 | X13: 0 | Y13: =IF(COUNTA(J13:T13)=0, "", SUM(J13:T13)) -> 5 | Z13: WT
A14: 13 | B14: NA | C14: MACT | D14: R001 | E14: R001-1013-SS-2025 | F14: =IF(D14="", "", _xlfn.XLOOKUP(D14, CLIENT_CODE!D:D, CLIENT_CODE!B:B, "")) -> Indusind General Insurance Co Ltd | G14: 2025209818 | H14: 45917 | I14: =IF(ISBLANK(H14), "", TEXT(H14, "mmm-yy")) -> Sep-25 | J14: 0 | K14: 0 | L14: 1 | M14: 0 | N14: 0 | O14: 0 | P14: 0 | Q14: 0 | R14: 0 | S14: 0 | T14: 0 | U14: 0 | V14: 0 | W14: 0 | X14: 0 | Y14: =IF(COUNTA(J14:T14)=0, "", SUM(J14:T14)) -> 1 | Z14: WT
A15: 14 | B15: Dilip Parshuram Salukhe | C15: MACT | D15: R001 | E15: R001-1014-SS-2025 | F15: =IF(D15="", "", _xlfn.XLOOKUP(D15, CLIENT_CODE!D:D, CLIENT_CODE!B:B, "")) -> Indusind General Insurance Co Ltd | G15: 2025210174 | H15: 45917 | I15: =IF(ISBLANK(H15), "", TEXT(H15, "mmm-yy")) -> Sep-25 | J15: 1 | K15: 0 | L15: 1 | M15: 0 | N15: 1 | O15: 0 | P15: 0 | Q15: 0 | R15: 1 | S15: 1 | T15: 0 | U15: 0 | V15: 0 | W15: 0 | X15: 0 | Y15: =IF(COUNTA(J15:T15)=0, "", SUM(J15:T15)) -> 5 | Z15: WT
A16: 15 | B16: Jitendra Dyaneshwar Naik | C16: MACT | D16: R001 | E16: R001-1015-SS-2025 | F16: =IF(D16="", "", _xlfn.XLOOKUP(D16, CLIENT_CODE!D:D, CLIENT_CODE!B:B, "")) -> Indusind General Insurance Co Ltd | G16: 2025210104 | H16: 45917 | I16: =IF(ISBLANK(H16), "", TEXT(H16, "mmm-yy")) -> Sep-25 | J16: 0 | K16: 0 | L16: 1 | M16: 0 | N16: 0 | O16: 0 | P16: 0 | Q16: 0 | R16: 0 | S16: 1 | T16: 0 | U16: 0 | V16: 0 | W16: 0 | X16: 0 | Y16: =IF(COUNTA(J16:T16)=0, "", SUM(J16:T16)) -> 2 | Z16: WT
A17: 16 | B17: Uday Bapurao Devekar | C17: MACT | D17: R001 | E17: R001-1016-SS-2025 | F17: =IF(D17="", "", _xlfn.XLOOKUP(D17, CLIENT_CODE!D:D, CLIENT_CODE!B:B, "")) -> Indusind General Insurance Co Ltd | G17: 2025209654 | H17: 45917 | I17: =IF(ISBLANK(H17), "", TEXT(H17, "mmm-yy")) -> Sep-25 | J17: 1 | K17: 0 | L17: 1 | M17: 0 | N17: 1 | O17: 0 | P17: 0 | Q17: 0 | R17: 1 | S17: 1 | T17: 0 | U17: 0 | V17: 0 | W17: 0 | X17: 0 | Y17: =IF(COUNTA(J17:T17)=0, "", SUM(J17:T17)) -> 5 | Z17: WT
A18: 17 | B18: Mahadev Vayankat Panchal | C18: MACT | D18: R001 | E18: R001-1017-SS-2025 | F18: =IF(D18="", "", _xlfn.XLOOKUP(D18, CLIENT_CODE!D:D, CLIENT_CODE!B:B, "")) -> Indusind General Insurance Co Ltd | G18: 2025209769 | H18: 45917 | I18: =IF(ISBLANK(H18), "", TEXT(H18, "mmm-yy")) -> Sep-25 | J18: 1 | K18: 0 | L18: 1 | M18: 0 | N18: 1 | O18: 0 | P18: 0 | Q18: 0 | R18: 1 | S18: 1 | T18: 0 | U18: 0 | V18: 0 | W18: 0 | X18: 0 | Y18: =IF(COUNTA(J18:T18)=0, "", SUM(J18:T18)) -> 5 | Z18: WT
A19: 18 | B19: Chand Babu Israr Ahmad Khan | C19: MACT | D19: F001 | E19: F001-1018-SS-2025 | F19: =IF(D19="", "", _xlfn.XLOOKUP(D19, CLIENT_CODE!D:D, CLIENT_CODE!B:B, "")) -> Generali Central Insurance Company Limited | G19: CN065449 | H19: 45917 | I19: =IF(ISBLANK(H19), "", TEXT(H19, "mmm-yy")) -> Sep-25 | J19: 0 | K19: 0 | L19: 1 | M19: 1 | N19: 0 | O19: 1 | P19: 1 | Q19: 0 | R19: 0 | S19: 1 | T19: 0 | U19: 0 | V19: 1 | W19: 0 | X19: 0 | Y19: =IF(COUNTA(J19:T19)=0, "", SUM(J19:T19)) -> 5 | Z19: WT
A20: 19 | B20: Chand Babu Israr Ahmad Khan | C20: MACT | D20: F001 | E20: F001-1019-SS-2025 | F20: =IF(D20="", "", _xlfn.XLOOKUP(D20, CLIENT_CODE!D:D, CLIENT_CODE!B:B, "")) -> Generali Central Insurance Company Limited | G20: MTP-N-2526-003270 | H20: 45917 | I20: =IF(ISBLANK(H20), "", TEXT(H20, "mmm-yy")) -> Sep-25 | J20: 0 | K20: 0 | L20: 1 | M20: 1 | N20: 0 | O20: 0 | P20: 0 | Q20: 0 | R20: 0 | S20: 0 | T20: 0 | U20: 0 | V20: 1 | W20: 0 | X20: 0 | Y20: =IF(COUNTA(J20:T20)=0, "", SUM(J20:T20)) -> 2 | Z20: WT
A21: 20 | B21: Chand Babu Israr Ahmad Khan | C21: MACT | D21: F001 | E21: F001-1020-SS-2025 | F21: =IF(D21="", "", _xlfn.XLOOKUP(D21, CLIENT_CODE!D:D, CLIENT_CODE!B:B, "")) -> Generali Central Insurance Company Limited | G21: MTP-N-2526-003272 | H21: 45917 | I21: =IF(ISBLANK(H21), "", TEXT(H21, "mmm-yy")) -> Sep-25 | J21: 0 | K21: 0 | L21: 1 | M21: 1 | N21: 0 | O21: 0 | P21: 0 | Q21: 0 | R21: 0 | S21: 0 | T21: 0 | U21: 0 | V21: 1 | W21: 0 | X21: 0 | Y21: =IF(COUNTA(J21:T21)=0, "", SUM(J21:T21)) -> 2 | Z21: WT
A22: 21 | B22: HOUSRAO DASHRATH JAYBHAY | C22: MACT | D22: M002 | E22: M002-1021-SS-2025 | F22: =IF(D22="", "", _xlfn.XLOOKUP(D22, CLIENT_CODE!D:D, CLIENT_CODE!B:B, "")) -> Magma HDI General Insurance Company Ltd | G22: C2254103102949-00 | H22: 45734 | I22: =IF(ISBLANK(H22), "", TEXT(H22, "mmm-yy")) -> Mar-25 | J22: 1 | K22: 0 | L22: 1 | M22: 0 | N22: 1 | O22: 0 | P22: 0 | Q22: 0 | R22: 1 | S22: 1 | T22: 0 | U22: 0 | V22: 0 | W22: 0 | X22: 0 | Y22: =IF(COUNTA(J22:T22)=0, "", SUM(J22:T22)) -> 5 | Z22: WT
A23: 22 | B23: Ramchand Bhagchand Bhandare 9823327788 | C23: MACT | D23: R001 | E23: R001-1022-SS-2025 | F23: =IF(D23="", "", _xlfn.XLOOKUP(D23, CLIENT_CODE!D:D, CLIENT_CODE!B:B, "")) -> Indusind General Insurance Co Ltd | G23: 2024214888 | H23: 45918 | I23: =IF(ISBLANK(H23), "", TEXT(H23, "mmm-yy")) -> Sep-25 | J23: 1 | K23: 0 | L23: 1 | M23: 0 | N23: 1 | O23: 0 | P23: 0 | Q23: 0 | R23: 1 | S23: 1 | T23: 0 | U23: 0 | V23: 0 | W23: 0 | X23: 0 | Y23: =IF(COUNTA(J23:T23)=0, "", SUM(J23:T23)) -> 5 | Z23: WT
... A37: 36 | B37: Shrinivas Narsing Pal 7777072902 | C37: MACT | D37: R001 | E37: R001-1036-SS-2025 | F37: =IF(D37="", "", _xlfn.XLOOKUP(D37, CLIENT_CODE!D:D, CLIENT_CODE!B:B, "")) -> Indusind General Insurance Co Ltd | G37: 2025211458 | H37: 45944 | I37: =IF(ISBLANK(H37), "", TEXT(H37, "mmm-yy")) -> Oct-25 | J37: 1 | K37: 0 | L37: 1 | M37: 0 | N37: 1 | O37: 0 | P37: 0 | Q37: 0 | R37: 1 | S37: 1 | T37: 0 | U37: 0 | V37: 0 | W37: 0 | X37: 0 | Y37: =IF(COUNTA(J37:T37)=0, "", SUM(J37:T37)) -> 5 | Z37: WT
A38: 37 | B38: Aksha Ramesh Pawar | C38: MACT | D38: R001 | E38: R001-1037-SS-2025 | F38: =IF(D38="", "", _xlfn.XLOOKUP(D38, CLIENT_CODE!D:D, CLIENT_CODE!B:B, "")) -> Indusind General Insurance Co Ltd | G38: 2025211454 | H38: 45944 | I38: =IF(ISBLANK(H38), "", TEXT(H38, "mmm-yy")) -> Oct-25 | J38: S | K38: 0 | L38: 1 | M38: 0 | N38: 1 | O38: 0 | P38: 0 | Q38: 0 | R38: 1 | S38: 1 | T38: 0 | U38: 0 | V38: 0 | W38: 0 | X38: 0 | Y38: =IF(COUNTA(J38:T38)=0, "", SUM(J38:T38)) -> 4 | Z38: WT
A39: 38 | B39: Lalaji Manikrao Dhonde @ Dhande | C39: MACT | D39: R001 | E39: R001-1038-SS-2025 | F39: =IF(D39="", "", _xlfn.XLOOKUP(D39, CLIENT_CODE!D:D, CLIENT_CODE!B:B, "")) -> Indusind General Insurance Co Ltd | G39: 2025211475 | H39: 45946 | I39: =IF(ISBLANK(H39), "", TEXT(H39, "mmm-yy")) -> Oct-25 | J39: 1 | K39: 0 | L39: 1 | M39: 0 | N39: 1 | O39: 0 | P39: 0 | Q39: 0 | R39: 1 | S39: 1 | T39: 0 | U39: 0 | V39: 0 | W39: 0 | X39: 0 | Y39: =IF(COUNTA(J39:T39)=0, "", SUM(J39:T39)) -> 5 | Z39: WT
A40: 39 | B40: Ajay Satyanarayan Totawar | C40: MACT | D40: R001 | E40: R001-1039-SS-2025 | F40: =IF(D40="", "", _xlfn.XLOOKUP(D40, CLIENT_CODE!D:D, CLIENT_CODE!B:B, "")) -> Indusind General Insurance Co Ltd | G40: 2025211478 | H40: 45946 | I40: =IF(ISBLANK(H40), "", TEXT(H40, "mmm-yy")) -> Oct-25 | J40: 1 | K40: 0 | L40: 1 | M40: 0 | N40: 1 | O40: 0 | P40: 0 | Q40: 0 | R40: 1 | S40: 1 | T40: 0 | U40: 0 | V40: 0 | W40: 0 | X40: 0 | Y40: =IF(COUNTA(J40:T40)=0, "", SUM(J40:T40)) -> 5 | Z40: WT
A41: 40 | B41: Sanjay Sudam Gadgul | C41: MACT | D41: R001 | E41: R001-1040-SS-2025 | F41: =IF(D41="", "", _xlfn.XLOOKUP(D41, CLIENT_CODE!D:D, CLIENT_CODE!B:B, "")) -> Indusind General Insurance Co Ltd | G41: 2025210709 | H41: 45946 | I41: =IF(ISBLANK(H41), "", TEXT(H41, "mmm-yy")) -> Oct-25 | J41: 1 | K41: 0 | L41: 1 | M41: 0 | N41: 0 | O41: 0 | P41: 0 | Q41: 0 | R41: 1 | S41: 0 | T41: 0 | U41: 0 | V41: 0 | W41: 0 | X41: 0 | Y41: =IF(COUNTA(J41:T41)=0, "", SUM(J41:T41)) -> 3 | Z41: WT
A42: 41 | B42: Umesh Govinda Gavli | C42: MACT | D42: F001 | E42: F001-1041-SS-2025 | F42: =IF(D42="", "", _xlfn.XLOOKUP(D42, CLIENT_CODE!D:D, CLIENT_CODE!B:B, "")) -> Generali Central Insurance Company Limited | G42: CN066141 | H42: 45957 | I42: =IF(ISBLANK(H42), "", TEXT(H42, "mmm-yy")) -> Oct-25 | J42: 0 | K42: 0 | L42: 0 | M42: 0 | N42: 0 | O42: 0 | P42: 0 | Q42: 0 | R42: 0 | S42: 0 | T42: 0 | U42: 0 | V42: 1 | W42: 0 | X42: 0 | Y42: =IF(COUNTA(J42:T42)=0, "", SUM(J42:T42)) -> 0 | Z42: WT
A43: 42 | B43: Ranjeet Lala Chavan | C43: MACT | D43: F001 | E43: F001-1042-SS-2025 | F43: =IF(D43="", "", _xlfn.XLOOKUP(D43, CLIENT_CODE!D:D, CLIENT_CODE!B:B, "")) -> Generali Central Insurance Company Limited | G43: MTP-N-2526-004127 | H43: 45960 | I43: =IF(ISBLANK(H43), "", TEXT(H43, "mmm-yy")) -> Oct-25 | J43: 1 | K43: 0 | L43: 1 | M43: 1 | N43: 1 | O43: 1 | P43: 1 | Q43: 0 | R43: 1 | S43: 1 | T43: 0 | U43: 0 | V43: 1 | W43: 0 | X43: 0 | Y43: =IF(COUNTA(J43:T43)=0, "", SUM(J43:T43)) -> 8 | Z43: WT
A44: 43 | B44: NA | C44: MACT | D44: R001 | E44: R001-1043-SS-2025 | F44: =IF(D44="", "", _xlfn.XLOOKUP(D44, CLIENT_CODE!D:D, CLIENT_CODE!B:B, "")) -> Indusind General Insurance Co Ltd | G44: 2025212071 | H44: 45961 | I44: =IF(ISBLANK(H44), "", TEXT(H44, "mmm-yy")) -> Oct-25 | J44: 0 | K44: 0 | L44: 1 | M44: 0 | N44: 0 | O44: 0 | P44: 0 | Q44: 0 | R44: 0 | S44: 0 | T44: 0 | U44: 0 | V44: 0 | W44: 0 | X44: 0 | Y44: =IF(COUNTA(J44:T44)=0, "", SUM(J44:T44)) -> 1 | Z44: WT
A45: 44 | B45: Kakasaheb Shrirang Dhumal | C45: MACT | D45: R001 | E45: R001-1044-SS-2025 | F45: =IF(D45="", "", _xlfn.XLOOKUP(D45, CLIENT_CODE!D:D, CLIENT_CODE!B:B, "")) -> Indusind General Insurance Co Ltd | G45: 2025212068 | H45: 45961 | I45: =IF(ISBLANK(H45), "", TEXT(H45, "mmm-yy")) -> Oct-25 | J45: 1 | K45: 0 | L45: 1 | M45: 1 | N45: 0 | O45: 0 | P45: 0 | Q45: 0 | R45: 1 | S45: 1 | T45: 0 | U45: 0 | V45: 0 | W45: 0 | X45: 0 | Y45: =IF(COUNTA(J45:T45)=0, "", SUM(J45:T45)) -> 5 | Z45: WT
A46: 45 | B46: S. CUBE INFRASTRUCTURE | C46: MACT | D46: R001 | E46: R001-1045-SS-2025 | F46: =IF(D46="", "", _xlfn.XLOOKUP(D46, CLIENT_CODE!D:D, CLIENT_CODE!B:B, "")) -> Indusind General Insurance Co Ltd | G46: 2025212058 | H46: 45961 | I46: =IF(ISBLANK(H46), "", TEXT(H46, "mmm-yy")) -> Oct-25 | J46: 1 | K46: 0 | L46: 1 | M46: 0 | N46: 1 | O46: 0 | P46: 0 | Q46: 0 | R46: 1 | S46: 1 | T46: 0 | U46: 0 | V46: 0 | W46: 0 | X46: 0 | Y46: =IF(COUNTA(J46:T46)=0, "", SUM(J46:T46)) -> 5 | Z46: WT
A47: 46 | B47: NA | C47: MACT | D47: R001 | E47: R001-1046-SS-2025 | F47: =IF(D47="", "", _xlfn.XLOOKUP(D47, CLIENT_CODE!D:D, CLIENT_CODE!B:B, "")) -> Indusind General Insurance Co Ltd | G47: 2025212055 | H47: 45961 | I47: =IF(ISBLANK(H47), "", TEXT(H47, "mmm-yy")) -> Oct-25 | J47: 0 | K47: 0 | L47: 1 | M47: 0 | N47: 0 | O47: 0 | P47: 0 | Q47: 0 | R47: 0 | S47: 0 | T47: 0 | U47: 0 | V47: 0 | W47: 0 | X47: 0 | Y47: =IF(COUNTA(J47:T47)=0, "", SUM(J47:T47)) -> 1 | Z47: WT
A48: 47 | B48: Umesh Laxman Sathe | C48: MACT | D48: R001 | E48: R001-1047-SS-2025 | F48: =IF(D48="", "", _xlfn.XLOOKUP(D48, CLIENT_CODE!D:D, CLIENT_CODE!B:B, "")) -> Indusind General Insurance Co Ltd | G48: 2025212053 | H48: 45961 | I48: =IF(ISBLANK(H48), "", TEXT(H48, "mmm-yy")) -> Oct-25 | J48: 1 | K48: 0 | L48: 1 | M48: 0 | N48: 1 | O48: 0 | P48: 0 | Q48: 0 | R48: 1 | S48: 1 | T48: 0 | U48: 0 | V48: 0 | W48: 0 | X48: 0 | Y48: =IF(COUNTA(J48:T48)=0, "", SUM(J48:T48)) -> 5 | Z48: WT
A49: 48 | B49: Pravin Ashruba Andhale 9890471033 | C49: MACT | D49: R001 | E49: R001-1048-SS-2025 | F49: =IF(D49="", "", _xlfn.XLOOKUP(D49, CLIENT_CODE!D:D, CLIENT_CODE!B:B, "")) -> Indusind General Insurance Co Ltd | G49: 2025212050 | H49: 45961 | I49: =IF(ISBLANK(H49), "", TEXT(H49, "mmm-yy")) -> Oct-25 | J49: 1 | K49: 0 | L49: 1 | M49: 0 | N49: 1 | O49: 0 | P49: 0 | Q49: 0 | R49: 1 | S49: 1 | T49: 0 | U49: 0 | V49: 0 | W49: 0 | X49: 0 | Y49: =IF(COUNTA(J49:T49)=0, "", SUM(J49:T49)) -> 5 | Z49: WT
A50: 49 | B50: Rohit Dadarao Shirsath | C50: MACT | D50: R001 | E50: R001-1049-SS-2025 | F50: =IF(D50="", "", _xlfn.XLOOKUP(D50, CLIENT_CODE!D:D, CLIENT_CODE!B:B, "")) -> Indusind General Insurance Co Ltd | G50: 2025212047 | H50: 45961 | I50: =IF(ISBLANK(H50), "", TEXT(H50, "mmm-yy")) -> Oct-25 | J50: 1 | K50: 0 | L50: 1 | M50: 0 | N50: 1 | O50: 0 | P50: 0 | Q50: 0 | R50: 1 | S50: 1 | T50: 0 | U50: 0 | V50: 0 | W50: 0 | X50: 0 | Y50: =IF(COUNTA(J50:T50)=0, "", SUM(J50:T50)) -> 5 | Z50: WT
A51: 50 | B51: Vishal Kumar Goutamchand 9845320803 | C51: MACT | D51: F001 | E51: F001-1050-SS-2025 | F51: =IF(D51="", "", _xlfn.XLOOKUP(D51, CLIENT_CODE!D:D, CLIENT_CODE!B:B, "")) -> Generali Central Insurance Company Limited | G51: MTP-N-2526-004166 | H51: 45962 | I51: =IF(ISBLANK(H51), "", TEXT(H51, "mmm-yy")) -> Nov-25 | J51: 0 | K51: 0 | L51: 1 | M51: 0 | N51: 0 | O51: 0 | P51: 0 | Q51: 0 | R51: 0 | S51: 0 | T51: 0 | U51: 0 | V51: 0 | W51: 0 | X51: 0 | Z51: WT
A52: 51 | B52: Prahlad Piraji Umbre | C52: MACT | D52: R001 | E52: R001-1051-SS-2025 | F52: =IF(D52="", "", _xlfn.XLOOKUP(D52, CLIENT_CODE!D:D, CLIENT_CODE!B:B, "")) -> Indusind General Insurance Co Ltd | G52: 2025212181 | H52: 45964 | I52: =IF(ISBLANK(H52), "", TEXT(H52, "mmm-yy")) -> Nov-25 | J52: 1 | K52: 0 | L52: 1 | M52: 0 | N52: 1 | O52: 0 | P52: 0 | Q52: 0 | R52: 1 | S52: 1 | T52: 0 | U52: 0 | V52: 0 | W52: 0 | X52: 0 | Y52: =IF(COUNTA(J52:T52)=0, "", SUM(J52:T52)) -> 5 | Z52: WT
A53: 52 | B53: Bhagyashree Amol Shelke | C53: MACT | D53: R001 | E53: R001-1052-SS-2025 | F53: =IF(D53="", "", _xlfn.XLOOKUP(D53, CLIENT_CODE!D:D, CLIENT_CODE!B:B, "")) -> Indusind General Insurance Co Ltd | G53: 2025212170 | H53: 45964 | I53: =IF(ISBLANK(H53), "", TEXT(H53, "mmm-yy")) -> Nov-25 | J53: 1 | K53: 0 | L53: 1 | M53: 0 | N53: 1 | O53: 0 | P53: 0 | Q53: 0 | R53: 1 | S53: 1 | T53: 0 | U53: 0 | V53: 0 | W53: 0 | X53: 0 | Y53: =IF(COUNTA(J53:T53)=0, "", SUM(J53:T53)) -> 5 | Z53: WT
A54: 53 | B54: Navnath Santu Gofne | C54: MACT | D54: R001 | E54: R001-1053-SS-2025 | F54: =IF(D54="", "", _xlfn.XLOOKUP(D54, CLIENT_CODE!D:D, CLIENT_CODE!B:B, "")) -> Indusind General Insurance Co Ltd | G54: 2025212168 | H54: 45964 | I54: =IF(ISBLANK(H54), "", TEXT(H54, "mmm-yy")) -> Nov-25 | J54: 1 | K54: 0 | L54: 1 | M54: 0 | N54: 1 | O54: 0 | P54: 0 | Q54: 0 | R54: 1 | S54: 1 | T54: 0 | U54: 0 | V54: 0 | W54: 0 | X54: 0 | Y54: =IF(COUNTA(J54:T54)=0, "", SUM(J54:T54)) -> 5 | Z54: WT
A55: 54 | B55: Yogesh Digambar Mindad | C55: MACT | D55: R001 | E55: R001-1054-SS-2025 | F55: =IF(D55="", "", _xlfn.XLOOKUP(D55, CLIENT_CODE!D:D, CLIENT_CODE!B:B, "")) -> Indusind General Insurance Co Ltd | G55: 2025212148 | H55: 45964 | I55: =IF(ISBLANK(H55), "", TEXT(H55, "mmm-yy")) -> Nov-25 | J55: 1 | K55: 0 | L55: 1 | M55: 0 | N55: 1 | O55: 0 | P55: 0 | Q55: 0 | R55: 1 | S55: 1 | T55: 0 | U55: 0 | V55: 0 | W55: 0 | X55: 0 | Y55: =IF(COUNTA(J55:T55)=0, "", SUM(J55:T55)) -> 5 | Z55: WT
A56: 55 | B56: Sagar Manohar Raska 9518771836 | C56: MACT | D56: R001 | E56: R001-1055-SS-2025 | F56: =IF(D56="", "", _xlfn.XLOOKUP(D56, CLIENT_CODE!D:D, CLIENT_CODE!B:B, "")) -> Indusind General Insurance Co Ltd | G56: 2025212191 | H56: 45964 | I56: =IF(ISBLANK(H56), "", TEXT(H56, "mmm-yy")) -> Nov-25 | J56: 1 | K56: 0 | L56: 1 | M56: 0 | N56: 1 | O56: 0 | P56: 0 | Q56: 0 | R56: 1 | S56: 1 | T56: 0 | U56: 0 | V56: 0 | W56: 0 | X56: 0 | Y56: =IF(COUNTA(J56:T56)=0, "", SUM(J56:T56)) -> 5 | Z56: WT
A57: 56 | B57: RAJENDRA SAHEBRAO CHAUDHARI 9096231099 | C57: MACT | D57: R001 | E57: R001-1056-SS-2025 | F57: =IF(D57="", "", _xlfn.XLOOKUP(D57, CLIENT_CODE!D:D, CLIENT_CODE!B:B, "")) -> Indusind General Insurance Co Ltd | G57: 2025212189 | H57: 45964 | I57: =IF(ISBLANK(H57), "", TEXT(H57, "mmm-yy")) -> Nov-25 | J57: 1 | K57: 0 | L57: 1 | M57: 0 | N57: 1 | O57: 0 | P57: 0 | Q57: 0 | R57: 1 | S57: 1 | T57: 0 | U57: 0 | V57: 0 | W57: 0 | X57: 0 | Y57: =IF(COUNTA(J57:T57)=0, "", SUM(J57:T57)) -> 5 | Z57: WT
A58: 57 | B58: RAMESHWAR VITTHAL BHAGYAWANT | C58: MACT | D58: R001 | E58: R001-1057-SS-2025 | F58: =IF(D58="", "", _xlfn.XLOOKUP(D58, CLIENT_CODE!D:D, CLIENT_CODE!B:B, "")) -> Indusind General Insurance Co Ltd | G58: 2025212179 | H58: 45964 | I58: =IF(ISBLANK(H58), "", TEXT(H58, "mmm-yy")) -> Nov-25 | J58: 1 | K58: 0 | L58: 1 | M58: 0 | N58: 1 | O58: 0 | P58: 0 | Q58: 0 | R58: 1 | S58: 1 | T58: 0 | U58: 0 | V58: 0 | W58: 0 | X58: 0 | Y58: =IF(COUNTA(J58:T58)=0, "", SUM(J58:T58)) -> 5 | Z58: WT
A59: 58 | B59: Laxman Nawaji Thorat | C59: MACT | D59: R001 | E59: R001-1058-SS-2025 | F59: =IF(D59="", "", _xlfn.XLOOKUP(D59, CLIENT_CODE!D:D, CLIENT_CODE!B:B, "")) -> Indusind General Insurance Co Ltd | G59: 2025212145 | H59: 45964 | I59: =IF(ISBLANK(H59), "", TEXT(H59, "mmm-yy")) -> Nov-25 | J59: 1 | K59: 0 | L59: 1 | M59: 0 | N59: 1 | O59: 0 | P59: 0 | Q59: 0 | R59: 1 | S59: 1 | T59: 0 | U59: 0 | V59: 0 | W59: 0 | X59: 0 | Y59: =IF(COUNTA(J59:T59)=0, "", SUM(J59:T59)) -> 5 | Z59: WT
A60: 59 | B60: Dnyaneshwar Bhimraj Pathak | C60: MACT | D60: R001 | E60: R001-1059-SS-2025 | F60: =IF(D60="", "", _xlfn.XLOOKUP(D60, CLIENT_CODE!D:D, CLIENT_CODE!B:B, "")) -> Indusind General Insurance Co Ltd | G60: 2025212140 | H60: 45964 | I60: =IF(ISBLANK(H60), "", TEXT(H60, "mmm-yy")) -> Nov-25 | J60: 1 | K60: 0 | L60: 1 | M60: 0 | N60: 1 | O60: 0 | P60: 0 | Q60: 0 | R60: 1 | S60: 1 | T60: 0 | U60: 0 | V60: 0 | W60: 0 | X60: 0 | Y60: =IF(COUNTA(J60:T60)=0, "", SUM(J60:T60)) -> 5 | Z60: WT
A61: 60 | B61: VIJAY SHIVAJI THORAVE | C61: MACT | D61: R001 | E61: R001-1060-SS-2025 | F61: =IF(D61="", "", _xlfn.XLOOKUP(D61, CLIENT_CODE!D:D, CLIENT_CODE!B:B, "")) -> Indusind General Insurance Co Ltd | G61: 2025212028 | H61: 45964 | I61: =IF(ISBLANK(H61), "", TEXT(H61, "mmm-yy")) -> Nov-25 | J61: 1 | K61: 0 | L61: 0 | M61: 0 | N61: 0 | O61: 0 | P61: 0 | Q61: 0 | R61: 0 | S61: 0 | T61: 0 | U61: 0 | V61: 0 | W61: 0 | X61: 0 | Y61: =IF(COUNTA(J61:T61)=0, "", SUM(J61:T61)) -> 1 | Z61: WT
A62: 61 | B62: NA | C62: MACT | D62: R001 | E62: R001-1061-SS-2025 | F62: =IF(D62="", "", _xlfn.XLOOKUP(D62, CLIENT_CODE!D:D, CLIENT_CODE!B:B, "")) -> Indusind General Insurance Co Ltd | G62: 2025212222 | H62: 45964 | I62: =IF(ISBLANK(H62), "", TEXT(H62, "mmm-yy")) -> Nov-25 | J62: 0 | K62: 0 | L62: 1 | M62: 0 | N62: 0 | O62: 0 | P62: 0 | Q62: 0 | R62: 0 | S62: 0 | T62: 0 | U62: 0 | V62: 0 | W62: 0 | X62: 0 | Y62: =IF(COUNTA(J62:T62)=0, "", SUM(J62:T62)) -> 1 | Z62: WT
A63: 62 | B63: NA | C63: MACT | D63: R001 | E63: R001-1062-SS-2025 | F63: =IF(D63="", "", _xlfn.XLOOKUP(D63, CLIENT_CODE!D:D, CLIENT_CODE!B:B, "")) -> Indusind General Insurance Co Ltd | G63: 2025212162 | H63: 45964 | I63: =IF(ISBLANK(H63), "", TEXT(H63, "mmm-yy")) -> Nov-25 | J63: 0 | K63: 0 | L63: 1 | M63: 0 | N63: 0 | O63: 0 | P63: 0 | Q63: 0 | R63: 0 | S63: 0 | T63: 0 | U63: 0 | V63: 0 | W63: 0 | X63: 0 | Y63: =IF(COUNTA(J63:T63)=0, "", SUM(J63:T63)) -> 1 | Z63: WT
A64: 63 | B64: Subhash Pratap Salariya | C64: MACT | D64: F001 | E64: F001-1063-SS-2025 | F64: =IF(D64="", "", _xlfn.XLOOKUP(D64, CLIENT_CODE!D:D, CLIENT_CODE!B:B, "")) -> Generali Central Insurance Company Limited | G64: CN074856 | H64: 45968 | I64: =IF(ISBLANK(H64), "", TEXT(H64, "mmm-yy")) -> Nov-25 | J64: 1 | K64: 0 | L64: 0 | M64: 0 | N64: 1 | O64: 0 | P64: 0 | Q64: 0 | R64: 0 | S64: 0 | T64: 0 | U64: 0 | V64: 0 | W64: 0 | X64: 0 | Y64: =IF(COUNTA(J64:T64)=0, "", SUM(J64:T64)) -> 2 | Z64: WT
A65: 64 | B65: NA | C65: MACT | D65: F001 | E65: F001-1064-SS-2025 | F65: =IF(D65="", "", _xlfn.XLOOKUP(D65, CLIENT_CODE!D:D, CLIENT_CODE!B:B, "")) -> Generali Central Insurance Company Limited | G65: CM596085 | H65: 45968 | I65: =IF(ISBLANK(H65), "", TEXT(H65, "mmm-yy")) -> Nov-25 | J65: 0 | K65: 0 | L65: 0 | M65: 0 | N65: 0 | O65: 0 | P65: 0 | Q65: 0 | R65: 0 | S65: 0 | T65: 2 | U65: 0 | V65: 0 | W65: 0 | X65: 0 | Y65: =IF(COUNTA(J65:T65)=0, "", SUM(J65:T65)) -> 2 | Z65: WT | AA65: Summons cases we will be charges 2000
A66: 65 | B66: Laxmen S/o Gangadhar Jahane | C66: MACT | D66: R001 | E66: R001-1065-SS-2025 | F66: =IF(D66="", "", _xlfn.XLOOKUP(D66, CLIENT_CODE!D:D, CLIENT_CODE!B:B, "")) -> Indusind General Insurance Co Ltd | G66: 2025212410 | H66: 45970 | I66: =IF(ISBLANK(H66), "", TEXT(H66, "mmm-yy")) -> Nov-25 | J66: 1 | K66: 0 | L66: 1 | M66: 0 | N66: 1 | O66: 0 | P66: 0 | Q66: 0 | R66: 1 | S66: 1 | T66: 0 | U66: 0 | V66: 0 | W66: 0 | X66: 0 | Y66: =IF(COUNTA(J66:T66)=0, "", SUM(J66:T66)) -> 5 | Z66: WT
A67: 66 | B67: Vishnu Ganesh Kale | C67: MACT | D67: R001 | E67: R001-1066-SS-2025 | F67: =IF(D67="", "", _xlfn.XLOOKUP(D67, CLIENT_CODE!D:D, CLIENT_CODE!B:B, "")) -> Indusind General Insurance Co Ltd | G67: 2025212250 | H67: 45970 | I67: =IF(ISBLANK(H67), "", TEXT(H67, "mmm-yy")) -> Nov-25 | J67: 1 | K67: 0 | L67: 1 | M67: 0 | N67: 1 | O67: 0 | P67: 0 | Q67: 0 | R67: 1 | S67: 0 | T67: 0 | U67: 0 | V67: 0 | W67: 0 | X67: 0 | Y67: =IF(COUNTA(J67:T67)=0, "", SUM(J67:T67)) -> 4
A68: 67 | B68: Raj Umar Gaffer | C68: MACT | D68: R001 | E68: R001-1067-SS-2025 | F68: =IF(D68="", "", _xlfn.XLOOKUP(D68, CLIENT_CODE!D:D, CLIENT_CODE!B:B, "")) -> Indusind General Insurance Co Ltd | G68: 2025212219 | H68: 45970 | I68: =IF(ISBLANK(H68), "", TEXT(H68, "mmm-yy")) -> Nov-25 | J68: 1 | K68: 0 | L68: 1 | M68: 0 | N68: 1 | O68: 0 | P68: 0 | Q68: 0 | R68: 1 | S68: 1 | T68: 0 | U68: 0 | V68: 0 | W68: 0 | X68: 0 | Y68: =IF(COUNTA(J68:T68)=0, "", SUM(J68:T68)) -> 5
A69: 68 | B69: Chandrakant Naryan Pise | C69: MACT | D69: R001 | E69: R001-1068-SS-2025 | F69: =IF(D69="", "", _xlfn.XLOOKUP(D69, CLIENT_CODE!D:D, CLIENT_CODE!B:B, "")) -> Indusind General Insurance Co Ltd | G69: 2025212215 | H69: 45970 | I69: =IF(ISBLANK(H69), "", TEXT(H69, "mmm-yy")) -> Nov-25 | J69: 1 | K69: 0 | L69: 1 | M69: 0 | N69: 1 | O69: 0 | P69: 0 | Q69: 0 | R69: 1 | S69: 1 | T69: 0 | U69: 0 | V69: 0 | W69: 0 | X69: 0 | Y69: =IF(COUNTA(J69:T69)=0, "", SUM(J69:T69)) -> 5
A70: 69 | B70: Satish Bhalchandra More | C70: MACT | D70: R001 | E70: R001-1069-SS-2025 | F70: =IF(D70="", "", _xlfn.XLOOKUP(D70, CLIENT_CODE!D:D, CLIENT_CODE!B:B, "")) -> Indusind General Insurance Co Ltd | G70: 2025212407 | H70: 45970 | I70: =IF(ISBLANK(H70), "", TEXT(H70, "mmm-yy")) -> Nov-25 | J70: 0 | K70: 0 | L70: 1 | M70: 0 | N70: 0 | O70: 0 | P70: 0 | Q70: 0 | R70: 0 | S70: 0 | T70: 0 | U70: 0 | V70: 0 | W70: 0 | X70: 0 | Y70: =IF(COUNTA(J70:T70)=0, "", SUM(J70:T70)) -> 1
A71: 70 | B71: Aatmaram jadhav | C71: MACT | D71: R001 | E71: R001-1070-SS-2025 | F71: =IF(D71="", "", _xlfn.XLOOKUP(D71, CLIENT_CODE!D:D, CLIENT_CODE!B:B, "")) -> Indusind General Insurance Co Ltd | G71: 2025212443 | H71: 45970 | I71: =IF(ISBLANK(H71), "", TEXT(H71, "mmm-yy")) -> Nov-25 | J71: 1 | K71: 0 | L71: 1 | M71: 0 | N71: 1 | O71: 0 | P71: 0 | Q71: 0 | R71: 1 | S71: 1 | T71: 0 | U71: 0 | V71: 0 | W71: 0 | X71: 0 | Y71: =IF(COUNTA(J71:T71)=0, "", SUM(J71:T71)) -> 5
A72: 71 | B72: Shivand Niranjan Palmker | C72: MACT | D72: R001 | E72: R001-1071-SS-2025 | F72: =IF(D72="", "", _xlfn.XLOOKUP(D72, CLIENT_CODE!D:D, CLIENT_CODE!B:B, "")) -> Indusind General Insurance Co Ltd | G72: 2025212467 | H72: 45970 | I72: =IF(ISBLANK(H72), "", TEXT(H72, "mmm-yy")) -> Nov-25 | J72: 1 | K72: 0 | L72: 1 | M72: 0 | N72: 1 | O72: 0 | P72: 0 | Q72: 0 | R72: 1 | S72: 1 | T72: 0 | U72: 0 | V72: 0 | W72: 0 | X72: 0 | Y72: =IF(COUNTA(J72:T72)=0, "", SUM(J72:T72)) -> 5
A73: 72 | B73: Darshan Suresh Nangre | C73: MACT | D73: R001 | E73: R001-1072-SS-2025 | F73: =IF(D73="", "", _xlfn.XLOOKUP(D73, CLIENT_CODE!D:D, CLIENT_CODE!B:B, "")) -> Indusind General Insurance Co Ltd | G73: 2025212380 | H73: 45970 | I73: =IF(ISBLANK(H73), "", TEXT(H73, "mmm-yy")) -> Nov-25 | J73: 1 | K73: 0 | L73: 1 | M73: 0 | N73: 1 | O73: 0 | P73: 0 | Q73: 0 | R73: 1 | S73: 1 | T73: 0 | U73: 0 | V73: 0 | W73: 0 | X73: 0 | Y73: =IF(COUNTA(J73:T73)=0, "", SUM(J73:T73)) -> 5
A74: 73 | B74: Mohin Munir Pathan | C74: MACT | D74: R001 | E74: R001-1073-SS-2025 | F74: =IF(D74="", "", _xlfn.XLOOKUP(D74, CLIENT_CODE!D:D, CLIENT_CODE!B:B, "")) -> Indusind General Insurance Co Ltd | G74: 2025212399 | H74: 45970 | I74: =IF(ISBLANK(H74), "", TEXT(H74, "mmm-yy")) -> Nov-25 | J74: 1 | K74: 0 | L74: 1 | M74: 0 | N74: 1 | O74: 0 | P74: 0 | Q74: 0 | R74: 1 | S74: 1 | T74: 0 | U74: 0 | V74: 0 | W74: 0 | X74: 0 | Y74: =IF(COUNTA(J74:T74)=0, "", SUM(J74:T74)) -> 5
A75: 74 | B75: Tirupati shikshan sanstha | C75: MACT | D75: R001 | E75: R001-1074-SS-2025 | F75: =IF(D75="", "", _xlfn.XLOOKUP(D75, CLIENT_CODE!D:D, CLIENT_CODE!B:B, "")) -> Indusind General Insurance Co Ltd | G75: 2025212401 | H75: 45970 | I75: =IF(ISBLANK(H75), "", TEXT(H75, "mmm-yy")) -> Nov-25 | J75: 1 | K75: 0 | L75: 1 | M75: 0 | N75: 1 | O75: 0 | P75: 0 | Q75: 0 | R75: 1 | S75: 0 | T75: 0 | U75: 0 | V75: 0 | W75: 0 | X75: 0 | Y75: =IF(COUNTA(J75:T75)=0, "", SUM(J75:T75)) -> 4
A76: 75 | B76: Ramesh Laxmen Matangi | C76: MACT | D76: R001 | E76: R001-1075-SS-2025 | F76: =IF(D76="", "", _xlfn.XLOOKUP(D76, CLIENT_CODE!D:D, CLIENT_CODE!B:B, "")) -> Indusind General Insurance Co Ltd | G76: 2025212349 | H76: 45970 | I76: =IF(ISBLANK(H76), "", TEXT(H76, "mmm-yy")) -> Nov-25 | J76: 1 | K76: 0 | L76: 1 | M76: 0 | N76: 1 | O76: 0 | P76: 0 | Q76: 0 | R76: 1 | S76: 1 | T76: 0 | U76: 0 | V76: 0 | W76: 0 | X76: 0 | Y76: =IF(COUNTA(J76:T76)=0, "", SUM(J76:T76)) -> 5
A77: 76 | B77: Yunush Nizam Pathan 9158589465 | C77: MACT | D77: R001 | E77: R001-1076-SS-2025 | F77: =IF(D77="", "", _xlfn.XLOOKUP(D77, CLIENT_CODE!D:D, CLIENT_CODE!B:B, "")) -> Indusind General Insurance Co Ltd | G77: 2025212447 | H77: 45973 | I77: =IF(ISBLANK(H77), "", TEXT(H77, "mmm-yy")) -> Nov-25 | J77: 1 | K77: 0 | L77: 1 | M77: 0 | N77: 1 | O77: 0 | P77: 0 | Q77: 0 | R77: 1 | S77: 1 | T77: 0 | U77: 0 | V77: 0 | W77: 0 | X77: 0 | Y77: =IF(COUNTA(J77:T77)=0, "", SUM(J77:T77)) -> 5
A78: 77 | B78: Gajendra Rangrao Patil SR Tours & Travals 86258312621 | C78: MACT | D78: F001 | E78: F001-1077-SS-2025 | F78: =IF(D78="", "", _xlfn.XLOOKUP(D78, CLIENT_CODE!D:D, CLIENT_CODE!B:B, "")) -> Generali Central Insurance Company Limited | G78: MTP-N-2526-004298 | H78: 45973 | I78: =IF(ISBLANK(H78), "", TEXT(H78, "mmm-yy")) -> Nov-25 | J78: 1 | K78: 0 | L78: 1 | M78: 1 | N78: 1 | O78: 1 | P78: 1 | Q78: 0 | R78: 1 | S78: 1 | T78: 0 | U78: 0 | V78: 1 | W78: 0 | X78: 0 | Y78: =IF(COUNTA(J78:T78)=0, "", SUM(J78:T78)) -> 8
... A80: 79 | B80: Akshara Tours@Travels . | C80: MACT | D80: R001 | E80: R001-1079-SS-2025 | F80: =IF(D80="", "", _xlfn.XLOOKUP(D80, CLIENT_CODE!D:D, CLIENT_CODE!B:B, "")) -> Indusind General Insurance Co Ltd | G80: 2025212533 | H80: 45975 | I80: =IF(ISBLANK(H80), "", TEXT(H80, "mmm-yy")) -> Nov-25 | J80: 1 | K80: 0 | L80: 1 | M80: 0 | N80: 1 | O80: 0 | P80: 0 | Q80: 0 | R80: 1 | S80: 1 | T80: 0 | U80: 0 | V80: 0 | W80: 0 | X80: 0 | Y80: =IF(COUNTA(J80:T80)=0, "", SUM(J80:T80)) -> 5
A81: 80 | B81: Mr. Sachin A. Kharmate, | C81: MACT | D81: R001 | E81: R001-1080-SS-2025 | F81: =IF(D81="", "", _xlfn.XLOOKUP(D81, CLIENT_CODE!D:D, CLIENT_CODE!B:B, "")) -> Indusind General Insurance Co Ltd | G81: 2023205098 | H81: 45975 | I81: =IF(ISBLANK(H81), "", TEXT(H81, "mmm-yy")) -> Nov-25 | J81: 0 | K81: 0 | L81: 1 | M81: 0 | N81: 0 | O81: 0 | P81: 0 | Q81: 0 | R81: 0 | S81: 0 | T81: 0 | U81: 0 | V81: 0 | W81: 0 | X81: 0 | Y81: =IF(COUNTA(J81:T81)=0, "", SUM(J81:T81)) -> 1 | AA81: Injury Reassessment
A82: 81 | B82: Ratanpal Sewakram Gawture | C82: MACT | D82: R001 | E82: R001-1081-SS-2025 | F82: =IF(D82="", "", _xlfn.XLOOKUP(D82, CLIENT_CODE!D:D, CLIENT_CODE!B:B, "")) -> Indusind General Insurance Co Ltd | G82: 2021205783 | H82: 45975 | I82: =IF(ISBLANK(H82), "", TEXT(H82, "mmm-yy")) -> Nov-25 | J82: 0 | K82: 0 | L82: 1 | M82: 0 | N82: 0 | O82: 0 | P82: 0 | Q82: 0 | R82: 0 | S82: 0 | T82: 0 | U82: 0 | V82: 0 | W82: 0 | X82: 0 | Y82: =IF(COUNTA(J82:T82)=0, "", SUM(J82:T82)) -> 1 | AA82: Injury Reassessment
A83: 82 | B83: Nasir Ahmad QureshiS/o Abdul Gani Qureshi | C83: MACT | D83: R001 | E83: R001-1082-SS-2025 | F83: =IF(D83="", "", _xlfn.XLOOKUP(D83, CLIENT_CODE!D:D, CLIENT_CODE!B:B, "")) -> Indusind General Insurance Co Ltd | G83: 2020208122 | H83: 45975 | I83: =IF(ISBLANK(H83), "", TEXT(H83, "mmm-yy")) -> Nov-25 | J83: 0 | K83: 0 | L83: 1 | M83: 0 | N83: 0 | O83: 0 | P83: 0 | Q83: 0 | R83: 0 | S83: 0 | T83: 0 | U83: 0 | V83: 0 | W83: 0 | X83: 0 | Y83: =IF(COUNTA(J83:T83)=0, "", SUM(J83:T83)) -> 1 | AA83: Injury Reassessment
A84: 83 | B84: Thakkar Corporation. | C84: MACT | D84: R001 | E84: R001-1083-SS-2025 | F84: =IF(D84="", "", _xlfn.XLOOKUP(D84, CLIENT_CODE!D:D, CLIENT_CODE!B:B, "")) -> Indusind General Insurance Co Ltd | G84: 2019201744 | H84: 45975 | I84: =IF(ISBLANK(H84), "", TEXT(H84, "mmm-yy")) -> Nov-25 | J84: 0 | K84: 0 | L84: 1 | M84: 0 | N84: 0 | O84: 0 | P84: 0 | Q84: 0 | R84: 0 | S84: 0 | T84: 0 | U84: 0 | V84: 0 | W84: 0 | X84: 0 | Y84: =IF(COUNTA(J84:T84)=0, "", SUM(J84:T84)) -> 1 | AA84: Injury Reassessment
A85: 84 | B85: Shabeer Babusab Pahadwale.7028595337 | C85: MACT | D85: R001 | E85: R001-1084-SS-2025 | F85: =IF(D85="", "", _xlfn.XLOOKUP(D85, CLIENT_CODE!D:D, CLIENT_CODE!B:B, "")) -> Indusind General Insurance Co Ltd | G85: 2022209063 | H85: 45975 | I85: =IF(ISBLANK(H85), "", TEXT(H85, "mmm-yy")) -> Nov-25 | J85: 0 | K85: 0 | L85: 1 | M85: 0 | N85: 0 | O85: 0 | P85: 0 | Q85: 0 | R85: 0 | S85: 0 | T85: 0 | U85: 0 | V85: 0 | W85: 0 | X85: 0 | Y85: =IF(COUNTA(J85:T85)=0, "", SUM(J85:T85)) -> 1 | AA85: Injury Reassessment
A86: 85 | B86: Mohsin Babumiya Shaikh 7385504710 | C86: MACT | D86: R001 | E86: R001-1085-SS-2025 | F86: =IF(D86="", "", _xlfn.XLOOKUP(D86, CLIENT_CODE!D:D, CLIENT_CODE!B:B, "")) -> Indusind General Insurance Co Ltd | G86: 2017212612 | H86: 45975 | I86: =IF(ISBLANK(H86), "", TEXT(H86, "mmm-yy")) -> Nov-25 | J86: 0 | K86: 0 | L86: 1 | M86: 0 | N86: 0 | O86: 0 | P86: 0 | Q86: 0 | R86: 0 | S86: 0 | T86: 0 | U86: 0 | V86: 0 | W86: 0 | X86: 0 | Y86: =IF(COUNTA(J86:T86)=0, "", SUM(J86:T86)) -> 1 | AA86: Injury Reassessment
A87: 86 | B87: LOKMANGAL SUGAR ETHENOL AND CO GENERATION. | C87: MACT | D87: F001 | E87: F001-1086-SS-2025 | F87: =IF(D87="", "", _xlfn.XLOOKUP(D87, CLIENT_CODE!D:D, CLIENT_CODE!B:B, "")) -> Generali Central Insurance Company Limited | G87: MISC-2025-001662 | H87: 45976 | I87: =IF(ISBLANK(H87), "", TEXT(H87, "mmm-yy")) -> Nov-25 | J87: 1 | K87: 0 | L87: 0 | M87: 0 | N87: 0 | O87: 0 | P87: 0 | Q87: 0 | R87: 0 | S87: 0 | T87: 0 | U87: 0 | V87: 0 | W87: 0 | X87: 0 | Y87: =IF(COUNTA(J87:T87)=0, "", SUM(J87:T87)) -> 1 | AA87: WC
A88: 87 | B88: Aarohi Tours @Travels /Mohan Pandhare | C88: MACT | D88: R001 | E88: R001-1087-SS-2025 | F88: =IF(D88="", "", _xlfn.XLOOKUP(D88, CLIENT_CODE!D:D, CLIENT_CODE!B:B, "")) -> Indusind General Insurance Co Ltd | G88: 2025212670 | H88: 45979 | I88: =IF(ISBLANK(H88), "", TEXT(H88, "mmm-yy")) -> Nov-25 | J88: 0 | K88: 0 | L88: 1 | M88: 0 | N88: 0 | O88: 0 | P88: 0 | Q88: 0 | R88: 0 | S88: 0 | T88: 0 | U88: 0 | V88: 0 | W88: 0 | X88: 0 | Y88: =IF(COUNTA(J88:T88)=0, "", SUM(J88:T88)) -> 1
A89: 88 | B89: Aarohi Tours @Travels /Mohan Pandhare | C89: MACT | D89: R001 | E89: R001-1088-SS-2025 | F89: =IF(D89="", "", _xlfn.XLOOKUP(D89, CLIENT_CODE!D:D, CLIENT_CODE!B:B, "")) -> Indusind General Insurance Co Ltd | G89: 2025212671 | H89: 45979 | I89: =IF(ISBLANK(H89), "", TEXT(H89, "mmm-yy")) -> Nov-25 | J89: 0 | K89: 0 | L89: 1 | M89: 0 | N89: 0 | O89: 0 | P89: 0 | Q89: 0 | R89: 0 | S89: 0 | T89: 0 | U89: 0 | V89: 0 | W89: 0 | X89: 0 | Y89: =IF(COUNTA(J89:T89)=0, "", SUM(J89:T89)) -> 1
A90: 89 | B90: Aarohi Tours @Travels /Mohan Pandhare | C90: MACT | D90: R001 | E90: R001-1089-SS-2025 | F90: =IF(D90="", "", _xlfn.XLOOKUP(D90, CLIENT_CODE!D:D, CLIENT_CODE!B:B, "")) -> Indusind General Insurance Co Ltd | G90: 2025212673 | H90: 45979 | I90: =IF(ISBLANK(H90), "", TEXT(H90, "mmm-yy")) -> Nov-25 | J90: 1 | K90: 0 | L90: 1 | M90: 0 | N90: 1 | O90: 0 | P90: 0 | Q90: 0 | R90: 1 | S90: 1 | T90: 0 | U90: 0 | V90: 0 | W90: 0 | X90: 0 | Y90: =IF(COUNTA(J90:T90)=0, "", SUM(J90:T90)) -> 5
A91: 90 | B91: Sachin Pandurang Vaidhya | C91: MACT | D91: R001 | E91: R001-1090-SS-2025 | F91: =IF(D91="", "", _xlfn.XLOOKUP(D91, CLIENT_CODE!D:D, CLIENT_CODE!B:B, "")) -> Indusind General Insurance Co Ltd | G91: 2025212540 | H91: 45979 | I91: =IF(ISBLANK(H91), "", TEXT(H91, "mmm-yy")) -> Nov-25 | J91: 1 | K91: 0 | L91: 1 | M91: 0 | N91: 1 | O91: 0 | P91: 0 | Q91: 0 | R91: 1 | S91: 1 | T91: 0 | U91: 0 | V91: 0 | W91: 0 | X91: 0 | Y91: =IF(COUNTA(J91:T91)=0, "", SUM(J91:T91)) -> 5
A92: 91 | B92: Shaikh Shahid | C92: MACT | D92: R001 | E92: R001-1091-SS-2025 | F92: =IF(D92="", "", _xlfn.XLOOKUP(D92, CLIENT_CODE!D:D, CLIENT_CODE!B:B, "")) -> Indusind General Insurance Co Ltd | G92: 2025212595 | H92: 45979 | I92: =IF(ISBLANK(H92), "", TEXT(H92, "mmm-yy")) -> Nov-25 | J92: 1 | K92: 0 | L92: 1 | M92: 0 | N92: 1 | O92: 0 | P92: 0 | Q92: 0 | R92: 1 | S92: 1 | T92: 0 | U92: 0 | V92: 0 | W92: 0 | X92: 0 | Y92: =IF(COUNTA(J92:T92)=0, "", SUM(J92:T92)) -> 5
A93: 92 | B93: v | C93: MACT | D93: R001 | E93: R001-1092-SS-2025 | F93: =IF(D93="", "", _xlfn.XLOOKUP(D93, CLIENT_CODE!D:D, CLIENT_CODE!B:B, "")) -> Indusind General Insurance Co Ltd | G93: 2025212716 | H93: 45979 | I93: =IF(ISBLANK(H93), "", TEXT(H93, "mmm-yy")) -> Nov-25 | J93: 1 | K93: 0 | L93: 1 | M93: 0 | N93: 1 | O93: 0 | P93: 0 | Q93: 0 | R93: 1 | S93: 1 | T93: 0 | U93: 0 | V93: 0 | W93: 0 | X93: 0 | Y93: =IF(COUNTA(J93:T93)=0, "", SUM(J93:T93)) -> 5
A94: 93 | B94: Gautam Ramchandar Kamble 9762968332 | C94: MACT | D94: R001 | E94: R001-1093-SS-2025 | F94: =IF(D94="", "", _xlfn.XLOOKUP(D94, CLIENT_CODE!D:D, CLIENT_CODE!B:B, "")) -> Indusind General Insurance Co Ltd | G94: 2025208486 | H94: 45980 | I94: =IF(ISBLANK(H94), "", TEXT(H94, "mmm-yy")) -> Nov-25 | J94: 1 | K94: 0 | L94: 1 | M94: 0 | N94: 1 | O94: 0 | P94: 0 | Q94: 0 | R94: 1 | S94: 1 | T94: 0 | U94: 0 | V94: 0 | W94: 0 | X94: 0 | Y94: =IF(COUNTA(J94:T94)=0, "", SUM(J94:T94)) -> 5
A95: 94 | B95: Asaram Sitaram Neharkar | C95: MACT | D95: R001 | E95: R001-1094-SS-2025 | F95: =IF(D95="", "", _xlfn.XLOOKUP(D95, CLIENT_CODE!D:D, CLIENT_CODE!B:B, "")) -> Indusind General Insurance Co Ltd | G95: 2025209152 | H95: 45980 | I95: =IF(ISBLANK(H95), "", TEXT(H95, "mmm-yy")) -> Nov-25 | J95: 1 | K95: 0 | L95: 1 | M95: 0 | N95: 1 | O95: 0 | P95: 0 | Q95: 0 | R95: 1 | S95: 1 | T95: 0 | U95: 0 | V95: 0 | W95: 0 | X95: 0 | Y95: =IF(COUNTA(J95:T95)=0, "", SUM(J95:T95)) -> 5
A96: 95 | B96: Ravindra Mohan Tambe 9665127299 | C96: MACT | D96: R001 | E96: R001-1095-SS-2025 | F96: =IF(D96="", "", _xlfn.XLOOKUP(D96, CLIENT_CODE!D:D, CLIENT_CODE!B:B, "")) -> Indusind General Insurance Co Ltd | G96: 2025212593 | H96: 45980 | I96: =IF(ISBLANK(H96), "", TEXT(H96, "mmm-yy")) -> Nov-25 | J96: 0 | K96: 0 | L96: 1 | M96: 0 | N96: 0 | O96: 0 | P96: 0 | Q96: 0 | R96: 0 | S96: 0 | T96: 0 | U96: 0 | V96: 0 | W96: 0 | X96: 0 | Y96: =IF(COUNTA(J96:T96)=0, "", SUM(J96:T96)) -> 1
A97: 96 | B97: Ravindra Mohan Tambe 9665127299 | C97: MACT | D97: R001 | E97: R001-1096-SS-2025 | F97: =IF(D97="", "", _xlfn.XLOOKUP(D97, CLIENT_CODE!D:D, CLIENT_CODE!B:B, "")) -> Indusind General Insurance Co Ltd | G97: 2025212721 | H97: 45980 | I97: =IF(ISBLANK(H97), "", TEXT(H97, "mmm-yy")) -> Nov-25 | J97: 1 | K97: 0 | L97: 1 | M97: 0 | N97: 1 | O97: 0 | P97: 0 | Q97: 0 | R97: 1 | S97: 1 | T97: 0 | U97: 0 | V97: 0 | W97: 0 | X97: 0 | Y97: =IF(COUNTA(J97:T97)=0, "", SUM(J97:T97)) -> 5
A98: 97 | B98: Abdul Kabeer Abdul Rasheed | C98: MACT | D98: R001 | E98: R001-1097-SS-2025 | F98: =IF(D98="", "", _xlfn.XLOOKUP(D98, CLIENT_CODE!D:D, CLIENT_CODE!B:B, "")) -> Indusind General Insurance Co Ltd | G98: 2025209441 | H98: 45980 | I98: =IF(ISBLANK(H98), "", TEXT(H98, "mmm-yy")) -> Nov-25 | J98: 1 | K98: 0 | L98: 1 | M98: 0 | N98: 1 | O98: 0 | P98: 0 | Q98: 0 | R98: 1 | S98: 1 | T98: 0 | U98: 0 | V98: 0 | W98: 0 | X98: 0 | Y98: =IF(COUNTA(J98:T98)=0, "", SUM(J98:T98)) -> 5
A99: 98 | B99: NIVARUTI VINAYAK KANDHARE | C99: MACT | D99: R001 | E99: R001-1098-SS-2025 | F99: =IF(D99="", "", _xlfn.XLOOKUP(D99, CLIENT_CODE!D:D, CLIENT_CODE!B:B, "")) -> Indusind General Insurance Co Ltd | G99: 2025209731 | H99: 45980 | I99: =IF(ISBLANK(H99), "", TEXT(H99, "mmm-yy")) -> Nov-25 | J99: 1 | K99: 0 | L99: 1 | M99: 0 | N99: 1 | O99: 0 | P99: 0 | Q99: 0 | R99: 1 | S99: 1 | T99: 0 | U99: 0 | V99: 0 | W99: 0 | X99: 0 | Y99: =IF(COUNTA(J99:T99)=0, "", SUM(J99:T99)) -> 5
... A130: 129 | B130: Karim Hasan Shaikh | C130: MACT | D130: S002 | E130: S002-1129-SS-2025 | F130: =IF(D130="", "", _xlfn.XLOOKUP(D130, CLIENT_CODE!D:D, CLIENT_CODE!B:B, "")) -> SBI General Insurance Company Ltd | G130: 2752072 | H130: 45987 | I130: =IF(ISBLANK(H130), "", TEXT(H130, "mmm-yy")) -> Nov-25 | J130: 1 | K130: 0 | L130: 1 | M130: 0 | N130: 1 | O130: 0 | P130: 0 | Q130: 0 | R130: 1 | S130: 1 | T130: 0 | U130: 0 | V130: 0 | W130: 0 | X130: 0 | Y130: =IF(COUNTA(J130:T130)=0, "", SUM(J130:T130)) -> 5
A131: 130 | B131: NA | C131: MACT | D131: S002 | E131: S002-1130-SS-2025 | F131: =IF(D131="", "", _xlfn.XLOOKUP(D131, CLIENT_CODE!D:D, CLIENT_CODE!B:B, "")) -> SBI General Insurance Company Ltd | G131: 2312792 | H131: 45987 | I131: =IF(ISBLANK(H131), "", TEXT(H131, "mmm-yy")) -> Nov-25 | J131: 0 | K131: 0 | L131: 0 | M131: 0 | N131: 0 | O131: 0 | P131: 0 | Q131: 0 | R131: 0 | S131: 0 | T131: 0 | U131: 0 | V131: 1 | W131: 0 | X131: 0 | Y131: 1
A132: 131 | B132: Manoj Ramchandra Chalke | C132: MACT | D132: F001 | E132: F001-1131-SS-2025 | F132: =IF(D132="", "", _xlfn.XLOOKUP(D132, CLIENT_CODE!D:D, CLIENT_CODE!B:B, "")) -> Generali Central Insurance Company Limited | G132: MTP-N-2526-004746 | H132: 45987 | I132: =IF(ISBLANK(H132), "", TEXT(H132, "mmm-yy")) -> Nov-25 | J132: 1 | K132: 0 | L132: 1 | M132: 1 | N132: 1 | O132: 1 | P132: 1 | Q132: 0 | R132: 1 | S132: 1 | T132: 0 | U132: 0 | V132: 1 | W132: 0 | X132: 0 | Y132: =IF(COUNTA(J132:T132)=0, "", SUM(J132:T132)) -> 8
A133: 132 | B133: NA | C133: MACT | D133: F001 | E133: F001-1132-SS-2025 | F133: =IF(D133="", "", _xlfn.XLOOKUP(D133, CLIENT_CODE!D:D, CLIENT_CODE!B:B, "")) -> Generali Central Insurance Company Limited | G133: CM570910 | H133: 45987 | I133: =IF(ISBLANK(H133), "", TEXT(H133, "mmm-yy")) -> Nov-25 | J133: 0 | K133: 0 | L133: 0 | M133: 0 | N133: 0 | O133: 0 | P133: 0 | Q133: 0 | R133: 0 | S133: 1 | T133: 0 | U133: 0 | V133: 0 | W133: 0 | X133: 0 | Y133: =IF(COUNTA(J133:T133)=0, "", SUM(J133:T133)) -> 1
A134: 133 | B134: NA | C134: MACT | D134: R001 | E134: R001-1133-SS-2025 | F134: =IF(D134="", "", _xlfn.XLOOKUP(D134, CLIENT_CODE!D:D, CLIENT_CODE!B:B, "")) -> Indusind General Insurance Co Ltd | G134: 2023209914 | H134: 45989 | I134: =IF(ISBLANK(H134), "", TEXT(H134, "mmm-yy")) -> Nov-25 | J134: 0 | K134: 0 | L134: 0 | M134: 0 | N134: 0 | O134: 0 | P134: 0 | Q134: 0 | R134: 0 | S134: 1 | T134: 0 | U134: 0 | V134: 0 | W134: 0 | X134: 0 | Y134: =IF(COUNTA(J134:T134)=0, "", SUM(J134:T134)) -> 1
A135: 134 | B135: NA | C135: MACT | D135: R001 | E135: R001-1134-SS-2025 | F135: =IF(D135="", "", _xlfn.XLOOKUP(D135, CLIENT_CODE!D:D, CLIENT_CODE!B:B, "")) -> Indusind General Insurance Co Ltd | G135: 2025200081 | H135: 45989 | I135: =IF(ISBLANK(H135), "", TEXT(H135, "mmm-yy")) -> Nov-25 | J135: 0 | K135: 0 | L135: 0 | M135: 0 | N135: 0 | O135: 0 | P135: 0 | Q135: 0 | R135: 0 | S135: 1 | T135: 0 | U135: 0 | V135: 0 | W135: 0 | X135: 0 | Y135: =IF(COUNTA(J135:T135)=0, "", SUM(J135:T135)) -> 1
A136: 135 | B136: NA | C136: MACT | D136: R001 | E136: R001-1135-SS-2025 | F136: =IF(D136="", "", _xlfn.XLOOKUP(D136, CLIENT_CODE!D:D, CLIENT_CODE!B:B, "")) -> Indusind General Insurance Co Ltd | G136: 2024200689 | H136: 45989 | I136: =IF(ISBLANK(H136), "", TEXT(H136, "mmm-yy")) -> Nov-25 | J136: 0 | K136: 0 | L136: 0 | M136: 0 | N136: 0 | O136: 0 | P136: 0 | Q136: 0 | R136: 0 | S136: 1 | T136: 0 | U136: 0 | V136: 1 | W136: 0 | X136: 0 | Y136: =IF(COUNTA(J136:T136)=0, "", SUM(J136:T136)) -> 1
A137: 136 | B137: NA | C137: MACT | D137: R001 | E137: R001-1136-SS-2025 | F137: =IF(D137="", "", _xlfn.XLOOKUP(D137, CLIENT_CODE!D:D, CLIENT_CODE!B:B, "")) -> Indusind General Insurance Co Ltd | G137: 2024216011 | H137: 45989 | I137: =IF(ISBLANK(H137), "", TEXT(H137, "mmm-yy")) -> Nov-25 | J137: 1 | K137: 0 | L137: 1 | M137: 0 | N137: 1 | O137: 0 | P137: 0 | Q137: 0 | R137: 1 | S137: 1 | T137: 0 | U137: 0 | V137: 0 | W137: 0 | X137: 0 | Y137: =IF(COUNTA(J137:T137)=0, "", SUM(J137:T137)) -> 5
A138: 137 | B138: NA | C138: MACT | D138: R001 | E138: R001-1137-SS-2025 | F138: =IF(D138="", "", _xlfn.XLOOKUP(D138, CLIENT_CODE!D:D, CLIENT_CODE!B:B, "")) -> Indusind General Insurance Co Ltd | G138: 2025202308 | H138: 45989 | I138: =IF(ISBLANK(H138), "", TEXT(H138, "mmm-yy")) -> Nov-25 | J138: 0 | K138: 0 | L138: 0 | M138: 0 | N138: 0 | O138: 0 | P138: 0 | Q138: 0 | R138: 0 | S138: 1 | T138: 0 | U138: 0 | V138: 1 | W138: 0 | X138: 0 | Y138: =IF(COUNTA(J138:T138)=0, "", SUM(J138:T138)) -> 1
A139: 138 | B139: Sheikh Junaid Sheikh Nazir | C139: MACT | D139: S002 | E139: S002-1138-SS-2025 | F139: =IF(D139="", "", _xlfn.XLOOKUP(D139, CLIENT_CODE!D:D, CLIENT_CODE!B:B, "")) -> SBI General Insurance Company Ltd | G139: 2585893 | H139: 45989 | I139: =IF(ISBLANK(H139), "", TEXT(H139, "mmm-yy")) -> Nov-25 | J139: 1 | K139: 0 | L139: 0 | M139: 0 | N139: 1 | O139: 0 | P139: 0 | Q139: 0 | R139: 0 | S139: 0 | T139: 0 | U139: 0 | V139: 0 | W139: 0 | X139: 0 | Y139: =IF(COUNTA(J139:T139)=0, "", SUM(J139:T139)) -> 2
A140: 139 | B140: RAJU DADARAO BHAGAT | C140: MACT | D140: R001 | E140: R001-1139-SS-2025 | F140: =IF(D140="", "", _xlfn.XLOOKUP(D140, CLIENT_CODE!D:D, CLIENT_CODE!B:B, "")) -> Indusind General Insurance Co Ltd | G140: 2025213092 | H140: 45990 | I140: =IF(ISBLANK(H140), "", TEXT(H140, "mmm-yy")) -> Nov-25 | J140: 1 | K140: 0 | L140: 0 | M140: 0 | N140: 1 | O140: 0 | P140: 0 | Q140: 0 | R140: 0 | S140: 1 | T140: 0 | U140: 0 | V140: 0 | W140: 0 | X140: 0 | Y140: =IF(COUNTA(J140:T140)=0, "", SUM(J140:T140)) -> 3
A141: 140 | B141: NA | C141: MACT | D141: R001 | E141: R001-1140-SS-2025 | F141: =IF(D141="", "", _xlfn.XLOOKUP(D141, CLIENT_CODE!D:D, CLIENT_CODE!B:B, "")) -> Indusind General Insurance Co Ltd | G141: 2025204832 | H141: 45990 | I141: =IF(ISBLANK(H141), "", TEXT(H141, "mmm-yy")) -> Nov-25 | J141: 0 | K141: 0 | L141: 1 | M141: 0 | N141: 0 | O141: 0 | P141: 0 | Q141: 0 | R141: 0 | S141: 1 | T141: 0 | U141: 0 | V141: 0 | W141: 0 | X141: 0 | Y141: =IF(COUNTA(J141:T141)=0, "", SUM(J141:T141)) -> 2
A142: 141 | B142: Mohmad Javad Khan | C142: MACT | D142: R001 | E142: R001-1141-SS-2025 | F142: =IF(D142="", "", _xlfn.XLOOKUP(D142, CLIENT_CODE!D:D, CLIENT_CODE!B:B, "")) -> Indusind General Insurance Co Ltd | G142: 2025213146 | H142: 45990 | I142: =IF(ISBLANK(H142), "", TEXT(H142, "mmm-yy")) -> Nov-25 | J142: 1 | K142: 0 | L142: 1 | M142: 0 | N142: 1 | O142: 0 | P142: 0 | Q142: 0 | R142: 1 | S142: 1 | T142: 0 | U142: 0 | V142: 0 | W142: 0 | X142: 0 | Y142: =IF(COUNTA(J142:T142)=0, "", SUM(J142:T142)) -> 5
A143: 142 | B143: PANDURANG GANPAT SHIGVAN | C143: MACT | D143: R001 | E143: R001-1142-SS-2025 | F143: =IF(D143="", "", _xlfn.XLOOKUP(D143, CLIENT_CODE!D:D, CLIENT_CODE!B:B, "")) -> Indusind General Insurance Co Ltd | G143: 2025213359 | H143: 45992 | I143: =IF(ISBLANK(H143), "", TEXT(H143, "mmm-yy")) -> Dec-25 | J143: 1 | K143: 0 | L143: 1 | M143: 0 | N143: 1 | O143: 0 | P143: 0 | Q143: 0 | R143: 1 | S143: 1 | T143: 0 | U143: 0 | V143: 0 | W143: 0 | X143: 0 | Y143: =IF(COUNTA(J143:T143)=0, "", SUM(J143:T143)) -> 5
A144: 143 | B144: Dagdaji Laxmanrao Shinde | C144: MACT | D144: S002 | E144: S002-1143-SS-2025 | F144: =IF(D144="", "", _xlfn.XLOOKUP(D144, CLIENT_CODE!D:D, CLIENT_CODE!B:B, "")) -> SBI General Insurance Company Ltd | G144: 2752851 | H144: 45992 | I144: =IF(ISBLANK(H144), "", TEXT(H144, "mmm-yy")) -> Dec-25 | J144: 1 | K144: 0 | L144: 1 | M144: 0 | N144: 1 | O144: 0 | P144: 0 | Q144: 0 | R144: 1 | S144: 1 | T144: 0 | U144: 0 | W144: 0 | X144: 0 | Y144: =IF(COUNTA(J144:T144)=0, "", SUM(J144:T144)) -> 5
...

Sheet Ganesh
A1: S | N | B1: Cliam Number | C1: Client Name | D1: INSURED/Back | E1: Insured | F1: 134 NOTICE/Backend | G1: 134 NOTICE | H1: Claimant / Backend | I1: Claimant | J1: Income/Backend | K1: Income | L1: DRIVER/Backend | M1: Driver | N1: DL/Backend | O1: DL | P1: RC/Backend | Q1: RC | R1: PERMIT/Backend | S1: PERMIT | T1: SPOT/Backend | U1: SPOT | V1: COURT/Backend | W1: COURT | X1: NOTICE/Backend | Y1: NOTICE | Z1: RTI/Backend | AA1: RTI | AB1: Hospital/Backend | AC1: Hospital | AD1: Total
A2: 1 | B2: {=_xlfn._xlws.FILTER(MIS_Backend_Data!B:B, (MIS_Backend_Data!O:O="WIP") + (MIS_Backend_Data!O:O="Pending for CS"))} -> C2264191100006-00 | C2: {=_xlfn._xlws.FILTER(MIS_Backend_Data!#REF!, (MIS_Backend_Data!O:O="WIP") + (MIS_Backend_Data!O:O="Pending for CS"), "")} -> #REF! | D2: =_xlfn.XLOOKUP(B2,CRN!G:G,CRN!J:J,"") -> 1 | E2: =IF(D2=0,0,_xlfn.XLOOKUP(C2,CLIENT_CODE!B:B,CLIENT_CODE!F:F,0)) -> #REF! | F2: =_xlfn.XLOOKUP(B2,CRN!G:G,CRN!K:K,"") -> 0 | G2: =IF(F2=0,0,_xlfn.XLOOKUP(C2,CLIENT_CODE!B:B,CLIENT_CODE!G:G,0)) -> 0 | H2: =_xlfn.XLOOKUP(B2,CRN!G:G,CRN!L:L,"") -> 1 | I2: =IF(H2=0,0,_xlfn.XLOOKUP(C2,CLIENT_CODE!B:B,CLIENT_CODE!H:H,0)) -> #REF! | J2: =_xlfn.XLOOKUP(B2,CRN!G:G,CRN!M:M,"") -> 0 | K2: =IF(J2=0,0,_xlfn.XLOOKUP(C2,CLIENT_CODE!B:B,CLIENT_CODE!I:I,0)) -> 0 | L2: =_xlfn.XLOOKUP(B2,CRN!G:G,CRN!N:N,"") -> 1 | M2: =IF(L2=0,0,_xlfn.XLOOKUP(C2,CLIENT_CODE!B:B,CLIENT_CODE!J:J,0)) -> #REF! | N2: =_xlfn.XLOOKUP(B2,CRN!G:G,CRN!O:O,"") -> 0 | O2: =IF(N2=0,0,_xlfn.XLOOKUP(C2,CLIENT_CODE!B:B,CLIENT_CODE!K:K,0)) -> 0 | P2: =_xlfn.XLOOKUP(B2,CRN!G:G,CRN!P:P,"") -> 0 | Q2: =IF(P2=0,0,_xlfn.XLOOKUP(C2,CLIENT_CODE!B:B,CLIENT_CODE!L:L,0)) -> 0 | R2: =_xlfn.XLOOKUP(B2,CRN!G:G,CRN!Q:Q,"") -> 0 | S2: =IF(R2=0,0,_xlfn.XLOOKUP(C2,CLIENT_CODE!B:B,CLIENT_CODE!M:M,0)) -> 0 | T2: =_xlfn.XLOOKUP(B2,CRN!G:G,CRN!R:R,"") -> 1 | U2: =IF(T2=0,0,_xlfn.XLOOKUP(C2,CLIENT_CODE!B:B,CLIENT_CODE!N:N,0)) -> #REF! | V2: =_xlfn.XLOOKUP(B2,CRN!G:G,CRN!S:S,"") -> 1 | W2: =IF(V2=0,0,_xlfn.XLOOKUP(C2,CLIENT_CODE!B:B,CLIENT_CODE!O:O,0)) -> #REF! | X2: =_xlfn.XLOOKUP(B2,CRN!G:G,CRN!T:T,"") -> 0 | Y2: =IF(X2=0,0,_xlfn.XLOOKUP(C2,CLIENT_CODE!B:B,CLIENT_CODE!P:P,0)) -> 0 | Z2: =_xlfn.XLOOKUP(B2,CRN!G:G,CRN!U:U,"") -> 0 | AA2: =IF(X2=0,0,_xlfn.XLOOKUP(C2,CLIENT_CODE!B:B,CLIENT_CODE!P:P,0)) -> 0 | AB2: =_xlfn.XLOOKUP(B2,CRN!G:G,CRN!V:V,"") -> 0 | AC2: =IF(AB2=0,0,_xlfn.XLOOKUP(C2,CLIENT_CODE!B:B,CLIENT_CODE!R:R,0)) -> 0 | AD2: =SUM(E2,G2,I2,K2,M2,O2,Q2,S2,U2,W2,Y2,AA2,AC2,) -> #REF!
A3: 2 | B3: 2025209769 | E3: =IF(D3=0,0,_xlfn.XLOOKUP(C3,CLIENT_CODE!B:B,CLIENT_CODE!F:F,0)) -> 0 | F3: =_xlfn.XLOOKUP(B3,CRN!G:G,CRN!K:K,"") -> 0 | G3: =IF(F3=0,0,_xlfn.XLOOKUP(C3,CLIENT_CODE!B:B,CLIENT_CODE!G:G,0)) -> 0 | H3: =_xlfn.XLOOKUP(B3,CRN!G:G,CRN!L:L,"") -> 1 | I3: =IF(H3=0,0,_xlfn.XLOOKUP(C3,CLIENT_CODE!B:B,CLIENT_CODE!H:H,0)) -> 0 | J3: =_xlfn.XLOOKUP(B3,CRN!G:G,CRN!M:M,"") -> 0 | K3: =IF(J3=0,0,_xlfn.XLOOKUP(C3,CLIENT_CODE!B:B,CLIENT_CODE!I:I,0)) -> 0 | L3: =_xlfn.XLOOKUP(B3,CRN!G:G,CRN!N:N,"") -> 1 | M3: =IF(L3=0,0,_xlfn.XLOOKUP(C3,CLIENT_CODE!B:B,CLIENT_CODE!J:J,0)) -> 0 | N3: =_xlfn.XLOOKUP(B3,CRN!G:G,CRN!O:O,"") -> 0 | O3: =IF(N3=0,0,_xlfn.XLOOKUP(C3,CLIENT_CODE!B:B,CLIENT_CODE!K:K,0)) -> 0 | P3: =_xlfn.XLOOKUP(B3,CRN!G:G,CRN!P:P,"") -> 0 | Q3: =IF(P3=0,0,_xlfn.XLOOKUP(C3,CLIENT_CODE!B:B,CLIENT_CODE!L:L,0)) -> 0 | R3: =_xlfn.XLOOKUP(B3,CRN!G:G,CRN!Q:Q,"") -> 0 | S3: =IF(R3=0,0,_xlfn.XLOOKUP(C3,CLIENT_CODE!B:B,CLIENT_CODE!M:M,0)) -> 0 | T3: =_xlfn.XLOOKUP(B3,CRN!G:G,CRN!R:R,"") -> 1 | U3: =IF(T3=0,0,_xlfn.XLOOKUP(C3,CLIENT_CODE!B:B,CLIENT_CODE!N:N,0)) -> 0 | V3: =_xlfn.XLOOKUP(B3,CRN!G:G,CRN!S:S,"") -> 1 | W3: =IF(V3=0,0,_xlfn.XLOOKUP(C3,CLIENT_CODE!B:B,CLIENT_CODE!O:O,0)) -> 0 | X3: =_xlfn.XLOOKUP(B3,CRN!G:G,CRN!T:T,"") -> 0 | Y3: =IF(X3=0,0,_xlfn.XLOOKUP(C3,CLIENT_CODE!B:B,CLIENT_CODE!P:P,0)) -> 0 | Z3: =_xlfn.XLOOKUP(B3,CRN!G:G,CRN!U:U,"") -> 0 | AA3: =IF(X3=0,0,_xlfn.XLOOKUP(C3,CLIENT_CODE!B:B,CLIENT_CODE!P:P,0)) -> 0 | AB3: =_xlfn.XLOOKUP(B3,CRN!G:G,CRN!V:V,"") -> 0 | AC3: =IF(AB3=0,0,_xlfn.XLOOKUP(C3,CLIENT_CODE!B:B,CLIENT_CODE!R:R,0)) -> 0 | AD3: =SUM(E3,G3,I3,K3,M3,O3,Q3,S3,U3,W3,Y3,AA3,AC3,) -> 0
A4: 3 | B4: CM889835 | E4: =IF(D4=0,0,_xlfn.XLOOKUP(C4,CLIENT_CODE!B:B,CLIENT_CODE!F:F,0)) -> 0 | F4: =_xlfn.XLOOKUP(B4,CRN!G:G,CRN!K:K,"") -> 0 | G4: =IF(F4=0,0,_xlfn.XLOOKUP(C4,CLIENT_CODE!B:B,CLIENT_CODE!G:G,0)) -> 0 | H4: =_xlfn.XLOOKUP(B4,CRN!G:G,CRN!L:L,"") -> 1 | I4: =IF(H4=0,0,_xlfn.XLOOKUP(C4,CLIENT_CODE!B:B,CLIENT_CODE!H:H,0)) -> 0 | J4: =_xlfn.XLOOKUP(B4,CRN!G:G,CRN!M:M,"") -> 0 | K4: =IF(J4=0,0,_xlfn.XLOOKUP(C4,CLIENT_CODE!B:B,CLIENT_CODE!I:I,0)) -> 0 | L4: =_xlfn.XLOOKUP(B4,CRN!G:G,CRN!N:N,"") -> 0 | M4: =IF(L4=0,0,_xlfn.XLOOKUP(C4,CLIENT_CODE!B:B,CLIENT_CODE!J:J,0)) -> 0 | N4: =_xlfn.XLOOKUP(B4,CRN!G:G,CRN!O:O,"") -> 0 | O4: =IF(N4=0,0,_xlfn.XLOOKUP(C4,CLIENT_CODE!B:B,CLIENT_CODE!K:K,0)) -> 0 | P4: =_xlfn.XLOOKUP(B4,CRN!G:G,CRN!P:P,"") -> 0 | Q4: =IF(P4=0,0,_xlfn.XLOOKUP(C4,CLIENT_CODE!B:B,CLIENT_CODE!L:L,0)) -> 0 | R4: =_xlfn.XLOOKUP(B4,CRN!G:G,CRN!Q:Q,"") -> 0 | S4: =IF(R4=0,0,_xlfn.XLOOKUP(C4,CLIENT_CODE!B:B,CLIENT_CODE!M:M,0)) -> 0 | T4: =_xlfn.XLOOKUP(B4,CRN!G:G,CRN!R:R,"") -> 1 | U4: =IF(T4=0,0,_xlfn.XLOOKUP(C4,CLIENT_CODE!B:B,CLIENT_CODE!N:N,0)) -> 0 | V4: =_xlfn.XLOOKUP(B4,CRN!G:G,CRN!S:S,"") -> 1 | W4: =IF(V4=0,0,_xlfn.XLOOKUP(C4,CLIENT_CODE!B:B,CLIENT_CODE!O:O,0)) -> 0 | X4: =_xlfn.XLOOKUP(B4,CRN!G:G,CRN!T:T,"") -> 0 | Y4: =IF(X4=0,0,_xlfn.XLOOKUP(C4,CLIENT_CODE!B:B,CLIENT_CODE!P:P,0)) -> 0 | Z4: =_xlfn.XLOOKUP(B4,CRN!G:G,CRN!U:U,"") -> 0 | AA4: =IF(X4=0,0,_xlfn.XLOOKUP(C4,CLIENT_CODE!B:B,CLIENT_CODE!P:P,0)) -> 0 | AB4: =_xlfn.XLOOKUP(B4,CRN!G:G,CRN!V:V,"") -> 0 | AC4: =IF(AB4=0,0,_xlfn.XLOOKUP(C4,CLIENT_CODE!B:B,CLIENT_CODE!R:R,0)) -> 0 | AD4: =SUM(E4,G4,I4,K4,M4,O4,Q4,S4,U4,W4,Y4,AA4,AC4,) -> 0
A5: 4 | B5: 2025200573 | E5: =IF(D5=0,0,_xlfn.XLOOKUP(C5,CLIENT_CODE!B:B,CLIENT_CODE!F:F,0)) -> 0 | F5: =_xlfn.XLOOKUP(B5,CRN!G:G,CRN!K:K,"") -> 0 | G5: =IF(F5=0,0,_xlfn.XLOOKUP(C5,CLIENT_CODE!B:B,CLIENT_CODE!G:G,0)) -> 0 | H5: =_xlfn.XLOOKUP(B5,CRN!G:G,CRN!L:L,"") -> 1 | I5: =IF(H5=0,0,_xlfn.XLOOKUP(C5,CLIENT_CODE!B:B,CLIENT_CODE!H:H,0)) -> 0 | J5: =_xlfn.XLOOKUP(B5,CRN!G:G,CRN!M:M,"") -> 0 | K5: =IF(J5=0,0,_xlfn.XLOOKUP(C5,CLIENT_CODE!B:B,CLIENT_CODE!I:I,0)) -> 0 | L5: =_xlfn.XLOOKUP(B5,CRN!G:G,CRN!N:N,"") -> 1 | M5: =IF(L5=0,0,_xlfn.XLOOKUP(C5,CLIENT_CODE!B:B,CLIENT_CODE!J:J,0)) -> 0 | N5: =_xlfn.XLOOKUP(B5,CRN!G:G,CRN!O:O,"") -> 0 | O5: =IF(N5=0,0,_xlfn.XLOOKUP(C5,CLIENT_CODE!B:B,CLIENT_CODE!K:K,0)) -> 0 | P5: =_xlfn.XLOOKUP(B5,CRN!G:G,CRN!P:P,"") -> 0 | Q5: =IF(P5=0,0,_xlfn.XLOOKUP(C5,CLIENT_CODE!B:B,CLIENT_CODE!L:L,0)) -> 0 | R5: =_xlfn.XLOOKUP(B5,CRN!G:G,CRN!Q:Q,"") -> 0 | S5: =IF(R5=0,0,_xlfn.XLOOKUP(C5,CLIENT_CODE!B:B,CLIENT_CODE!M:M,0)) -> 0 | T5: =_xlfn.XLOOKUP(B5,CRN!G:G,CRN!R:R,"") -> 1 | U5: =IF(T5=0,0,_xlfn.XLOOKUP(C5,CLIENT_CODE!B:B,CLIENT_CODE!N:N,0)) -> 0 | V5: =_xlfn.XLOOKUP(B5,CRN!G:G,CRN!S:S,"") -> 1 | W5: =IF(V5=0,0,_xlfn.XLOOKUP(C5,CLIENT_CODE!B:B,CLIENT_CODE!O:O,0)) -> 0 | X5: =_xlfn.XLOOKUP(B5,CRN!G:G,CRN!T:T,"") -> 0 | Y5: =IF(X5=0,0,_xlfn.XLOOKUP(C5,CLIENT_CODE!B:B,CLIENT_CODE!P:P,0)) -> 0 | Z5: =_xlfn.XLOOKUP(B5,CRN!G:G,CRN!U:U,"") -> 0 | AA5: =IF(X5=0,0,_xlfn.XLOOKUP(C5,CLIENT_CODE!B:B,CLIENT_CODE!P:P,0)) -> 0 | AB5: =_xlfn.XLOOKUP(B5,CRN!G:G,CRN!V:V,"") -> 0 | AC5: =IF(AB5=0,0,_xlfn.XLOOKUP(C5,CLIENT_CODE!B:B,CLIENT_CODE!R:R,0)) -> 0 | AD5: =SUM(E5,G5,I5,K5,M5,O5,Q5,S5,U5,W5,Y5,AA5,AC5,) -> 0
A6: 5 | B6: 2025211134 | E6: =IF(D6=0,0,_xlfn.XLOOKUP(C6,CLIENT_CODE!B:B,CLIENT_CODE!F:F,0)) -> 0 | F6: =_xlfn.XLOOKUP(B6,CRN!G:G,CRN!K:K,"") -> 0 | G6: =IF(F6=0,0,_xlfn.XLOOKUP(C6,CLIENT_CODE!B:B,CLIENT_CODE!G:G,0)) -> 0 | H6: =_xlfn.XLOOKUP(B6,CRN!G:G,CRN!L:L,"") -> 1 | I6: =IF(H6=0,0,_xlfn.XLOOKUP(C6,CLIENT_CODE!B:B,CLIENT_CODE!H:H,0)) -> 0 | J6: =_xlfn.XLOOKUP(B6,CRN!G:G,CRN!M:M,"") -> 0 | K6: =IF(J6=0,0,_xlfn.XLOOKUP(C6,CLIENT_CODE!B:B,CLIENT_CODE!I:I,0)) -> 0 | L6: =_xlfn.XLOOKUP(B6,CRN!G:G,CRN!N:N,"") -> 1 | M6: =IF(L6=0,0,_xlfn.XLOOKUP(C6,CLIENT_CODE!B:B,CLIENT_CODE!J:J,0)) -> 0 | N6: =_xlfn.XLOOKUP(B6,CRN!G:G,CRN!O:O,"") -> 0 | O6: =IF(N6=0,0,_xlfn.XLOOKUP(C6,CLIENT_CODE!B:B,CLIENT_CODE!K:K,0)) -> 0 | P6: =_xlfn.XLOOKUP(B6,CRN!G:G,CRN!P:P,"") -> 0 | Q6: =IF(P6=0,0,_xlfn.XLOOKUP(C6,CLIENT_CODE!B:B,CLIENT_CODE!L:L,0)) -> 0 | R6: =_xlfn.XLOOKUP(B6,CRN!G:G,CRN!Q:Q,"") -> 0 | S6: =IF(R6=0,0,_xlfn.XLOOKUP(C6,CLIENT_CODE!B:B,CLIENT_CODE!M:M,0)) -> 0 | T6: =_xlfn.XLOOKUP(B6,CRN!G:G,CRN!R:R,"") -> 1 | U6: =IF(T6=0,0,_xlfn.XLOOKUP(C6,CLIENT_CODE!B:B,CLIENT_CODE!N:N,0)) -> 0 | V6: =_xlfn.XLOOKUP(B6,CRN!G:G,CRN!S:S,"") -> 1 | W6: =IF(V6=0,0,_xlfn.XLOOKUP(C6,CLIENT_CODE!B:B,CLIENT_CODE!O:O,0)) -> 0 | X6: =_xlfn.XLOOKUP(B6,CRN!G:G,CRN!T:T,"") -> 0 | Y6: =IF(X6=0,0,_xlfn.XLOOKUP(C6,CLIENT_CODE!B:B,CLIENT_CODE!P:P,0)) -> 0 | Z6: =_xlfn.XLOOKUP(B6,CRN!G:G,CRN!U:U,"") -> 0 | AA6: =IF(X6=0,0,_xlfn.XLOOKUP(C6,CLIENT_CODE!B:B,CLIENT_CODE!P:P,0)) -> 0 | AB6: =_xlfn.XLOOKUP(B6,CRN!G:G,CRN!V:V,"") -> 0 | AC6: =IF(AB6=0,0,_xlfn.XLOOKUP(C6,CLIENT_CODE!B:B,CLIENT_CODE!R:R,0)) -> 0 | AD6: =SUM(E6,G6,I6,K6,M6,O6,Q6,S6,U6,W6,Y6,AA6,AC6,) -> 0
A7: 6 | B7: 2025211454 | E7: =IF(D7=0,0,_xlfn.XLOOKUP(C7,CLIENT_CODE!B:B,CLIENT_CODE!F:F,0)) -> 0 | F7: =_xlfn.XLOOKUP(B7,CRN!G:G,CRN!K:K,"") -> 0 | G7: =IF(F7=0,0,_xlfn.XLOOKUP(C7,CLIENT_CODE!B:B,CLIENT_CODE!G:G,0)) -> 0 | H7: =_xlfn.XLOOKUP(B7,CRN!G:G,CRN!L:L,"") -> 1 | I7: =IF(H7=0,0,_xlfn.XLOOKUP(C7,CLIENT_CODE!B:B,CLIENT_CODE!H:H,0)) -> 0 | J7: =_xlfn.XLOOKUP(B7,CRN!G:G,CRN!M:M,"") -> 0 | K7: =IF(J7=0,0,_xlfn.XLOOKUP(C7,CLIENT_CODE!B:B,CLIENT_CODE!I:I,0)) -> 0 | L7: =_xlfn.XLOOKUP(B7,CRN!G:G,CRN!N:N,"") -> 1 | M7: =IF(L7=0,0,_xlfn.XLOOKUP(C7,CLIENT_CODE!B:B,CLIENT_CODE!J:J,0)) -> 0 | N7: =_xlfn.XLOOKUP(B7,CRN!G:G,CRN!O:O,"") -> 0 | O7: =IF(N7=0,0,_xlfn.XLOOKUP(C7,CLIENT_CODE!B:B,CLIENT_CODE!K:K,0)) -> 0 | P7: =_xlfn.XLOOKUP(B7,CRN!G:G,CRN!P:P,"") -> 0 | Q7: =IF(P7=0,0,_xlfn.XLOOKUP(C7,CLIENT_CODE!B:B,CLIENT_CODE!L:L,0)) -> 0 | R7: =_xlfn.XLOOKUP(B7,CRN!G:G,CRN!Q:Q,"") -> 0 | S7: =IF(R7=0,0,_xlfn.XLOOKUP(C7,CLIENT_CODE!B:B,CLIENT_CODE!M:M,0)) -> 0 | T7: =_xlfn.XLOOKUP(B7,CRN!G:G,CRN!R:R,"") -> 1 | U7: =IF(T7=0,0,_xlfn.XLOOKUP(C7,CLIENT_CODE!B:B,CLIENT_CODE!N:N,0)) -> 0 | V7: =_xlfn.XLOOKUP(B7,CRN!G:G,CRN!S:S,"") -> 1 | W7: =IF(V7=0,0,_xlfn.XLOOKUP(C7,CLIENT_CODE!B:B,CLIENT_CODE!O:O,0)) -> 0 | X7: =_xlfn.XLOOKUP(B7,CRN!G:G,CRN!T:T,"") -> 0 | Y7: =IF(X7=0,0,_xlfn.XLOOKUP(C7,CLIENT_CODE!B:B,CLIENT_CODE!P:P,0)) -> 0 | Z7: =_xlfn.XLOOKUP(B7,CRN!G:G,CRN!U:U,"") -> 0 | AA7: =IF(X7=0,0,_xlfn.XLOOKUP(C7,CLIENT_CODE!B:B,CLIENT_CODE!P:P,0)) -> 0 | AB7: =_xlfn.XLOOKUP(B7,CRN!G:G,CRN!V:V,"") -> 0 | AC7: =IF(AB7=0,0,_xlfn.XLOOKUP(C7,CLIENT_CODE!B:B,CLIENT_CODE!R:R,0)) -> 0 | AD7: =SUM(E7,G7,I7,K7,M7,O7,Q7,S7,U7,W7,Y7,AA7,AC7,) -> 0
A8: 7 | B8: 2025211475 | E8: =IF(D8=0,0,_xlfn.XLOOKUP(C8,CLIENT_CODE!B:B,CLIENT_CODE!F:F,0)) -> 0 | F8: =_xlfn.XLOOKUP(B8,CRN!G:G,CRN!K:K,"") -> 0 | G8: =IF(F8=0,0,_xlfn.XLOOKUP(C8,CLIENT_CODE!B:B,CLIENT_CODE!G:G,0)) -> 0 | H8: =_xlfn.XLOOKUP(B8,CRN!G:G,CRN!L:L,"") -> 1 | I8: =IF(H8=0,0,_xlfn.XLOOKUP(C8,CLIENT_CODE!B:B,CLIENT_CODE!H:H,0)) -> 0 | J8: =_xlfn.XLOOKUP(B8,CRN!G:G,CRN!M:M,"") -> 0 | K8: =IF(J8=0,0,_xlfn.XLOOKUP(C8,CLIENT_CODE!B:B,CLIENT_CODE!I:I,0)) -> 0 | L8: =_xlfn.XLOOKUP(B8,CRN!G:G,CRN!N:N,"") -> 1 | M8: =IF(L8=0,0,_xlfn.XLOOKUP(C8,CLIENT_CODE!B:B,CLIENT_CODE!J:J,0)) -> 0 | N8: =_xlfn.XLOOKUP(B8,CRN!G:G,CRN!O:O,"") -> 0 | O8: =IF(N8=0,0,_xlfn.XLOOKUP(C8,CLIENT_CODE!B:B,CLIENT_CODE!K:K,0)) -> 0 | P8: =_xlfn.XLOOKUP(B8,CRN!G:G,CRN!P:P,"") -> 0 | Q8: =IF(P8=0,0,_xlfn.XLOOKUP(C8,CLIENT_CODE!B:B,CLIENT_CODE!L:L,0)) -> 0 | R8: =_xlfn.XLOOKUP(B8,CRN!G:G,CRN!Q:Q,"") -> 0 | S8: =IF(R8=0,0,_xlfn.XLOOKUP(C8,CLIENT_CODE!B:B,CLIENT_CODE!M:M,0)) -> 0 | T8: =_xlfn.XLOOKUP(B8,CRN!G:G,CRN!R:R,"") -> 1 | U8: =IF(T8=0,0,_xlfn.XLOOKUP(C8,CLIENT_CODE!B:B,CLIENT_CODE!N:N,0)) -> 0 | V8: =_xlfn.XLOOKUP(B8,CRN!G:G,CRN!S:S,"") -> 1 | W8: =IF(V8=0,0,_xlfn.XLOOKUP(C8,CLIENT_CODE!B:B,CLIENT_CODE!O:O,0)) -> 0 | X8: =_xlfn.XLOOKUP(B8,CRN!G:G,CRN!T:T,"") -> 0 | Y8: =IF(X8=0,0,_xlfn.XLOOKUP(C8,CLIENT_CODE!B:B,CLIENT_CODE!P:P,0)) -> 0 | Z8: =_xlfn.XLOOKUP(B8,CRN!G:G,CRN!U:U,"") -> 0 | AA8: =IF(X8=0,0,_xlfn.XLOOKUP(C8,CLIENT_CODE!B:B,CLIENT_CODE!P:P,0)) -> 0 | AB8: =_xlfn.XLOOKUP(B8,CRN!G:G,CRN!V:V,"") -> 0 | AC8: =IF(AB8=0,0,_xlfn.XLOOKUP(C8,CLIENT_CODE!B:B,CLIENT_CODE!R:R,0)) -> 0 | AD8: =SUM(E8,G8,I8,K8,M8,O8,Q8,S8,U8,W8,Y8,AA8,AC8,) -> 0
A9: 8 | B9: MTP-N-2526-004127 | E9: =IF(D9=0,0,_xlfn.XLOOKUP(C9,CLIENT_CODE!B:B,CLIENT_CODE!F:F,0)) -> 0 | F9: =_xlfn.XLOOKUP(B9,CRN!G:G,CRN!K:K,"") -> 0 | G9: =IF(F9=0,0,_xlfn.XLOOKUP(C9,CLIENT_CODE!B:B,CLIENT_CODE!G:G,0)) -> 0 | H9: =_xlfn.XLOOKUP(B9,CRN!G:G,CRN!L:L,"") -> 1 | I9: =IF(H9=0,0,_xlfn.XLOOKUP(C9,CLIENT_CODE!B:B,CLIENT_CODE!H:H,0)) -> 0 | J9: =_xlfn.XLOOKUP(B9,CRN!G:G,CRN!M:M,"") -> 1 | K9: =IF(J9=0,0,_xlfn.XLOOKUP(C9,CLIENT_CODE!B:B,CLIENT_CODE!I:I,0)) -> 0 | L9: =_xlfn.XLOOKUP(B9,CRN!G:G,CRN!N:N,"") -> 1 | M9: =IF(L9=0,0,_xlfn.XLOOKUP(C9,CLIENT_CODE!B:B,CLIENT_CODE!J:J,0)) -> 0 | N9: =_xlfn.XLOOKUP(B9,CRN!G:G,CRN!O:O,"") -> 1 | O9: =IF(N9=0,0,_xlfn.XLOOKUP(C9,CLIENT_CODE!B:B,CLIENT_CODE!K:K,0)) -> 0 | P9: =_xlfn.XLOOKUP(B9,CRN!G:G,CRN!P:P,"") -> 1 | Q9: =IF(P9=0,0,_xlfn.XLOOKUP(C9,CLIENT_CODE!B:B,CLIENT_CODE!L:L,0)) -> 0 | R9: =_xlfn.XLOOKUP(B9,CRN!G:G,CRN!Q:Q,"") -> 0 | S9: =IF(R9=0,0,_xlfn.XLOOKUP(C9,CLIENT_CODE!B:B,CLIENT_CODE!M:M,0)) -> 0 | T9: =_xlfn.XLOOKUP(B9,CRN!G:G,CRN!R:R,"") -> 1 | U9: =IF(T9=0,0,_xlfn.XLOOKUP(C9,CLIENT_CODE!B:B,CLIENT_CODE!N:N,0)) -> 0 | V9: =_xlfn.XLOOKUP(B9,CRN!G:G,CRN!S:S,"") -> 1 | W9: =IF(V9=0,0,_xlfn.XLOOKUP(C9,CLIENT_CODE!B:B,CLIENT_CODE!O:O,0)) -> 0 | X9: =_xlfn.XLOOKUP(B9,CRN!G:G,CRN!T:T,"") -> 0 | Y9: =IF(X9=0,0,_xlfn.XLOOKUP(C9,CLIENT_CODE!B:B,CLIENT_CODE!P:P,0)) -> 0 | Z9: =_xlfn.XLOOKUP(B9,CRN!G:G,CRN!U:U,"") -> 0 | AA9: =IF(X9=0,0,_xlfn.XLOOKUP(C9,CLIENT_CODE!B:B,CLIENT_CODE!P:P,0)) -> 0 | AB9: =_xlfn.XLOOKUP(B9,CRN!G:G,CRN!V:V,"") -> 1 | AC9: =IF(AB9=0,0,_xlfn.XLOOKUP(C9,CLIENT_CODE!B:B,CLIENT_CODE!R:R,0)) -> 0 | AD9: =SUM(E9,G9,I9,K9,M9,O9,Q9,S9,U9,W9,Y9,AA9,AC9,) -> 0
A10: 9 | B10: 2025212058 | E10: =IF(D10=0,0,_xlfn.XLOOKUP(C10,CLIENT_CODE!B:B,CLIENT_CODE!F:F,0)) -> 0 | F10: =_xlfn.XLOOKUP(B10,CRN!G:G,CRN!K:K,"") -> 0 | G10: =IF(F10=0,0,_xlfn.XLOOKUP(C10,CLIENT_CODE!B:B,CLIENT_CODE!G:G,0)) -> 0 | H10: =_xlfn.XLOOKUP(B10,CRN!G:G,CRN!L:L,"") -> 1 | I10: =IF(H10=0,0,_xlfn.XLOOKUP(C10,CLIENT_CODE!B:B,CLIENT_CODE!H:H,0)) -> 0 | J10: =_xlfn.XLOOKUP(B10,CRN!G:G,CRN!M:M,"") -> 0 | K10: =IF(J10=0,0,_xlfn.XLOOKUP(C10,CLIENT_CODE!B:B,CLIENT_CODE!I:I,0)) -> 0 | L10: =_xlfn.XLOOKUP(B10,CRN!G:G,CRN!N:N,"") -> 1 | M10: =IF(L10=0,0,_xlfn.XLOOKUP(C10,CLIENT_CODE!B:B,CLIENT_CODE!J:J,0)) -> 0 | N10: =_xlfn.XLOOKUP(B10,CRN!G:G,CRN!O:O,"") -> 0 | O10: =IF(N10=0,0,_xlfn.XLOOKUP(C10,CLIENT_CODE!B:B,CLIENT_CODE!K:K,0)) -> 0 | P10: =_xlfn.XLOOKUP(B10,CRN!G:G,CRN!P:P,"") -> 0 | Q10: =IF(P10=0,0,_xlfn.XLOOKUP(C10,CLIENT_CODE!B:B,CLIENT_CODE!L:L,0)) -> 0 | R10: =_xlfn.XLOOKUP(B10,CRN!G:G,CRN!Q:Q,"") -> 0 | S10: =IF(R10=0,0,_xlfn.XLOOKUP(C10,CLIENT_CODE!B:B,CLIENT_CODE!M:M,0)) -> 0 | T10: =_xlfn.XLOOKUP(B10,CRN!G:G,CRN!R:R,"") -> 1 | U10: =IF(T10=0,0,_xlfn.XLOOKUP(C10,CLIENT_CODE!B:B,CLIENT_CODE!N:N,0)) -> 0 | V10: =_xlfn.XLOOKUP(B10,CRN!G:G,CRN!S:S,"") -> 1 | W10: =IF(V10=0,0,_xlfn.XLOOKUP(C10,CLIENT_CODE!B:B,CLIENT_CODE!O:O,0)) -> 0 | X10: =_xlfn.XLOOKUP(B10,CRN!G:G,CRN!T:T,"") -> 0 | Y10: =IF(X10=0,0,_xlfn.XLOOKUP(C10,CLIENT_CODE!B:B,CLIENT_CODE!P:P,0)) -> 0 | Z10: =_xlfn.XLOOKUP(B10,CRN!G:G,CRN!U:U,"") -> 0 | AA10: =IF(X10=0,0,_xlfn.XLOOKUP(C10,CLIENT_CODE!B:B,CLIENT_CODE!P:P,0)) -> 0 | AB10: =_xlfn.XLOOKUP(B10,CRN!G:G,CRN!V:V,"") -> 0 | AC10: =IF(AB10=0,0,_xlfn.XLOOKUP(C10,CLIENT_CODE!B:B,CLIENT_CODE!R:R,0)) -> 0 | AD10: =SUM(E10,G10,I10,K10,M10,O10,Q10,S10,U10,W10,Y10,AA10,AC10,) -> 0
A11: 10 | B11: 2025212055 | E11: =IF(D11=0,0,_xlfn.XLOOKUP(C11,CLIENT_CODE!B:B,CLIENT_CODE!F:F,0)) -> 0 | F11: =_xlfn.XLOOKUP(B11,CRN!G:G,CRN!K:K,"") -> 0 | G11: =IF(F11=0,0,_xlfn.XLOOKUP(C11,CLIENT_CODE!B:B,CLIENT_CODE!G:G,0)) -> 0 | H11: =_xlfn.XLOOKUP(B11,CRN!G:G,CRN!L:L,"") -> 1 | I11: =IF(H11=0,0,_xlfn.XLOOKUP(C11,CLIENT_CODE!B:B,CLIENT_CODE!H:H,0)) -> 0 | J11: =_xlfn.XLOOKUP(B11,CRN!G:G,CRN!M:M,"") -> 0 | K11: =IF(J11=0,0,_xlfn.XLOOKUP(C11,CLIENT_CODE!B:B,CLIENT_CODE!I:I,0)) -> 0 | L11: =_xlfn.XLOOKUP(B11,CRN!G:G,CRN!N:N,"") -> 0 | M11: =IF(L11=0,0,_xlfn.XLOOKUP(C11,CLIENT_CODE!B:B,CLIENT_CODE!J:J,0)) -> 0 | N11: =_xlfn.XLOOKUP(B11,CRN!G:G,CRN!O:O,"") -> 0 | O11: =IF(N11=0,0,_xlfn.XLOOKUP(C11,CLIENT_CODE!B:B,CLIENT_CODE!K:K,0)) -> 0 | P11: =_xlfn.XLOOKUP(B11,CRN!G:G,CRN!P:P,"") -> 0 | Q11: =IF(P11=0,0,_xlfn.XLOOKUP(C11,CLIENT_CODE!B:B,CLIENT_CODE!L:L,0)) -> 0 | R11: =_xlfn.XLOOKUP(B11,CRN!G:G,CRN!Q:Q,"") -> 0 | S11: =IF(R11=0,0,_xlfn.XLOOKUP(C11,CLIENT_CODE!B:B,CLIENT_CODE!M:M,0)) -> 0 | T11: =_xlfn.XLOOKUP(B11,CRN!G:G,CRN!R:R,"") -> 0 | U11: =IF(T11=0,0,_xlfn.XLOOKUP(C11,CLIENT_CODE!B:B,CLIENT_CODE!N:N,0)) -> 0 | V11: =_xlfn.XLOOKUP(B11,CRN!G:G,CRN!S:S,"") -> 0 | W11: =IF(V11=0,0,_xlfn.XLOOKUP(C11,CLIENT_CODE!B:B,CLIENT_CODE!O:O,0)) -> 0 | X11: =_xlfn.XLOOKUP(B11,CRN!G:G,CRN!T:T,"") -> 0 | Y11: =IF(X11=0,0,_xlfn.XLOOKUP(C11,CLIENT_CODE!B:B,CLIENT_CODE!P:P,0)) -> 0 | Z11: =_xlfn.XLOOKUP(B11,CRN!G:G,CRN!U:U,"") -> 0 | AA11: =IF(X11=0,0,_xlfn.XLOOKUP(C11,CLIENT_CODE!B:B,CLIENT_CODE!P:P,0)) -> 0 | AB11: =_xlfn.XLOOKUP(B11,CRN!G:G,CRN!V:V,"") -> 0 | AC11: =IF(AB11=0,0,_xlfn.XLOOKUP(C11,CLIENT_CODE!B:B,CLIENT_CODE!R:R,0)) -> 0 | AD11: =SUM(E11,G11,I11,K11,M11,O11,Q11,S11,U11,W11,Y11,AA11,AC11,) -> 0
A12: 11 | B12: 2025212053 | E12: =IF(D12=0,0,_xlfn.XLOOKUP(C12,CLIENT_CODE!B:B,CLIENT_CODE!F:F,0)) -> 0 | F12: =_xlfn.XLOOKUP(B12,CRN!G:G,CRN!K:K,"") -> 0 | G12: =IF(F12=0,0,_xlfn.XLOOKUP(C12,CLIENT_CODE!B:B,CLIENT_CODE!G:G,0)) -> 0 | H12: =_xlfn.XLOOKUP(B12,CRN!G:G,CRN!L:L,"") -> 1 | I12: =IF(H12=0,0,_xlfn.XLOOKUP(C12,CLIENT_CODE!B:B,CLIENT_CODE!H:H,0)) -> 0 | J12: =_xlfn.XLOOKUP(B12,CRN!G:G,CRN!M:M,"") -> 0 | K12: =IF(J12=0,0,_xlfn.XLOOKUP(C12,CLIENT_CODE!B:B,CLIENT_CODE!I:I,0)) -> 0 | L12: =_xlfn.XLOOKUP(B12,CRN!G:G,CRN!N:N,"") -> 1 | M12: =IF(L12=0,0,_xlfn.XLOOKUP(C12,CLIENT_CODE!B:B,CLIENT_CODE!J:J,0)) -> 0 | N12: =_xlfn.XLOOKUP(B12,CRN!G:G,CRN!O:O,"") -> 0 | O12: =IF(N12=0,0,_xlfn.XLOOKUP(C12,CLIENT_CODE!B:B,CLIENT_CODE!K:K,0)) -> 0 | P12: =_xlfn.XLOOKUP(B12,CRN!G:G,CRN!P:P,"") -> 0 | Q12: =IF(P12=0,0,_xlfn.XLOOKUP(C12,CLIENT_CODE!B:B,CLIENT_CODE!L:L,0)) -> 0 | R12: =_xlfn.XLOOKUP(B12,CRN!G:G,CRN!Q:Q,"") -> 0 | S12: =IF(R12=0,0,_xlfn.XLOOKUP(C12,CLIENT_CODE!B:B,CLIENT_CODE!M:M,0)) -> 0 | T12: =_xlfn.XLOOKUP(B12,CRN!G:G,CRN!R:R,"") -> 1 | U12: =IF(T12=0,0,_xlfn.XLOOKUP(C12,CLIENT_CODE!B:B,CLIENT_CODE!N:N,0)) -> 0 | V12: =_xlfn.XLOOKUP(B12,CRN!G:G,CRN!S:S,"") -> 1 | W12: =IF(V12=0,0,_xlfn.XLOOKUP(C12,CLIENT_CODE!B:B,CLIENT_CODE!O:O,0)) -> 0 | X12: =_xlfn.XLOOKUP(B12,CRN!G:G,CRN!T:T,"") -> 0 | Y12: =IF(X12=0,0,_xlfn.XLOOKUP(C12,CLIENT_CODE!B:B,CLIENT_CODE!P:P,0)) -> 0 | Z12: =_xlfn.XLOOKUP(B12,CRN!G:G,CRN!U:U,"") -> 0 | AA12: =IF(X12=0,0,_xlfn.XLOOKUP(C12,CLIENT_CODE!B:B,CLIENT_CODE!P:P,0)) -> 0 | AB12: =_xlfn.XLOOKUP(B12,CRN!G:G,CRN!V:V,"") -> 0 | AC12: =IF(AB12=0,0,_xlfn.XLOOKUP(C12,CLIENT_CODE!B:B,CLIENT_CODE!R:R,0)) -> 0 | AD12: =SUM(E12,G12,I12,K12,M12,O12,Q12,S12,U12,W12,Y12,AA12,AC12,) -> 0
A13: 12 | B13: 2025212050 | E13: =IF(D13=0,0,_xlfn.XLOOKUP(C13,CLIENT_CODE!B:B,CLIENT_CODE!F:F,0)) -> 0 | F13: =_xlfn.XLOOKUP(B13,CRN!G:G,CRN!K:K,"") -> 0 | G13: =IF(F13=0,0,_xlfn.XLOOKUP(C13,CLIENT_CODE!B:B,CLIENT_CODE!G:G,0)) -> 0 | H13: =_xlfn.XLOOKUP(B13,CRN!G:G,CRN!L:L,"") -> 1 | I13: =IF(H13=0,0,_xlfn.XLOOKUP(C13,CLIENT_CODE!B:B,CLIENT_CODE!H:H,0)) -> 0 | J13: =_xlfn.XLOOKUP(B13,CRN!G:G,CRN!M:M,"") -> 0 | K13: =IF(J13=0,0,_xlfn.XLOOKUP(C13,CLIENT_CODE!B:B,CLIENT_CODE!I:I,0)) -> 0 | L13: =_xlfn.XLOOKUP(B13,CRN!G:G,CRN!N:N,"") -> 1 | M13: =IF(L13=0,0,_xlfn.XLOOKUP(C13,CLIENT_CODE!B:B,CLIENT_CODE!J:J,0)) -> 0 | N13: =_xlfn.XLOOKUP(B13,CRN!G:G,CRN!O:O,"") -> 0 | O13: =IF(N13=0,0,_xlfn.XLOOKUP(C13,CLIENT_CODE!B:B,CLIENT_CODE!K:K,0)) -> 0 | P13: =_xlfn.XLOOKUP(B13,CRN!G:G,CRN!P:P,"") -> 0 | Q13: =IF(P13=0,0,_xlfn.XLOOKUP(C13,CLIENT_CODE!B:B,CLIENT_CODE!L:L,0)) -> 0 | R13: =_xlfn.XLOOKUP(B13,CRN!G:G,CRN!Q:Q,"") -> 0 | S13: =IF(R13=0,0,_xlfn.XLOOKUP(C13,CLIENT_CODE!B:B,CLIENT_CODE!M:M,0)) -> 0 | T13: =_xlfn.XLOOKUP(B13,CRN!G:G,CRN!R:R,"") -> 1 | U13: =IF(T13=0,0,_xlfn.XLOOKUP(C13,CLIENT_CODE!B:B,CLIENT_CODE!N:N,0)) -> 0 | V13: =_xlfn.XLOOKUP(B13,CRN!G:G,CRN!S:S,"") -> 1 | W13: =IF(V13=0,0,_xlfn.XLOOKUP(C13,CLIENT_CODE!B:B,CLIENT_CODE!O:O,0)) -> 0 | X13: =_xlfn.XLOOKUP(B13,CRN!G:G,CRN!T:T,"") -> 0 | Y13: =IF(X13=0,0,_xlfn.XLOOKUP(C13,CLIENT_CODE!B:B,CLIENT_CODE!P:P,0)) -> 0 | Z13: =_xlfn.XLOOKUP(B13,CRN!G:G,CRN!U:U,"") -> 0 | AA13: =IF(X13=0,0,_xlfn.XLOOKUP(C13,CLIENT_CODE!B:B,CLIENT_CODE!P:P,0)) -> 0 | AB13: =_xlfn.XLOOKUP(B13,CRN!G:G,CRN!V:V,"") -> 0 | AC13: =IF(AB13=0,0,_xlfn.XLOOKUP(C13,CLIENT_CODE!B:B,CLIENT_CODE!R:R,0)) -> 0 | AD13: =SUM(E13,G13,I13,K13,M13,O13,Q13,S13,U13,W13,Y13,AA13,AC13,) -> 0
A14: 13 | B14: 2025212191 | E14: =IF(D14=0,0,_xlfn.XLOOKUP(C14,CLIENT_CODE!B:B,CLIENT_CODE!F:F,0)) -> 0 | F14: =_xlfn.XLOOKUP(B14,CRN!G:G,CRN!K:K,"") -> 0 | G14: =IF(F14=0,0,_xlfn.XLOOKUP(C14,CLIENT_CODE!B:B,CLIENT_CODE!G:G,0)) -> 0 | H14: =_xlfn.XLOOKUP(B14,CRN!G:G,CRN!L:L,"") -> 1 | I14: =IF(H14=0,0,_xlfn.XLOOKUP(C14,CLIENT_CODE!B:B,CLIENT_CODE!H:H,0)) -> 0 | J14: =_xlfn.XLOOKUP(B14,CRN!G:G,CRN!M:M,"") -> 0 | K14: =IF(J14=0,0,_xlfn.XLOOKUP(C14,CLIENT_CODE!B:B,CLIENT_CODE!I:I,0)) -> 0 | L14: =_xlfn.XLOOKUP(B14,CRN!G:G,CRN!N:N,"") -> 1 | M14: =IF(L14=0,0,_xlfn.XLOOKUP(C14,CLIENT_CODE!B:B,CLIENT_CODE!J:J,0)) -> 0 | N14: =_xlfn.XLOOKUP(B14,CRN!G:G,CRN!O:O,"") -> 0 | O14: =IF(N14=0,0,_xlfn.XLOOKUP(C14,CLIENT_CODE!B:B,CLIENT_CODE!K:K,0)) -> 0 | P14: =_xlfn.XLOOKUP(B14,CRN!G:G,CRN!P:P,"") -> 0 | Q14: =IF(P14=0,0,_xlfn.XLOOKUP(C14,CLIENT_CODE!B:B,CLIENT_CODE!L:L,0)) -> 0 | R14: =_xlfn.XLOOKUP(B14,CRN!G:G,CRN!Q:Q,"") -> 0 | S14: =IF(R14=0,0,_xlfn.XLOOKUP(C14,CLIENT_CODE!B:B,CLIENT_CODE!M:M,0)) -> 0 | T14: =_xlfn.XLOOKUP(B14,CRN!G:G,CRN!R:R,"") -> 1 | U14: =IF(T14=0,0,_xlfn.XLOOKUP(C14,CLIENT_CODE!B:B,CLIENT_CODE!N:N,0)) -> 0 | V14: =_xlfn.XLOOKUP(B14,CRN!G:G,CRN!S:S,"") -> 1 | W14: =IF(V14=0,0,_xlfn.XLOOKUP(C14,CLIENT_CODE!B:B,CLIENT_CODE!O:O,0)) -> 0 | X14: =_xlfn.XLOOKUP(B14,CRN!G:G,CRN!T:T,"") -> 0 | Y14: =IF(X14=0,0,_xlfn.XLOOKUP(C14,CLIENT_CODE!B:B,CLIENT_CODE!P:P,0)) -> 0 | Z14: =_xlfn.XLOOKUP(B14,CRN!G:G,CRN!U:U,"") -> 0 | AA14: =IF(X14=0,0,_xlfn.XLOOKUP(C14,CLIENT_CODE!B:B,CLIENT_CODE!P:P,0)) -> 0 | AB14: =_xlfn.XLOOKUP(B14,CRN!G:G,CRN!V:V,"") -> 0 | AC14: =IF(AB14=0,0,_xlfn.XLOOKUP(C14,CLIENT_CODE!B:B,CLIENT_CODE!R:R,0)) -> 0 | AD14: =SUM(E14,G14,I14,K14,M14,O14,Q14,S14,U14,W14,Y14,AA14,AC14,) -> 0
A15: 14 | B15: 2025212189 | E15: =IF(D15=0,0,_xlfn.XLOOKUP(C15,CLIENT_CODE!B:B,CLIENT_CODE!F:F,0)) -> 0 | F15: =_xlfn.XLOOKUP(B15,CRN!G:G,CRN!K:K,"") -> 0 | G15: =IF(F15=0,0,_xlfn.XLOOKUP(C15,CLIENT_CODE!B:B,CLIENT_CODE!G:G,0)) -> 0 | H15: =_xlfn.XLOOKUP(B15,CRN!G:G,CRN!L:L,"") -> 1 | I15: =IF(H15=0,0,_xlfn.XLOOKUP(C15,CLIENT_CODE!B:B,CLIENT_CODE!H:H,0)) -> 0 | J15: =_xlfn.XLOOKUP(B15,CRN!G:G,CRN!M:M,"") -> 0 | K15: =IF(J15=0,0,_xlfn.XLOOKUP(C15,CLIENT_CODE!B:B,CLIENT_CODE!I:I,0)) -> 0 | L15: =_xlfn.XLOOKUP(B15,CRN!G:G,CRN!N:N,"") -> 1 | M15: =IF(L15=0,0,_xlfn.XLOOKUP(C15,CLIENT_CODE!B:B,CLIENT_CODE!J:J,0)) -> 0 | N15: =_xlfn.XLOOKUP(B15,CRN!G:G,CRN!O:O,"") -> 0 | O15: =IF(N15=0,0,_xlfn.XLOOKUP(C15,CLIENT_CODE!B:B,CLIENT_CODE!K:K,0)) -> 0 | P15: =_xlfn.XLOOKUP(B15,CRN!G:G,CRN!P:P,"") -> 0 | Q15: =IF(P15=0,0,_xlfn.XLOOKUP(C15,CLIENT_CODE!B:B,CLIENT_CODE!L:L,0)) -> 0 | R15: =_xlfn.XLOOKUP(B15,CRN!G:G,CRN!Q:Q,"") -> 0 | S15: =IF(R15=0,0,_xlfn.XLOOKUP(C15,CLIENT_CODE!B:B,CLIENT_CODE!M:M,0)) -> 0 | T15: =_xlfn.XLOOKUP(B15,CRN!G:G,CRN!R:R,"") -> 1 | U15: =IF(T15=0,0,_xlfn.XLOOKUP(C15,CLIENT_CODE!B:B,CLIENT_CODE!N:N,0)) -> 0 | V15: =_xlfn.XLOOKUP(B15,CRN!G:G,CRN!S:S,"") -> 1 | W15: =IF(V15=0,0,_xlfn.XLOOKUP(C15,CLIENT_CODE!B:B,CLIENT_CODE!O:O,0)) -> 0 | X15: =_xlfn.XLOOKUP(B15,CRN!G:G,CRN!T:T,"") -> 0 | Y15: =IF(X15=0,0,_xlfn.XLOOKUP(C15,CLIENT_CODE!B:B,CLIENT_CODE!P:P,0)) -> 0 | Z15: =_xlfn.XLOOKUP(B15,CRN!G:G,CRN!U:U,"") -> 0 | AA15: =IF(X15=0,0,_xlfn.XLOOKUP(C15,CLIENT_CODE!B:B,CLIENT_CODE!P:P,0)) -> 0 | AB15: =_xlfn.XLOOKUP(B15,CRN!G:G,CRN!V:V,"") -> 0 | AC15: =IF(AB15=0,0,_xlfn.XLOOKUP(C15,CLIENT_CODE!B:B,CLIENT_CODE!R:R,0)) -> 0 | AD15: =SUM(E15,G15,I15,K15,M15,O15,Q15,S15,U15,W15,Y15,AA15,AC15,) -> 0
A16: 15 | B16: 2025212222 | E16: =IF(D16=0,0,_xlfn.XLOOKUP(C16,CLIENT_CODE!B:B,CLIENT_CODE!F:F,0)) -> 0 | F16: =_xlfn.XLOOKUP(B16,CRN!G:G,CRN!K:K,"") -> 0 | G16: =IF(F16=0,0,_xlfn.XLOOKUP(C16,CLIENT_CODE!B:B,CLIENT_CODE!G:G,0)) -> 0 | H16: =_xlfn.XLOOKUP(B16,CRN!G:G,CRN!L:L,"") -> 1 | I16: =IF(H16=0,0,_xlfn.XLOOKUP(C16,CLIENT_CODE!B:B,CLIENT_CODE!H:H,0)) -> 0 | J16: =_xlfn.XLOOKUP(B16,CRN!G:G,CRN!M:M,"") -> 0 | K16: =IF(J16=0,0,_xlfn.XLOOKUP(C16,CLIENT_CODE!B:B,CLIENT_CODE!I:I,0)) -> 0 | L16: =_xlfn.XLOOKUP(B16,CRN!G:G,CRN!N:N,"") -> 0 | M16: =IF(L16=0,0,_xlfn.XLOOKUP(C16,CLIENT_CODE!B:B,CLIENT_CODE!J:J,0)) -> 0 | N16: =_xlfn.XLOOKUP(B16,CRN!G:G,CRN!O:O,"") -> 0 | O16: =IF(N16=0,0,_xlfn.XLOOKUP(C16,CLIENT_CODE!B:B,CLIENT_CODE!K:K,0)) -> 0 | P16: =_xlfn.XLOOKUP(B16,CRN!G:G,CRN!P:P,"") -> 0 | Q16: =IF(P16=0,0,_xlfn.XLOOKUP(C16,CLIENT_CODE!B:B,CLIENT_CODE!L:L,0)) -> 0 | R16: =_xlfn.XLOOKUP(B16,CRN!G:G,CRN!Q:Q,"") -> 0 | S16: =IF(R16=0,0,_xlfn.XLOOKUP(C16,CLIENT_CODE!B:B,CLIENT_CODE!M:M,0)) -> 0 | T16: =_xlfn.XLOOKUP(B16,CRN!G:G,CRN!R:R,"") -> 0 | U16: =IF(T16=0,0,_xlfn.XLOOKUP(C16,CLIENT_CODE!B:B,CLIENT_CODE!N:N,0)) -> 0 | V16: =_xlfn.XLOOKUP(B16,CRN!G:G,CRN!S:S,"") -> 0 | W16: =IF(V16=0,0,_xlfn.XLOOKUP(C16,CLIENT_CODE!B:B,CLIENT_CODE!O:O,0)) -> 0 | X16: =_xlfn.XLOOKUP(B16,CRN!G:G,CRN!T:T,"") -> 0 | Y16: =IF(X16=0,0,_xlfn.XLOOKUP(C16,CLIENT_CODE!B:B,CLIENT_CODE!P:P,0)) -> 0 | Z16: =_xlfn.XLOOKUP(B16,CRN!G:G,CRN!U:U,"") -> 0 | AA16: =IF(X16=0,0,_xlfn.XLOOKUP(C16,CLIENT_CODE!B:B,CLIENT_CODE!P:P,0)) -> 0 | AB16: =_xlfn.XLOOKUP(B16,CRN!G:G,CRN!V:V,"") -> 0 | AC16: =IF(AB16=0,0,_xlfn.XLOOKUP(C16,CLIENT_CODE!B:B,CLIENT_CODE!R:R,0)) -> 0 | AD16: =SUM(E16,G16,I16,K16,M16,O16,Q16,S16,U16,W16,Y16,AA16,AC16,) -> 0
A17: 16 | B17: 2025212162 | E17: =IF(D17=0,0,_xlfn.XLOOKUP(C17,CLIENT_CODE!B:B,CLIENT_CODE!F:F,0)) -> 0 | F17: =_xlfn.XLOOKUP(B17,CRN!G:G,CRN!K:K,"") -> 0 | G17: =IF(F17=0,0,_xlfn.XLOOKUP(C17,CLIENT_CODE!B:B,CLIENT_CODE!G:G,0)) -> 0 | H17: =_xlfn.XLOOKUP(B17,CRN!G:G,CRN!L:L,"") -> 1 | I17: =IF(H17=0,0,_xlfn.XLOOKUP(C17,CLIENT_CODE!B:B,CLIENT_CODE!H:H,0)) -> 0 | J17: =_xlfn.XLOOKUP(B17,CRN!G:G,CRN!M:M,"") -> 0 | K17: =IF(J17=0,0,_xlfn.XLOOKUP(C17,CLIENT_CODE!B:B,CLIENT_CODE!I:I,0)) -> 0 | L17: =_xlfn.XLOOKUP(B17,CRN!G:G,CRN!N:N,"") -> 0 | M17: =IF(L17=0,0,_xlfn.XLOOKUP(C17,CLIENT_CODE!B:B,CLIENT_CODE!J:J,0)) -> 0 | N17: =_xlfn.XLOOKUP(B17,CRN!G:G,CRN!O:O,"") -> 0 | O17: =IF(N17=0,0,_xlfn.XLOOKUP(C17,CLIENT_CODE!B:B,CLIENT_CODE!K:K,0)) -> 0 | P17: =_xlfn.XLOOKUP(B17,CRN!G:G,CRN!P:P,"") -> 0 | Q17: =IF(P17=0,0,_xlfn.XLOOKUP(C17,CLIENT_CODE!B:B,CLIENT_CODE!L:L,0)) -> 0 | R17: =_xlfn.XLOOKUP(B17,CRN!G:G,CRN!Q:Q,"") -> 0 | S17: =IF(R17=0,0,_xlfn.XLOOKUP(C17,CLIENT_CODE!B:B,CLIENT_CODE!M:M,0)) -> 0 | T17: =_xlfn.XLOOKUP(B17,CRN!G:G,CRN!R:R,"") -> 0 | U17: =IF(T17=0,0,_xlfn.XLOOKUP(C17,CLIENT_CODE!B:B,CLIENT_CODE!N:N,0)) -> 0 | V17: =_xlfn.XLOOKUP(B17,CRN!G:G,CRN!S:S,"") -> 0 | W17: =IF(V17=0,0,_xlfn.XLOOKUP(C17,CLIENT_CODE!B:B,CLIENT_CODE!O:O,0)) -> 0 | X17: =_xlfn.XLOOKUP(B17,CRN!G:G,CRN!T:T,"") -> 0 | Y17: =IF(X17=0,0,_xlfn.XLOOKUP(C17,CLIENT_CODE!B:B,CLIENT_CODE!P:P,0)) -> 0 | Z17: =_xlfn.XLOOKUP(B17,CRN!G:G,CRN!U:U,"") -> 0 | AA17: =IF(X17=0,0,_xlfn.XLOOKUP(C17,CLIENT_CODE!B:B,CLIENT_CODE!P:P,0)) -> 0 | AB17: =_xlfn.XLOOKUP(B17,CRN!G:G,CRN!V:V,"") -> 0 | AC17: =IF(AB17=0,0,_xlfn.XLOOKUP(C17,CLIENT_CODE!B:B,CLIENT_CODE!R:R,0)) -> 0 | AD17: =SUM(E17,G17,I17,K17,M17,O17,Q17,S17,U17,W17,Y17,AA17,AC17,) -> 0
A18: 17 | B18: 2025212410 | E18: =IF(D18=0,0,_xlfn.XLOOKUP(C18,CLIENT_CODE!B:B,CLIENT_CODE!F:F,0)) -> 0 | F18: =_xlfn.XLOOKUP(B18,CRN!G:G,CRN!K:K,"") -> 0 | G18: =IF(F18=0,0,_xlfn.XLOOKUP(C18,CLIENT_CODE!B:B,CLIENT_CODE!G:G,0)) -> 0 | H18: =_xlfn.XLOOKUP(B18,CRN!G:G,CRN!L:L,"") -> 1 | I18: =IF(H18=0,0,_xlfn.XLOOKUP(C18,CLIENT_CODE!B:B,CLIENT_CODE!H:H,0)) -> 0 | J18: =_xlfn.XLOOKUP(B18,CRN!G:G,CRN!M:M,"") -> 0 | K18: =IF(J18=0,0,_xlfn.XLOOKUP(C18,CLIENT_CODE!B:B,CLIENT_CODE!I:I,0)) -> 0 | L18: =_xlfn.XLOOKUP(B18,CRN!G:G,CRN!N:N,"") -> 1 | M18: =IF(L18=0,0,_xlfn.XLOOKUP(C18,CLIENT_CODE!B:B,CLIENT_CODE!J:J,0)) -> 0 | N18: =_xlfn.XLOOKUP(B18,CRN!G:G,CRN!O:O,"") -> 0 | O18: =IF(N18=0,0,_xlfn.XLOOKUP(C18,CLIENT_CODE!B:B,CLIENT_CODE!K:K,0)) -> 0 | P18: =_xlfn.XLOOKUP(B18,CRN!G:G,CRN!P:P,"") -> 0 | Q18: =IF(P18=0,0,_xlfn.XLOOKUP(C18,CLIENT_CODE!B:B,CLIENT_CODE!L:L,0)) -> 0 | R18: =_xlfn.XLOOKUP(B18,CRN!G:G,CRN!Q:Q,"") -> 0 | S18: =IF(R18=0,0,_xlfn.XLOOKUP(C18,CLIENT_CODE!B:B,CLIENT_CODE!M:M,0)) -> 0 | T18: =_xlfn.XLOOKUP(B18,CRN!G:G,CRN!R:R,"") -> 1 | U18: =IF(T18=0,0,_xlfn.XLOOKUP(C18,CLIENT_CODE!B:B,CLIENT_CODE!N:N,0)) -> 0 | V18: =_xlfn.XLOOKUP(B18,CRN!G:G,CRN!S:S,"") -> 1 | W18: =IF(V18=0,0,_xlfn.XLOOKUP(C18,CLIENT_CODE!B:B,CLIENT_CODE!O:O,0)) -> 0 | X18: =_xlfn.XLOOKUP(B18,CRN!G:G,CRN!T:T,"") -> 0 | Y18: =IF(X18=0,0,_xlfn.XLOOKUP(C18,CLIENT_CODE!B:B,CLIENT_CODE!P:P,0)) -> 0 | Z18: =_xlfn.XLOOKUP(B18,CRN!G:G,CRN!U:U,"") -> 0 | AA18: =IF(X18=0,0,_xlfn.XLOOKUP(C18,CLIENT_CODE!B:B,CLIENT_CODE!P:P,0)) -> 0 | AB18: =_xlfn.XLOOKUP(B18,CRN!G:G,CRN!V:V,"") -> 0 | AC18: =IF(AB18=0,0,_xlfn.XLOOKUP(C18,CLIENT_CODE!B:B,CLIENT_CODE!R:R,0)) -> 0 | AD18: =SUM(E18,G18,I18,K18,M18,O18,Q18,S18,U18,W18,Y18,AA18,AC18,) -> 0
A19: 18 | B19: 2025212215 | E19: =IF(D19=0,0,_xlfn.XLOOKUP(C19,CLIENT_CODE!B:B,CLIENT_CODE!F:F,0)) -> 0 | F19: =_xlfn.XLOOKUP(B19,CRN!G:G,CRN!K:K,"") -> 0 | G19: =IF(F19=0,0,_xlfn.XLOOKUP(C19,CLIENT_CODE!B:B,CLIENT_CODE!G:G,0)) -> 0 | H19: =_xlfn.XLOOKUP(B19,CRN!G:G,CRN!L:L,"") -> 1 | I19: =IF(H19=0,0,_xlfn.XLOOKUP(C19,CLIENT_CODE!B:B,CLIENT_CODE!H:H,0)) -> 0 | J19: =_xlfn.XLOOKUP(B19,CRN!G:G,CRN!M:M,"") -> 0 | K19: =IF(J19=0,0,_xlfn.XLOOKUP(C19,CLIENT_CODE!B:B,CLIENT_CODE!I:I,0)) -> 0 | L19: =_xlfn.XLOOKUP(B19,CRN!G:G,CRN!N:N,"") -> 1 | M19: =IF(L19=0,0,_xlfn.XLOOKUP(C19,CLIENT_CODE!B:B,CLIENT_CODE!J:J,0)) -> 0 | N19: =_xlfn.XLOOKUP(B19,CRN!G:G,CRN!O:O,"") -> 0 | O19: =IF(N19=0,0,_xlfn.XLOOKUP(C19,CLIENT_CODE!B:B,CLIENT_CODE!K:K,0)) -> 0 | P19: =_xlfn.XLOOKUP(B19,CRN!G:G,CRN!P:P,"") -> 0 | Q19: =IF(P19=0,0,_xlfn.XLOOKUP(C19,CLIENT_CODE!B:B,CLIENT_CODE!L:L,0)) -> 0 | R19: =_xlfn.XLOOKUP(B19,CRN!G:G,CRN!Q:Q,"") -> 0 | S19: =IF(R19=0,0,_xlfn.XLOOKUP(C19,CLIENT_CODE!B:B,CLIENT_CODE!M:M,0)) -> 0 | T19: =_xlfn.XLOOKUP(B19,CRN!G:G,CRN!R:R,"") -> 1 | U19: =IF(T19=0,0,_xlfn.XLOOKUP(C19,CLIENT_CODE!B:B,CLIENT_CODE!N:N,0)) -> 0 | V19: =_xlfn.XLOOKUP(B19,CRN!G:G,CRN!S:S,"") -> 1 | W19: =IF(V19=0,0,_xlfn.XLOOKUP(C19,CLIENT_CODE!B:B,CLIENT_CODE!O:O,0)) -> 0 | X19: =_xlfn.XLOOKUP(B19,CRN!G:G,CRN!T:T,"") -> 0 | Y19: =IF(X19=0,0,_xlfn.XLOOKUP(C19,CLIENT_CODE!B:B,CLIENT_CODE!P:P,0)) -> 0 | Z19: =_xlfn.XLOOKUP(B19,CRN!G:G,CRN!U:U,"") -> 0 | AA19: =IF(X19=0,0,_xlfn.XLOOKUP(C19,CLIENT_CODE!B:B,CLIENT_CODE!P:P,0)) -> 0 | AB19: =_xlfn.XLOOKUP(B19,CRN!G:G,CRN!V:V,"") -> 0 | AC19: =IF(AB19=0,0,_xlfn.XLOOKUP(C19,CLIENT_CODE!B:B,CLIENT_CODE!R:R,0)) -> 0 | AD19: =SUM(E19,G19,I19,K19,M19,O19,Q19,S19,U19,W19,Y19,AA19,AC19,) -> 0
A20: 19 | B20: 2025212407 | E20: =IF(D20=0,0,_xlfn.XLOOKUP(C20,CLIENT_CODE!B:B,CLIENT_CODE!F:F,0)) -> 0 | F20: =_xlfn.XLOOKUP(B20,CRN!G:G,CRN!K:K,"") -> 0 | G20: =IF(F20=0,0,_xlfn.XLOOKUP(C20,CLIENT_CODE!B:B,CLIENT_CODE!G:G,0)) -> 0 | H20: =_xlfn.XLOOKUP(B20,CRN!G:G,CRN!L:L,"") -> 1 | I20: =IF(H20=0,0,_xlfn.XLOOKUP(C20,CLIENT_CODE!B:B,CLIENT_CODE!H:H,0)) -> 0 | J20: =_xlfn.XLOOKUP(B20,CRN!G:G,CRN!M:M,"") -> 0 | K20: =IF(J20=0,0,_xlfn.XLOOKUP(C20,CLIENT_CODE!B:B,CLIENT_CODE!I:I,0)) -> 0 | L20: =_xlfn.XLOOKUP(B20,CRN!G:G,CRN!N:N,"") -> 0 | M20: =IF(L20=0,0,_xlfn.XLOOKUP(C20,CLIENT_CODE!B:B,CLIENT_CODE!J:J,0)) -> 0 | N20: =_xlfn.XLOOKUP(B20,CRN!G:G,CRN!O:O,"") -> 0 | O20: =IF(N20=0,0,_xlfn.XLOOKUP(C20,CLIENT_CODE!B:B,CLIENT_CODE!K:K,0)) -> 0 | P20: =_xlfn.XLOOKUP(B20,CRN!G:G,CRN!P:P,"") -> 0 | Q20: =IF(P20=0,0,_xlfn.XLOOKUP(C20,CLIENT_CODE!B:B,CLIENT_CODE!L:L,0)) -> 0 | R20: =_xlfn.XLOOKUP(B20,CRN!G:G,CRN!Q:Q,"") -> 0 | S20: =IF(R20=0,0,_xlfn.XLOOKUP(C20,CLIENT_CODE!B:B,CLIENT_CODE!M:M,0)) -> 0 | T20: =_xlfn.XLOOKUP(B20,CRN!G:G,CRN!R:R,"") -> 0 | U20: =IF(T20=0,0,_xlfn.XLOOKUP(C20,CLIENT_CODE!B:B,CLIENT_CODE!N:N,0)) -> 0 | V20: =_xlfn.XLOOKUP(B20,CRN!G:G,CRN!S:S,"") -> 0 | W20: =IF(V20=0,0,_xlfn.XLOOKUP(C20,CLIENT_CODE!B:B,CLIENT_CODE!O:O,0)) -> 0 | X20: =_xlfn.XLOOKUP(B20,CRN!G:G,CRN!T:T,"") -> 0 | Y20: =IF(X20=0,0,_xlfn.XLOOKUP(C20,CLIENT_CODE!B:B,CLIENT_CODE!P:P,0)) -> 0 | Z20: =_xlfn.XLOOKUP(B20,CRN!G:G,CRN!U:U,"") -> 0 | AA20: =IF(X20=0,0,_xlfn.XLOOKUP(C20,CLIENT_CODE!B:B,CLIENT_CODE!P:P,0)) -> 0 | AB20: =_xlfn.XLOOKUP(B20,CRN!G:G,CRN!V:V,"") -> 0 | AC20: =IF(AB20=0,0,_xlfn.XLOOKUP(C20,CLIENT_CODE!B:B,CLIENT_CODE!R:R,0)) -> 0 | AD20: =SUM(E20,G20,I20,K20,M20,O20,Q20,S20,U20,W20,Y20,AA20,AC20,) -> 0
A21: 20 | B21: 2025212443 | E21: =IF(D21=0,0,_xlfn.XLOOKUP(C21,CLIENT_CODE!B:B,CLIENT_CODE!F:F,0)) -> 0 | F21: =_xlfn.XLOOKUP(B21,CRN!G:G,CRN!K:K,"") -> 0 | G21: =IF(F21=0,0,_xlfn.XLOOKUP(C21,CLIENT_CODE!B:B,CLIENT_CODE!G:G,0)) -> 0 | H21: =_xlfn.XLOOKUP(B21,CRN!G:G,CRN!L:L,"") -> 1 | I21: =IF(H21=0,0,_xlfn.XLOOKUP(C21,CLIENT_CODE!B:B,CLIENT_CODE!H:H,0)) -> 0 | J21: =_xlfn.XLOOKUP(B21,CRN!G:G,CRN!M:M,"") -> 0 | K21: =IF(J21=0,0,_xlfn.XLOOKUP(C21,CLIENT_CODE!B:B,CLIENT_CODE!I:I,0)) -> 0 | L21: =_xlfn.XLOOKUP(B21,CRN!G:G,CRN!N:N,"") -> 1 | M21: =IF(L21=0,0,_xlfn.XLOOKUP(C21,CLIENT_CODE!B:B,CLIENT_CODE!J:J,0)) -> 0 | N21: =_xlfn.XLOOKUP(B21,CRN!G:G,CRN!O:O,"") -> 0 | O21: =IF(N21=0,0,_xlfn.XLOOKUP(C21,CLIENT_CODE!B:B,CLIENT_CODE!K:K,0)) -> 0 | P21: =_xlfn.XLOOKUP(B21,CRN!G:G,CRN!P:P,"") -> 0 | Q21: =IF(P21=0,0,_xlfn.XLOOKUP(C21,CLIENT_CODE!B:B,CLIENT_CODE!L:L,0)) -> 0 | R21: =_xlfn.XLOOKUP(B21,CRN!G:G,CRN!Q:Q,"") -> 0 | S21: =IF(R21=0,0,_xlfn.XLOOKUP(C21,CLIENT_CODE!B:B,CLIENT_CODE!M:M,0)) -> 0 | T21: =_xlfn.XLOOKUP(B21,CRN!G:G,CRN!R:R,"") -> 1 | U21: =IF(T21=0,0,_xlfn.XLOOKUP(C21,CLIENT_CODE!B:B,CLIENT_CODE!N:N,0)) -> 0 | V21: =_xlfn.XLOOKUP(B21,CRN!G:G,CRN!S:S,"") -> 1 | W21: =IF(V21=0,0,_xlfn.XLOOKUP(C21,CLIENT_CODE!B:B,CLIENT_CODE!O:O,0)) -> 0 | X21: =_xlfn.XLOOKUP(B21,CRN!G:G,CRN!T:T,"") -> 0 | Y21: =IF(X21=0,0,_xlfn.XLOOKUP(C21,CLIENT_CODE!B:B,CLIENT_CODE!P:P,0)) -> 0 | Z21: =_xlfn.XLOOKUP(B21,CRN!G:G,CRN!U:U,"") -> 0 | AA21: =IF(X21=0,0,_xlfn.XLOOKUP(C21,CLIENT_CODE!B:B,CLIENT_CODE!P:P,0)) -> 0 | AB21: =_xlfn.XLOOKUP(B21,CRN!G:G,CRN!V:V,"") -> 0 | AC21: =IF(AB21=0,0,_xlfn.XLOOKUP(C21,CLIENT_CODE!B:B,CLIENT_CODE!R:R,0)) -> 0 | AD21: =SUM(E21,G21,I21,K21,M21,O21,Q21,S21,U21,W21,Y21,AA21,AC21,) -> 0
A22: 21 | B22: 2025212467 | E22: =IF(D22=0,0,_xlfn.XLOOKUP(C22,CLIENT_CODE!B:B,CLIENT_CODE!F:F,0)) -> 0 | F22: =_xlfn.XLOOKUP(B22,CRN!G:G,CRN!K:K,"") -> 0 | G22: =IF(F22=0,0,_xlfn.XLOOKUP(C22,CLIENT_CODE!B:B,CLIENT_CODE!G:G,0)) -> 0 | H22: =_xlfn.XLOOKUP(B22,CRN!G:G,CRN!L:L,"") -> 1 | I22: =IF(H22=0,0,_xlfn.XLOOKUP(C22,CLIENT_CODE!B:B,CLIENT_CODE!H:H,0)) -> 0 | J22: =_xlfn.XLOOKUP(B22,CRN!G:G,CRN!M:M,"") -> 0 | K22: =IF(J22=0,0,_xlfn.XLOOKUP(C22,CLIENT_CODE!B:B,CLIENT_CODE!I:I,0)) -> 0 | L22: =_xlfn.XLOOKUP(B22,CRN!G:G,CRN!N:N,"") -> 1 | M22: =IF(L22=0,0,_xlfn.XLOOKUP(C22,CLIENT_CODE!B:B,CLIENT_CODE!J:J,0)) -> 0 | N22: =_xlfn.XLOOKUP(B22,CRN!G:G,CRN!O:O,"") -> 0 | O22: =IF(N22=0,0,_xlfn.XLOOKUP(C22,CLIENT_CODE!B:B,CLIENT_CODE!K:K,0)) -> 0 | P22: =_xlfn.XLOOKUP(B22,CRN!G:G,CRN!P:P,"") -> 0 | Q22: =IF(P22=0,0,_xlfn.XLOOKUP(C22,CLIENT_CODE!B:B,CLIENT_CODE!L:L,0)) -> 0 | R22: =_xlfn.XLOOKUP(B22,CRN!G:G,CRN!Q:Q,"") -> 0 | S22: =IF(R22=0,0,_xlfn.XLOOKUP(C22,CLIENT_CODE!B:B,CLIENT_CODE!M:M,0)) -> 0 | T22: =_xlfn.XLOOKUP(B22,CRN!G:G,CRN!R:R,"") -> 1 | U22: =IF(T22=0,0,_xlfn.XLOOKUP(C22,CLIENT_CODE!B:B,CLIENT_CODE!N:N,0)) -> 0 | V22: =_xlfn.XLOOKUP(B22,CRN!G:G,CRN!S:S,"") -> 1 | W22: =IF(V22=0,0,_xlfn.XLOOKUP(C22,CLIENT_CODE!B:B,CLIENT_CODE!O:O,0)) -> 0 | X22: =_xlfn.XLOOKUP(B22,CRN!G:G,CRN!T:T,"") -> 0 | Y22: =IF(X22=0,0,_xlfn.XLOOKUP(C22,CLIENT_CODE!B:B,CLIENT_CODE!P:P,0)) -> 0 | Z22: =_xlfn.XLOOKUP(B22,CRN!G:G,CRN!U:U,"") -> 0 | AA22: =IF(X22=0,0,_xlfn.XLOOKUP(C22,CLIENT_CODE!B:B,CLIENT_CODE!P:P,0)) -> 0 | AB22: =_xlfn.XLOOKUP(B22,CRN!G:G,CRN!V:V,"") -> 0 | AC22: =IF(AB22=0,0,_xlfn.XLOOKUP(C22,CLIENT_CODE!B:B,CLIENT_CODE!R:R,0)) -> 0 | AD22: =SUM(E22,G22,I22,K22,M22,O22,Q22,S22,U22,W22,Y22,AA22,AC22,) -> 0
A23: 22 | B23: 2024213743 | E23: =IF(D23=0,0,_xlfn.XLOOKUP(C23,CLIENT_CODE!B:B,CLIENT_CODE!F:F,0)) -> 0 | F23: =_xlfn.XLOOKUP(B23,CRN!G:G,CRN!K:K,"") -> 0 | G23: =IF(F23=0,0,_xlfn.XLOOKUP(C23,CLIENT_CODE!B:B,CLIENT_CODE!G:G,0)) -> 0 | H23: =_xlfn.XLOOKUP(B23,CRN!G:G,CRN!L:L,"") -> 0 | I23: =IF(H23=0,0,_xlfn.XLOOKUP(C23,CLIENT_CODE!B:B,CLIENT_CODE!H:H,0)) -> 0 | J23: =_xlfn.XLOOKUP(B23,CRN!G:G,CRN!M:M,"") -> 0 | K23: =IF(J23=0,0,_xlfn.XLOOKUP(C23,CLIENT_CODE!B:B,CLIENT_CODE!I:I,0)) -> 0 | L23: =_xlfn.XLOOKUP(B23,CRN!G:G,CRN!N:N,"") -> 0 | M23: =IF(L23=0,0,_xlfn.XLOOKUP(C23,CLIENT_CODE!B:B,CLIENT_CODE!J:J,0)) -> 0 | N23: =_xlfn.XLOOKUP(B23,CRN!G:G,CRN!O:O,"") -> 0 | O23: =IF(N23=0,0,_xlfn.XLOOKUP(C23,CLIENT_CODE!B:B,CLIENT_CODE!K:K,0)) -> 0 | P23: =_xlfn.XLOOKUP(B23,CRN!G:G,CRN!P:P,"") -> 0 | Q23: =IF(P23=0,0,_xlfn.XLOOKUP(C23,CLIENT_CODE!B:B,CLIENT_CODE!L:L,0)) -> 0 | R23: =_xlfn.XLOOKUP(B23,CRN!G:G,CRN!Q:Q,"") -> 0 | S23: =IF(R23=0,0,_xlfn.XLOOKUP(C23,CLIENT_CODE!B:B,CLIENT_CODE!M:M,0)) -> 0 | T23: =_xlfn.XLOOKUP(B23,CRN!G:G,CRN!R:R,"") -> 0 | U23: =IF(T23=0,0,_xlfn.XLOOKUP(C23,CLIENT_CODE!B:B,CLIENT_CODE!N:N,0)) -> 0 | V23: =_xlfn.XLOOKUP(B23,CRN!G:G,CRN!S:S,"") -> 1 | W23: =IF(V23=0,0,_xlfn.XLOOKUP(C23,CLIENT_CODE!B:B,CLIENT_CODE!O:O,0)) -> 0 | X23: =_xlfn.XLOOKUP(B23,CRN!G:G,CRN!T:T,"") -> 0 | Y23: =IF(X23=0,0,_xlfn.XLOOKUP(C23,CLIENT_CODE!B:B,CLIENT_CODE!P:P,0)) -> 0 | Z23: =_xlfn.XLOOKUP(B23,CRN!G:G,CRN!U:U,"") -> 0 | AA23: =IF(X23=0,0,_xlfn.XLOOKUP(C23,CLIENT_CODE!B:B,CLIENT_CODE!P:P,0)) -> 0 | AB23: =_xlfn.XLOOKUP(B23,CRN!G:G,CRN!V:V,"") -> 0 | AC23: =IF(AB23=0,0,_xlfn.XLOOKUP(C23,CLIENT_CODE!B:B,CLIENT_CODE!R:R,0)) -> 0 | AD23: =SUM(E23,G23,I23,K23,M23,O23,Q23,S23,U23,W23,Y23,AA23,AC23,) -> 0
A24: 23 | B24: 2025212533 | E24: =IF(D24=0,0,_xlfn.XLOOKUP(C24,CLIENT_CODE!B:B,CLIENT_CODE!F:F,0)) -> 0 | F24: =_xlfn.XLOOKUP(B24,CRN!G:G,CRN!K:K,"") -> 0 | G24: =IF(F24=0,0,_xlfn.XLOOKUP(C24,CLIENT_CODE!B:B,CLIENT_CODE!G:G,0)) -> 0 | H24: =_xlfn.XLOOKUP(B24,CRN!G:G,CRN!L:L,"") -> 1 | I24: =IF(H24=0,0,_xlfn.XLOOKUP(C24,CLIENT_CODE!B:B,CLIENT_CODE!H:H,0)) -> 0 | J24: =_xlfn.XLOOKUP(B24,CRN!G:G,CRN!M:M,"") -> 0 | K24: =IF(J24=0,0,_xlfn.XLOOKUP(C24,CLIENT_CODE!B:B,CLIENT_CODE!I:I,0)) -> 0 | L24: =_xlfn.XLOOKUP(B24,CRN!G:G,CRN!N:N,"") -> 1 | M24: =IF(L24=0,0,_xlfn.XLOOKUP(C24,CLIENT_CODE!B:B,CLIENT_CODE!J:J,0)) -> 0 | N24: =_xlfn.XLOOKUP(B24,CRN!G:G,CRN!O:O,"") -> 0 | O24: =IF(N24=0,0,_xlfn.XLOOKUP(C24,CLIENT_CODE!B:B,CLIENT_CODE!K:K,0)) -> 0 | P24: =_xlfn.XLOOKUP(B24,CRN!G:G,CRN!P:P,"") -> 0 | Q24: =IF(P24=0,0,_xlfn.XLOOKUP(C24,CLIENT_CODE!B:B,CLIENT_CODE!L:L,0)) -> 0 | R24: =_xlfn.XLOOKUP(B24,CRN!G:G,CRN!Q:Q,"") -> 0 | S24: =IF(R24=0,0,_xlfn.XLOOKUP(C24,CLIENT_CODE!B:B,CLIENT_CODE!M:M,0)) -> 0 | T24: =_xlfn.XLOOKUP(B24,CRN!G:G,CRN!R:R,"") -> 1 | U24: =IF(T24=0,0,_xlfn.XLOOKUP(C24,CLIENT_CODE!B:B,CLIENT_CODE!N:N,0)) -> 0 | V24: =_xlfn.XLOOKUP(B24,CRN!G:G,CRN!S:S,"") -> 1 | W24: =IF(V24=0,0,_xlfn.XLOOKUP(C24,CLIENT_CODE!B:B,CLIENT_CODE!O:O,0)) -> 0 | X24: =_xlfn.XLOOKUP(B24,CRN!G:G,CRN!T:T,"") -> 0 | Y24: =IF(X24=0,0,_xlfn.XLOOKUP(C24,CLIENT_CODE!B:B,CLIENT_CODE!P:P,0)) -> 0 | Z24: =_xlfn.XLOOKUP(B24,CRN!G:G,CRN!U:U,"") -> 0 | AA24: =IF(X24=0,0,_xlfn.XLOOKUP(C24,CLIENT_CODE!B:B,CLIENT_CODE!P:P,0)) -> 0 | AB24: =_xlfn.XLOOKUP(B24,CRN!G:G,CRN!V:V,"") -> 0 | AC24: =IF(AB24=0,0,_xlfn.XLOOKUP(C24,CLIENT_CODE!B:B,CLIENT_CODE!R:R,0)) -> 0 | AD24: =SUM(E24,G24,I24,K24,M24,O24,Q24,S24,U24,W24,Y24,AA24,AC24,) -> 0
A25: 24 | B25: 2017212612 | E25: =IF(D25=0,0,_xlfn.XLOOKUP(C25,CLIENT_CODE!B:B,CLIENT_CODE!F:F,0)) -> 0 | F25: =_xlfn.XLOOKUP(B25,CRN!G:G,CRN!K:K,"") -> 0 | G25: =IF(F25=0,0,_xlfn.XLOOKUP(C25,CLIENT_CODE!B:B,CLIENT_CODE!G:G,0)) -> 0 | H25: =_xlfn.XLOOKUP(B25,CRN!G:G,CRN!L:L,"") -> 1 | I25: =IF(H25=0,0,_xlfn.XLOOKUP(C25,CLIENT_CODE!B:B,CLIENT_CODE!H:H,0)) -> 0 | J25: =_xlfn.XLOOKUP(B25,CRN!G:G,CRN!M:M,"") -> 0 | K25: =IF(J25=0,0,_xlfn.XLOOKUP(C25,CLIENT_CODE!B:B,CLIENT_CODE!I:I,0)) -> 0 | L25: =_xlfn.XLOOKUP(B25,CRN!G:G,CRN!N:N,"") -> 0 | M25: =IF(L25=0,0,_xlfn.XLOOKUP(C25,CLIENT_CODE!B:B,CLIENT_CODE!J:J,0)) -> 0 | N25: =_xlfn.XLOOKUP(B25,CRN!G:G,CRN!O:O,"") -> 0 | O25: =IF(N25=0,0,_xlfn.XLOOKUP(C25,CLIENT_CODE!B:B,CLIENT_CODE!K:K,0)) -> 0 | P25: =_xlfn.XLOOKUP(B25,CRN!G:G,CRN!P:P,"") -> 0 | Q25: =IF(P25=0,0,_xlfn.XLOOKUP(C25,CLIENT_CODE!B:B,CLIENT_CODE!L:L,0)) -> 0 | R25: =_xlfn.XLOOKUP(B25,CRN!G:G,CRN!Q:Q,"") -> 0 | S25: =IF(R25=0,0,_xlfn.XLOOKUP(C25,CLIENT_CODE!B:B,CLIENT_CODE!M:M,0)) -> 0 | T25: =_xlfn.XLOOKUP(B25,CRN!G:G,CRN!R:R,"") -> 0 | U25: =IF(T25=0,0,_xlfn.XLOOKUP(C25,CLIENT_CODE!B:B,CLIENT_CODE!N:N,0)) -> 0 | V25: =_xlfn.XLOOKUP(B25,CRN!G:G,CRN!S:S,"") -> 0 | W25: =IF(V25=0,0,_xlfn.XLOOKUP(C25,CLIENT_CODE!B:B,CLIENT_CODE!O:O,0)) -> 0 | X25: =_xlfn.XLOOKUP(B25,CRN!G:G,CRN!T:T,"") -> 0 | Y25: =IF(X25=0,0,_xlfn.XLOOKUP(C25,CLIENT_CODE!B:B,CLIENT_CODE!P:P,0)) -> 0 | Z25: =_xlfn.XLOOKUP(B25,CRN!G:G,CRN!U:U,"") -> 0 | AA25: =IF(X25=0,0,_xlfn.XLOOKUP(C25,CLIENT_CODE!B:B,CLIENT_CODE!P:P,0)) -> 0 | AB25: =_xlfn.XLOOKUP(B25,CRN!G:G,CRN!V:V,"") -> 0 | AC25: =IF(AB25=0,0,_xlfn.XLOOKUP(C25,CLIENT_CODE!B:B,CLIENT_CODE!R:R,0)) -> 0 | AD25: =SUM(E25,G25,I25,K25,M25,O25,Q25,S25,U25,W25,Y25,AA25,AC25,) -> 0
... A87: 86 | B87: 2025214020 | E87: =IF(D87=0,0,_xlfn.XLOOKUP(C87,CLIENT_CODE!B:B,CLIENT_CODE!F:F,0)) -> 0 | F87: =_xlfn.XLOOKUP(B87,CRN!G:G,CRN!K:K,"") -> 0 | G87: =IF(F87=0,0,_xlfn.XLOOKUP(C87,CLIENT_CODE!B:B,CLIENT_CODE!G:G,0)) -> 0 | H87: =_xlfn.XLOOKUP(B87,CRN!G:G,CRN!L:L,"") -> 1 | I87: =IF(H87=0,0,_xlfn.XLOOKUP(C87,CLIENT_CODE!B:B,CLIENT_CODE!H:H,0)) -> 0 | J87: =_xlfn.XLOOKUP(B87,CRN!G:G,CRN!M:M,"") -> 0 | K87: =IF(J87=0,0,_xlfn.XLOOKUP(C87,CLIENT_CODE!B:B,CLIENT_CODE!I:I,0)) -> 0 | L87: =_xlfn.XLOOKUP(B87,CRN!G:G,CRN!N:N,"") -> 0 | M87: =IF(L87=0,0,_xlfn.XLOOKUP(C87,CLIENT_CODE!B:B,CLIENT_CODE!J:J,0)) -> 0 | N87: =_xlfn.XLOOKUP(B87,CRN!G:G,CRN!O:O,"") -> 0 | O87: =IF(N87=0,0,_xlfn.XLOOKUP(C87,CLIENT_CODE!B:B,CLIENT_CODE!K:K,0)) -> 0 | P87: =_xlfn.XLOOKUP(B87,CRN!G:G,CRN!P:P,"") -> 0 | Q87: =IF(P87=0,0,_xlfn.XLOOKUP(C87,CLIENT_CODE!B:B,CLIENT_CODE!L:L,0)) -> 0 | R87: =_xlfn.XLOOKUP(B87,CRN!G:G,CRN!Q:Q,"") -> 0 | S87: =IF(R87=0,0,_xlfn.XLOOKUP(C87,CLIENT_CODE!B:B,CLIENT_CODE!M:M,0)) -> 0 | T87: =_xlfn.XLOOKUP(B87,CRN!G:G,CRN!R:R,"") -> 1 | U87: =IF(T87=0,0,_xlfn.XLOOKUP(C87,CLIENT_CODE!B:B,CLIENT_CODE!N:N,0)) -> 0 | V87: =_xlfn.XLOOKUP(B87,CRN!G:G,CRN!S:S,"") -> 1 | W87: =IF(V87=0,0,_xlfn.XLOOKUP(C87,CLIENT_CODE!B:B,CLIENT_CODE!O:O,0)) -> 0 | X87: =_xlfn.XLOOKUP(B87,CRN!G:G,CRN!T:T,"") -> 0 | Y87: =IF(X87=0,0,_xlfn.XLOOKUP(C87,CLIENT_CODE!B:B,CLIENT_CODE!P:P,0)) -> 0 | Z87: =_xlfn.XLOOKUP(B87,CRN!G:G,CRN!U:U,"") -> 0 | AA87: =IF(X87=0,0,_xlfn.XLOOKUP(C87,CLIENT_CODE!B:B,CLIENT_CODE!P:P,0)) -> 0 | AB87: =_xlfn.XLOOKUP(B87,CRN!G:G,CRN!V:V,"") -> 0 | AC87: =IF(AB87=0,0,_xlfn.XLOOKUP(C87,CLIENT_CODE!B:B,CLIENT_CODE!R:R,0)) -> 0 | AD87: =SUM(E87,G87,I87,K87,M87,O87,Q87,S87,U87,W87,Y87,AA87,AC87,) -> 0
A88: 87 | B88: 2759892 | E88: =IF(D88=0,0,_xlfn.XLOOKUP(C88,CLIENT_CODE!B:B,CLIENT_CODE!F:F,0)) -> 0 | F88: =_xlfn.XLOOKUP(B88,CRN!G:G,CRN!K:K,"") -> 0 | G88: =IF(F88=0,0,_xlfn.XLOOKUP(C88,CLIENT_CODE!B:B,CLIENT_CODE!G:G,0)) -> 0 | H88: =_xlfn.XLOOKUP(B88,CRN!G:G,CRN!L:L,"") -> 1 | I88: =IF(H88=0,0,_xlfn.XLOOKUP(C88,CLIENT_CODE!B:B,CLIENT_CODE!H:H,0)) -> 0 | J88: =_xlfn.XLOOKUP(B88,CRN!G:G,CRN!M:M,"") -> 0 | K88: =IF(J88=0,0,_xlfn.XLOOKUP(C88,CLIENT_CODE!B:B,CLIENT_CODE!I:I,0)) -> 0 | L88: =_xlfn.XLOOKUP(B88,CRN!G:G,CRN!N:N,"") -> 1 | M88: =IF(L88=0,0,_xlfn.XLOOKUP(C88,CLIENT_CODE!B:B,CLIENT_CODE!J:J,0)) -> 0 | N88: =_xlfn.XLOOKUP(B88,CRN!G:G,CRN!O:O,"") -> 0 | O88: =IF(N88=0,0,_xlfn.XLOOKUP(C88,CLIENT_CODE!B:B,CLIENT_CODE!K:K,0)) -> 0 | P88: =_xlfn.XLOOKUP(B88,CRN!G:G,CRN!P:P,"") -> 0 | Q88: =IF(P88=0,0,_xlfn.XLOOKUP(C88,CLIENT_CODE!B:B,CLIENT_CODE!L:L,0)) -> 0 | R88: =_xlfn.XLOOKUP(B88,CRN!G:G,CRN!Q:Q,"") -> 0 | S88: =IF(R88=0,0,_xlfn.XLOOKUP(C88,CLIENT_CODE!B:B,CLIENT_CODE!M:M,0)) -> 0 | T88: =_xlfn.XLOOKUP(B88,CRN!G:G,CRN!R:R,"") -> 1 | U88: =IF(T88=0,0,_xlfn.XLOOKUP(C88,CLIENT_CODE!B:B,CLIENT_CODE!N:N,0)) -> 0 | V88: =_xlfn.XLOOKUP(B88,CRN!G:G,CRN!S:S,"") -> 1 | W88: =IF(V88=0,0,_xlfn.XLOOKUP(C88,CLIENT_CODE!B:B,CLIENT_CODE!O:O,0)) -> 0 | X88: =_xlfn.XLOOKUP(B88,CRN!G:G,CRN!T:T,"") -> 0 | Y88: =IF(X88=0,0,_xlfn.XLOOKUP(C88,CLIENT_CODE!B:B,CLIENT_CODE!P:P,0)) -> 0 | Z88: =_xlfn.XLOOKUP(B88,CRN!G:G,CRN!U:U,"") -> 0 | AA88: =IF(X88=0,0,_xlfn.XLOOKUP(C88,CLIENT_CODE!B:B,CLIENT_CODE!P:P,0)) -> 0 | AB88: =_xlfn.XLOOKUP(B88,CRN!G:G,CRN!V:V,"") -> 0 | AC88: =IF(AB88=0,0,_xlfn.XLOOKUP(C88,CLIENT_CODE!B:B,CLIENT_CODE!R:R,0)) -> 0 | AD88: =SUM(E88,G88,I88,K88,M88,O88,Q88,S88,U88,W88,Y88,AA88,AC88,) -> 0
A89: 88 | B89: 2759893 | E89: =IF(D89=0,0,_xlfn.XLOOKUP(C89,CLIENT_CODE!B:B,CLIENT_CODE!F:F,0)) -> 0 | F89: =_xlfn.XLOOKUP(B89,CRN!G:G,CRN!K:K,"") -> 0 | G89: =IF(F89=0,0,_xlfn.XLOOKUP(C89,CLIENT_CODE!B:B,CLIENT_CODE!G:G,0)) -> 0 | H89: =_xlfn.XLOOKUP(B89,CRN!G:G,CRN!L:L,"") -> 1 | I89: =IF(H89=0,0,_xlfn.XLOOKUP(C89,CLIENT_CODE!B:B,CLIENT_CODE!H:H,0)) -> 0 | J89: =_xlfn.XLOOKUP(B89,CRN!G:G,CRN!M:M,"") -> 0 | K89: =IF(J89=0,0,_xlfn.XLOOKUP(C89,CLIENT_CODE!B:B,CLIENT_CODE!I:I,0)) -> 0 | L89: =_xlfn.XLOOKUP(B89,CRN!G:G,CRN!N:N,"") -> 0 | M89: =IF(L89=0,0,_xlfn.XLOOKUP(C89,CLIENT_CODE!B:B,CLIENT_CODE!J:J,0)) -> 0 | N89: =_xlfn.XLOOKUP(B89,CRN!G:G,CRN!O:O,"") -> 0 | O89: =IF(N89=0,0,_xlfn.XLOOKUP(C89,CLIENT_CODE!B:B,CLIENT_CODE!K:K,0)) -> 0 | P89: =_xlfn.XLOOKUP(B89,CRN!G:G,CRN!P:P,"") -> 0 | Q89: =IF(P89=0,0,_xlfn.XLOOKUP(C89,CLIENT_CODE!B:B,CLIENT_CODE!L:L,0)) -> 0 | R89: =_xlfn.XLOOKUP(B89,CRN!G:G,CRN!Q:Q,"") -> 0 | S89: =IF(R89=0,0,_xlfn.XLOOKUP(C89,CLIENT_CODE!B:B,CLIENT_CODE!M:M,0)) -> 0 | T89: =_xlfn.XLOOKUP(B89,CRN!G:G,CRN!R:R,"") -> 0 | U89: =IF(T89=0,0,_xlfn.XLOOKUP(C89,CLIENT_CODE!B:B,CLIENT_CODE!N:N,0)) -> 0 | V89: =_xlfn.XLOOKUP(B89,CRN!G:G,CRN!S:S,"") -> 0 | W89: =IF(V89=0,0,_xlfn.XLOOKUP(C89,CLIENT_CODE!B:B,CLIENT_CODE!O:O,0)) -> 0 | X89: =_xlfn.XLOOKUP(B89,CRN!G:G,CRN!T:T,"") -> 0 | Y89: =IF(X89=0,0,_xlfn.XLOOKUP(C89,CLIENT_CODE!B:B,CLIENT_CODE!P:P,0)) -> 0 | Z89: =_xlfn.XLOOKUP(B89,CRN!G:G,CRN!U:U,"") -> 0 | AA89: =IF(X89=0,0,_xlfn.XLOOKUP(C89,CLIENT_CODE!B:B,CLIENT_CODE!P:P,0)) -> 0 | AB89: =_xlfn.XLOOKUP(B89,CRN!G:G,CRN!V:V,"") -> 0 | AC89: =IF(AB89=0,0,_xlfn.XLOOKUP(C89,CLIENT_CODE!B:B,CLIENT_CODE!R:R,0)) -> 0 | AD89: =SUM(E89,G89,I89,K89,M89,O89,Q89,S89,U89,W89,Y89,AA89,AC89,) -> 0
A90: 89 | E90: =IF(D90=0,0,_xlfn.XLOOKUP(C90,CLIENT_CODE!B:B,CLIENT_CODE!F:F,0)) -> 0 | F90: =_xlfn.XLOOKUP(B90,CRN!G:G,CRN!K:K,"") -> 0 | G90: =IF(F90=0,0,_xlfn.XLOOKUP(C90,CLIENT_CODE!B:B,CLIENT_CODE!G:G,0)) -> 0 | H90: =_xlfn.XLOOKUP(B90,CRN!G:G,CRN!L:L,"") -> 0 | I90: =IF(H90=0,0,_xlfn.XLOOKUP(C90,CLIENT_CODE!B:B,CLIENT_CODE!H:H,0)) -> 0 | J90: =_xlfn.XLOOKUP(B90,CRN!G:G,CRN!M:M,"") -> 0 | K90: =IF(J90=0,0,_xlfn.XLOOKUP(C90,CLIENT_CODE!B:B,CLIENT_CODE!I:I,0)) -> 0 | L90: =_xlfn.XLOOKUP(B90,CRN!G:G,CRN!N:N,"") -> 0 | M90: =IF(L90=0,0,_xlfn.XLOOKUP(C90,CLIENT_CODE!B:B,CLIENT_CODE!J:J,0)) -> 0 | N90: =_xlfn.XLOOKUP(B90,CRN!G:G,CRN!O:O,"") -> 0 | O90: =IF(N90=0,0,_xlfn.XLOOKUP(C90,CLIENT_CODE!B:B,CLIENT_CODE!K:K,0)) -> 0 | P90: =_xlfn.XLOOKUP(B90,CRN!G:G,CRN!P:P,"") -> 0 | Q90: =IF(P90=0,0,_xlfn.XLOOKUP(C90,CLIENT_CODE!B:B,CLIENT_CODE!L:L,0)) -> 0 | R90: =_xlfn.XLOOKUP(B90,CRN!G:G,CRN!Q:Q,"") -> 0 | S90: =IF(R90=0,0,_xlfn.XLOOKUP(C90,CLIENT_CODE!B:B,CLIENT_CODE!M:M,0)) -> 0 | T90: =_xlfn.XLOOKUP(B90,CRN!G:G,CRN!R:R,"") -> 0 | U90: =IF(T90=0,0,_xlfn.XLOOKUP(C90,CLIENT_CODE!B:B,CLIENT_CODE!N:N,0)) -> 0 | V90: =_xlfn.XLOOKUP(B90,CRN!G:G,CRN!S:S,"") -> 0 | W90: =IF(V90=0,0,_xlfn.XLOOKUP(C90,CLIENT_CODE!B:B,CLIENT_CODE!O:O,0)) -> 0 | X90: =_xlfn.XLOOKUP(B90,CRN!G:G,CRN!T:T,"") -> 0 | Y90: =IF(X90=0,0,_xlfn.XLOOKUP(C90,CLIENT_CODE!B:B,CLIENT_CODE!P:P,0)) -> 0 | Z90: =_xlfn.XLOOKUP(B90,CRN!G:G,CRN!U:U,"") -> 0 | AA90: =IF(X90=0,0,_xlfn.XLOOKUP(C90,CLIENT_CODE!B:B,CLIENT_CODE!P:P,0)) -> 0 | AB90: =_xlfn.XLOOKUP(B90,CRN!G:G,CRN!V:V,"") -> 0 | AC90: =IF(AB90=0,0,_xlfn.XLOOKUP(C90,CLIENT_CODE!B:B,CLIENT_CODE!R:R,0)) -> 0 | AD90: =SUM(E90,G90,I90,K90,M90,O90,Q90,S90,U90,W90,Y90,AA90,AC90,) -> 0
A91: 90 | E91: =IF(D91=0,0,_xlfn.XLOOKUP(C91,CLIENT_CODE!B:B,CLIENT_CODE!F:F,0)) -> 0 | F91: =_xlfn.XLOOKUP(B91,CRN!G:G,CRN!K:K,"") -> 0 | G91: =IF(F91=0,0,_xlfn.XLOOKUP(C91,CLIENT_CODE!B:B,CLIENT_CODE!G:G,0)) -> 0 | H91: =_xlfn.XLOOKUP(B91,CRN!G:G,CRN!L:L,"") -> 0 | I91: =IF(H91=0,0,_xlfn.XLOOKUP(C91,CLIENT_CODE!B:B,CLIENT_CODE!H:H,0)) -> 0 | J91: =_xlfn.XLOOKUP(B91,CRN!G:G,CRN!M:M,"") -> 0 | K91: =IF(J91=0,0,_xlfn.XLOOKUP(C91,CLIENT_CODE!B:B,CLIENT_CODE!I:I,0)) -> 0 | L91: =_xlfn.XLOOKUP(B91,CRN!G:G,CRN!N:N,"") -> 0 | M91: =IF(L91=0,0,_xlfn.XLOOKUP(C91,CLIENT_CODE!B:B,CLIENT_CODE!J:J,0)) -> 0 | N91: =_xlfn.XLOOKUP(B91,CRN!G:G,CRN!O:O,"") -> 0 | O91: =IF(N91=0,0,_xlfn.XLOOKUP(C91,CLIENT_CODE!B:B,CLIENT_CODE!K:K,0)) -> 0 | P91: =_xlfn.XLOOKUP(B91,CRN!G:G,CRN!P:P,"") -> 0 | Q91: =IF(P91=0,0,_xlfn.XLOOKUP(C91,CLIENT_CODE!B:B,CLIENT_CODE!L:L,0)) -> 0 | R91: =_xlfn.XLOOKUP(B91,CRN!G:G,CRN!Q:Q,"") -> 0 | S91: =IF(R91=0,0,_xlfn.XLOOKUP(C91,CLIENT_CODE!B:B,CLIENT_CODE!M:M,0)) -> 0 | T91: =_xlfn.XLOOKUP(B91,CRN!G:G,CRN!R:R,"") -> 0 | U91: =IF(T91=0,0,_xlfn.XLOOKUP(C91,CLIENT_CODE!B:B,CLIENT_CODE!N:N,0)) -> 0 | V91: =_xlfn.XLOOKUP(B91,CRN!G:G,CRN!S:S,"") -> 0 | W91: =IF(V91=0,0,_xlfn.XLOOKUP(C91,CLIENT_CODE!B:B,CLIENT_CODE!O:O,0)) -> 0 | X91: =_xlfn.XLOOKUP(B91,CRN!G:G,CRN!T:T,"") -> 0 | Y91: =IF(X91=0,0,_xlfn.XLOOKUP(C91,CLIENT_CODE!B:B,CLIENT_CODE!P:P,0)) -> 0 | Z91: =_xlfn.XLOOKUP(B91,CRN!G:G,CRN!U:U,"") -> 0 | AA91: =IF(X91=0,0,_xlfn.XLOOKUP(C91,CLIENT_CODE!B:B,CLIENT_CODE!P:P,0)) -> 0 | AB91: =_xlfn.XLOOKUP(B91,CRN!G:G,CRN!V:V,"") -> 0 | AC91: =IF(AB91=0,0,_xlfn.XLOOKUP(C91,CLIENT_CODE!B:B,CLIENT_CODE!R:R,0)) -> 0 | AD91: =SUM(E91,G91,I91,K91,M91,O91,Q91,S91,U91,W91,Y91,AA91,AC91,) -> 0
A92: 91 | E92: =IF(D92=0,0,_xlfn.XLOOKUP(C92,CLIENT_CODE!B:B,CLIENT_CODE!F:F,0)) -> 0 | F92: =_xlfn.XLOOKUP(B92,CRN!G:G,CRN!K:K,"") -> 0 | G92: =IF(F92=0,0,_xlfn.XLOOKUP(C92,CLIENT_CODE!B:B,CLIENT_CODE!G:G,0)) -> 0 | H92: =_xlfn.XLOOKUP(B92,CRN!G:G,CRN!L:L,"") -> 0 | I92: =IF(H92=0,0,_xlfn.XLOOKUP(C92,CLIENT_CODE!B:B,CLIENT_CODE!H:H,0)) -> 0 | J92: =_xlfn.XLOOKUP(B92,CRN!G:G,CRN!M:M,"") -> 0 | K92: =IF(J92=0,0,_xlfn.XLOOKUP(C92,CLIENT_CODE!B:B,CLIENT_CODE!I:I,0)) -> 0 | L92: =_xlfn.XLOOKUP(B92,CRN!G:G,CRN!N:N,"") -> 0 | M92: =IF(L92=0,0,_xlfn.XLOOKUP(C92,CLIENT_CODE!B:B,CLIENT_CODE!J:J,0)) -> 0 | N92: =_xlfn.XLOOKUP(B92,CRN!G:G,CRN!O:O,"") -> 0 | O92: =IF(N92=0,0,_xlfn.XLOOKUP(C92,CLIENT_CODE!B:B,CLIENT_CODE!K:K,0)) -> 0 | P92: =_xlfn.XLOOKUP(B92,CRN!G:G,CRN!P:P,"") -> 0 | Q92: =IF(P92=0,0,_xlfn.XLOOKUP(C92,CLIENT_CODE!B:B,CLIENT_CODE!L:L,0)) -> 0 | R92: =_xlfn.XLOOKUP(B92,CRN!G:G,CRN!Q:Q,"") -> 0 | S92: =IF(R92=0,0,_xlfn.XLOOKUP(C92,CLIENT_CODE!B:B,CLIENT_CODE!M:M,0)) -> 0 | T92: =_xlfn.XLOOKUP(B92,CRN!G:G,CRN!R:R,"") -> 0 | U92: =IF(T92=0,0,_xlfn.XLOOKUP(C92,CLIENT_CODE!B:B,CLIENT_CODE!N:N,0)) -> 0 | V92: =_xlfn.XLOOKUP(B92,CRN!G:G,CRN!S:S,"") -> 0 | W92: =IF(V92=0,0,_xlfn.XLOOKUP(C92,CLIENT_CODE!B:B,CLIENT_CODE!O:O,0)) -> 0 | X92: =_xlfn.XLOOKUP(B92,CRN!G:G,CRN!T:T,"") -> 0 | Y92: =IF(X92=0,0,_xlfn.XLOOKUP(C92,CLIENT_CODE!B:B,CLIENT_CODE!P:P,0)) -> 0 | Z92: =_xlfn.XLOOKUP(B92,CRN!G:G,CRN!U:U,"") -> 0 | AA92: =IF(X92=0,0,_xlfn.XLOOKUP(C92,CLIENT_CODE!B:B,CLIENT_CODE!P:P,0)) -> 0 | AB92: =_xlfn.XLOOKUP(B92,CRN!G:G,CRN!V:V,"") -> 0 | AC92: =IF(AB92=0,0,_xlfn.XLOOKUP(C92,CLIENT_CODE!B:B,CLIENT_CODE!R:R,0)) -> 0 | AD92: =SUM(E92,G92,I92,K92,M92,O92,Q92,S92,U92,W92,Y92,AA92,AC92,) -> 0
A93: 92 | E93: =IF(D93=0,0,_xlfn.XLOOKUP(C93,CLIENT_CODE!B:B,CLIENT_CODE!F:F,0)) -> 0 | F93: =_xlfn.XLOOKUP(B93,CRN!G:G,CRN!K:K,"") -> 0 | G93: =IF(F93=0,0,_xlfn.XLOOKUP(C93,CLIENT_CODE!B:B,CLIENT_CODE!G:G,0)) -> 0 | H93: =_xlfn.XLOOKUP(B93,CRN!G:G,CRN!L:L,"") -> 0 | I93: =IF(H93=0,0,_xlfn.XLOOKUP(C93,CLIENT_CODE!B:B,CLIENT_CODE!H:H,0)) -> 0 | J93: =_xlfn.XLOOKUP(B93,CRN!G:G,CRN!M:M,"") -> 0 | K93: =IF(J93=0,0,_xlfn.XLOOKUP(C93,CLIENT_CODE!B:B,CLIENT_CODE!I:I,0)) -> 0 | L93: =_xlfn.XLOOKUP(B93,CRN!G:G,CRN!N:N,"") -> 0 | M93: =IF(L93=0,0,_xlfn.XLOOKUP(C93,CLIENT_CODE!B:B,CLIENT_CODE!J:J,0)) -> 0 | N93: =_xlfn.XLOOKUP(B93,CRN!G:G,CRN!O:O,"") -> 0 | O93: =IF(N93=0,0,_xlfn.XLOOKUP(C93,CLIENT_CODE!B:B,CLIENT_CODE!K:K,0)) -> 0 | P93: =_xlfn.XLOOKUP(B93,CRN!G:G,CRN!P:P,"") -> 0 | Q93: =IF(P93=0,0,_xlfn.XLOOKUP(C93,CLIENT_CODE!B:B,CLIENT_CODE!L:L,0)) -> 0 | R93: =_xlfn.XLOOKUP(B93,CRN!G:G,CRN!Q:Q,"") -> 0 | S93: =IF(R93=0,0,_xlfn.XLOOKUP(C93,CLIENT_CODE!B:B,CLIENT_CODE!M:M,0)) -> 0 | T93: =_xlfn.XLOOKUP(B93,CRN!G:G,CRN!R:R,"") -> 0 | U93: =IF(T93=0,0,_xlfn.XLOOKUP(C93,CLIENT_CODE!B:B,CLIENT_CODE!N:N,0)) -> 0 | V93: =_xlfn.XLOOKUP(B93,CRN!G:G,CRN!S:S,"") -> 0 | W93: =IF(V93=0,0,_xlfn.XLOOKUP(C93,CLIENT_CODE!B:B,CLIENT_CODE!O:O,0)) -> 0 | X93: =_xlfn.XLOOKUP(B93,CRN!G:G,CRN!T:T,"") -> 0 | Y93: =IF(X93=0,0,_xlfn.XLOOKUP(C93,CLIENT_CODE!B:B,CLIENT_CODE!P:P,0)) -> 0 | Z93: =_xlfn.XLOOKUP(B93,CRN!G:G,CRN!U:U,"") -> 0 | AA93: =IF(X93=0,0,_xlfn.XLOOKUP(C93,CLIENT_CODE!B:B,CLIENT_CODE!P:P,0)) -> 0 | AB93: =_xlfn.XLOOKUP(B93,CRN!G:G,CRN!V:V,"") -> 0 | AC93: =IF(AB93=0,0,_xlfn.XLOOKUP(C93,CLIENT_CODE!B:B,CLIENT_CODE!R:R,0)) -> 0 | AD93: =SUM(E93,G93,I93,K93,M93,O93,Q93,S93,U93,W93,Y93,AA93,AC93,) -> 0
A94: 93 | E94: =IF(D94=0,0,_xlfn.XLOOKUP(C94,CLIENT_CODE!B:B,CLIENT_CODE!F:F,0)) -> 0 | F94: =_xlfn.XLOOKUP(B94,CRN!G:G,CRN!K:K,"") -> 0 | G94: =IF(F94=0,0,_xlfn.XLOOKUP(C94,CLIENT_CODE!B:B,CLIENT_CODE!G:G,0)) -> 0 | H94: =_xlfn.XLOOKUP(B94,CRN!G:G,CRN!L:L,"") -> 0 | I94: =IF(H94=0,0,_xlfn.XLOOKUP(C94,CLIENT_CODE!B:B,CLIENT_CODE!H:H,0)) -> 0 | J94: =_xlfn.XLOOKUP(B94,CRN!G:G,CRN!M:M,"") -> 0 | K94: =IF(J94=0,0,_xlfn.XLOOKUP(C94,CLIENT_CODE!B:B,CLIENT_CODE!I:I,0)) -> 0 | L94: =_xlfn.XLOOKUP(B94,CRN!G:G,CRN!N:N,"") -> 0 | M94: =IF(L94=0,0,_xlfn.XLOOKUP(C94,CLIENT_CODE!B:B,CLIENT_CODE!J:J,0)) -> 0 | N94: =_xlfn.XLOOKUP(B94,CRN!G:G,CRN!O:O,"") -> 0 | O94: =IF(N94=0,0,_xlfn.XLOOKUP(C94,CLIENT_CODE!B:B,CLIENT_CODE!K:K,0)) -> 0 | P94: =_xlfn.XLOOKUP(B94,CRN!G:G,CRN!P:P,"") -> 0 | Q94: =IF(P94=0,0,_xlfn.XLOOKUP(C94,CLIENT_CODE!B:B,CLIENT_CODE!L:L,0)) -> 0 | R94: =_xlfn.XLOOKUP(B94,CRN!G:G,CRN!Q:Q,"") -> 0 | S94: =IF(R94=0,0,_xlfn.XLOOKUP(C94,CLIENT_CODE!B:B,CLIENT_CODE!M:M,0)) -> 0 | T94: =_xlfn.XLOOKUP(B94,CRN!G:G,CRN!R:R,"") -> 0 | U94: =IF(T94=0,0,_xlfn.XLOOKUP(C94,CLIENT_CODE!B:B,CLIENT_CODE!N:N,0)) -> 0 | V94: =_xlfn.XLOOKUP(B94,CRN!G:G,CRN!S:S,"") -> 0 | W94: =IF(V94=0,0,_xlfn.XLOOKUP(C94,CLIENT_CODE!B:B,CLIENT_CODE!O:O,0)) -> 0 | X94: =_xlfn.XLOOKUP(B94,CRN!G:G,CRN!T:T,"") -> 0 | Y94: =IF(X94=0,0,_xlfn.XLOOKUP(C94,CLIENT_CODE!B:B,CLIENT_CODE!P:P,0)) -> 0 | Z94: =_xlfn.XLOOKUP(B94,CRN!G:G,CRN!U:U,"") -> 0 | AA94: =IF(X94=0,0,_xlfn.XLOOKUP(C94,CLIENT_CODE!B:B,CLIENT_CODE!P:P,0)) -> 0 | AB94: =_xlfn.XLOOKUP(B94,CRN!G:G,CRN!V:V,"") -> 0 | AC94: =IF(AB94=0,0,_xlfn.XLOOKUP(C94,CLIENT_CODE!B:B,CLIENT_CODE!R:R,0)) -> 0 | AD94: =SUM(E94,G94,I94,K94,M94,O94,Q94,S94,U94,W94,Y94,AA94,AC94,) -> 0
A95: 94 | E95: =IF(D95=0,0,_xlfn.XLOOKUP(C95,CLIENT_CODE!B:B,CLIENT_CODE!F:F,0)) -> 0 | F95: =_xlfn.XLOOKUP(B95,CRN!G:G,CRN!K:K,"") -> 0 | G95: =IF(F95=0,0,_xlfn.XLOOKUP(C95,CLIENT_CODE!B:B,CLIENT_CODE!G:G,0)) -> 0 | H95: =_xlfn.XLOOKUP(B95,CRN!G:G,CRN!L:L,"") -> 0 | I95: =IF(H95=0,0,_xlfn.XLOOKUP(C95,CLIENT_CODE!B:B,CLIENT_CODE!H:H,0)) -> 0 | J95: =_xlfn.XLOOKUP(B95,CRN!G:G,CRN!M:M,"") -> 0 | K95: =IF(J95=0,0,_xlfn.XLOOKUP(C95,CLIENT_CODE!B:B,CLIENT_CODE!I:I,0)) -> 0 | L95: =_xlfn.XLOOKUP(B95,CRN!G:G,CRN!N:N,"") -> 0 | M95: =IF(L95=0,0,_xlfn.XLOOKUP(C95,CLIENT_CODE!B:B,CLIENT_CODE!J:J,0)) -> 0 | N95: =_xlfn.XLOOKUP(B95,CRN!G:G,CRN!O:O,"") -> 0 | O95: =IF(N95=0,0,_xlfn.XLOOKUP(C95,CLIENT_CODE!B:B,CLIENT_CODE!K:K,0)) -> 0 | P95: =_xlfn.XLOOKUP(B95,CRN!G:G,CRN!P:P,"") -> 0 | Q95: =IF(P95=0,0,_xlfn.XLOOKUP(C95,CLIENT_CODE!B:B,CLIENT_CODE!L:L,0)) -> 0 | R95: =_xlfn.XLOOKUP(B95,CRN!G:G,CRN!Q:Q,"") -> 0 | S95: =IF(R95=0,0,_xlfn.XLOOKUP(C95,CLIENT_CODE!B:B,CLIENT_CODE!M:M,0)) -> 0 | T95: =_xlfn.XLOOKUP(B95,CRN!G:G,CRN!R:R,"") -> 0 | U95: =IF(T95=0,0,_xlfn.XLOOKUP(C95,CLIENT_CODE!B:B,CLIENT_CODE!N:N,0)) -> 0 | V95: =_xlfn.XLOOKUP(B95,CRN!G:G,CRN!S:S,"") -> 0 | W95: =IF(V95=0,0,_xlfn.XLOOKUP(C95,CLIENT_CODE!B:B,CLIENT_CODE!O:O,0)) -> 0 | X95: =_xlfn.XLOOKUP(B95,CRN!G:G,CRN!T:T,"") -> 0 | Y95: =IF(X95=0,0,_xlfn.XLOOKUP(C95,CLIENT_CODE!B:B,CLIENT_CODE!P:P,0)) -> 0 | Z95: =_xlfn.XLOOKUP(B95,CRN!G:G,CRN!U:U,"") -> 0 | AA95: =IF(X95=0,0,_xlfn.XLOOKUP(C95,CLIENT_CODE!B:B,CLIENT_CODE!P:P,0)) -> 0 | AB95: =_xlfn.XLOOKUP(B95,CRN!G:G,CRN!V:V,"") -> 0 | AC95: =IF(AB95=0,0,_xlfn.XLOOKUP(C95,CLIENT_CODE!B:B,CLIENT_CODE!R:R,0)) -> 0 | AD95: =SUM(E95,G95,I95,K95,M95,O95,Q95,S95,U95,W95,Y95,AA95,AC95,) -> 0
A96: 95 | E96: =IF(D96=0,0,_xlfn.XLOOKUP(C96,CLIENT_CODE!B:B,CLIENT_CODE!F:F,0)) -> 0 | F96: =_xlfn.XLOOKUP(B96,CRN!G:G,CRN!K:K,"") -> 0 | G96: =IF(F96=0,0,_xlfn.XLOOKUP(C96,CLIENT_CODE!B:B,CLIENT_CODE!G:G,0)) -> 0 | H96: =_xlfn.XLOOKUP(B96,CRN!G:G,CRN!L:L,"") -> 0 | I96: =IF(H96=0,0,_xlfn.XLOOKUP(C96,CLIENT_CODE!B:B,CLIENT_CODE!H:H,0)) -> 0 | J96: =_xlfn.XLOOKUP(B96,CRN!G:G,CRN!M:M,"") -> 0 | K96: =IF(J96=0,0,_xlfn.XLOOKUP(C96,CLIENT_CODE!B:B,CLIENT_CODE!I:I,0)) -> 0 | L96: =_xlfn.XLOOKUP(B96,CRN!G:G,CRN!N:N,"") -> 0 | M96: =IF(L96=0,0,_xlfn.XLOOKUP(C96,CLIENT_CODE!B:B,CLIENT_CODE!J:J,0)) -> 0 | N96: =_xlfn.XLOOKUP(B96,CRN!G:G,CRN!O:O,"") -> 0 | O96: =IF(N96=0,0,_xlfn.XLOOKUP(C96,CLIENT_CODE!B:B,CLIENT_CODE!K:K,0)) -> 0 | P96: =_xlfn.XLOOKUP(B96,CRN!G:G,CRN!P:P,"") -> 0 | Q96: =IF(P96=0,0,_xlfn.XLOOKUP(C96,CLIENT_CODE!B:B,CLIENT_CODE!L:L,0)) -> 0 | R96: =_xlfn.XLOOKUP(B96,CRN!G:G,CRN!Q:Q,"") -> 0 | S96: =IF(R96=0,0,_xlfn.XLOOKUP(C96,CLIENT_CODE!B:B,CLIENT_CODE!M:M,0)) -> 0 | T96: =_xlfn.XLOOKUP(B96,CRN!G:G,CRN!R:R,"") -> 0 | U96: =IF(T96=0,0,_xlfn.XLOOKUP(C96,CLIENT_CODE!B:B,CLIENT_CODE!N:N,0)) -> 0 | V96: =_xlfn.XLOOKUP(B96,CRN!G:G,CRN!S:S,"") -> 0 | W96: =IF(V96=0,0,_xlfn.XLOOKUP(C96,CLIENT_CODE!B:B,CLIENT_CODE!O:O,0)) -> 0 | X96: =_xlfn.XLOOKUP(B96,CRN!G:G,CRN!T:T,"") -> 0 | Y96: =IF(X96=0,0,_xlfn.XLOOKUP(C96,CLIENT_CODE!B:B,CLIENT_CODE!P:P,0)) -> 0 | Z96: =_xlfn.XLOOKUP(B96,CRN!G:G,CRN!U:U,"") -> 0 | AA96: =IF(X96=0,0,_xlfn.XLOOKUP(C96,CLIENT_CODE!B:B,CLIENT_CODE!P:P,0)) -> 0 | AB96: =_xlfn.XLOOKUP(B96,CRN!G:G,CRN!V:V,"") -> 0 | AC96: =IF(AB96=0,0,_xlfn.XLOOKUP(C96,CLIENT_CODE!B:B,CLIENT_CODE!R:R,0)) -> 0 | AD96: =SUM(E96,G96,I96,K96,M96,O96,Q96,S96,U96,W96,Y96,AA96,AC96,) -> 0
A97: 96 | E97: =IF(D97=0,0,_xlfn.XLOOKUP(C97,CLIENT_CODE!B:B,CLIENT_CODE!F:F,0)) -> 0 | F97: =_xlfn.XLOOKUP(B97,CRN!G:G,CRN!K:K,"") -> 0 | G97: =IF(F97=0,0,_xlfn.XLOOKUP(C97,CLIENT_CODE!B:B,CLIENT_CODE!G:G,0)) -> 0 | H97: =_xlfn.XLOOKUP(B97,CRN!G:G,CRN!L:L,"") -> 0 | I97: =IF(H97=0,0,_xlfn.XLOOKUP(C97,CLIENT_CODE!B:B,CLIENT_CODE!H:H,0)) -> 0 | J97: =_xlfn.XLOOKUP(B97,CRN!G:G,CRN!M:M,"") -> 0 | K97: =IF(J97=0,0,_xlfn.XLOOKUP(C97,CLIENT_CODE!B:B,CLIENT_CODE!I:I,0)) -> 0 | L97: =_xlfn.XLOOKUP(B97,CRN!G:G,CRN!N:N,"") -> 0 | M97: =IF(L97=0,0,_xlfn.XLOOKUP(C97,CLIENT_CODE!B:B,CLIENT_CODE!J:J,0)) -> 0 | N97: =_xlfn.XLOOKUP(B97,CRN!G:G,CRN!O:O,"") -> 0 | O97: =IF(N97=0,0,_xlfn.XLOOKUP(C97,CLIENT_CODE!B:B,CLIENT_CODE!K:K,0)) -> 0 | P97: =_xlfn.XLOOKUP(B97,CRN!G:G,CRN!P:P,"") -> 0 | Q97: =IF(P97=0,0,_xlfn.XLOOKUP(C97,CLIENT_CODE!B:B,CLIENT_CODE!L:L,0)) -> 0 | R97: =_xlfn.XLOOKUP(B97,CRN!G:G,CRN!Q:Q,"") -> 0 | S97: =IF(R97=0,0,_xlfn.XLOOKUP(C97,CLIENT_CODE!B:B,CLIENT_CODE!M:M,0)) -> 0 | T97: =_xlfn.XLOOKUP(B97,CRN!G:G,CRN!R:R,"") -> 0 | U97: =IF(T97=0,0,_xlfn.XLOOKUP(C97,CLIENT_CODE!B:B,CLIENT_CODE!N:N,0)) -> 0 | V97: =_xlfn.XLOOKUP(B97,CRN!G:G,CRN!S:S,"") -> 0 | W97: =IF(V97=0,0,_xlfn.XLOOKUP(C97,CLIENT_CODE!B:B,CLIENT_CODE!O:O,0)) -> 0 | X97: =_xlfn.XLOOKUP(B97,CRN!G:G,CRN!T:T,"") -> 0 | Y97: =IF(X97=0,0,_xlfn.XLOOKUP(C97,CLIENT_CODE!B:B,CLIENT_CODE!P:P,0)) -> 0 | Z97: =_xlfn.XLOOKUP(B97,CRN!G:G,CRN!U:U,"") -> 0 | AA97: =IF(X97=0,0,_xlfn.XLOOKUP(C97,CLIENT_CODE!B:B,CLIENT_CODE!P:P,0)) -> 0 | AB97: =_xlfn.XLOOKUP(B97,CRN!G:G,CRN!V:V,"") -> 0 | AC97: =IF(AB97=0,0,_xlfn.XLOOKUP(C97,CLIENT_CODE!B:B,CLIENT_CODE!R:R,0)) -> 0 | AD97: =SUM(E97,G97,I97,K97,M97,O97,Q97,S97,U97,W97,Y97,AA97,AC97,) -> 0
A98: 97 | E98: =IF(D98=0,0,_xlfn.XLOOKUP(C98,CLIENT_CODE!B:B,CLIENT_CODE!F:F,0)) -> 0 | F98: =_xlfn.XLOOKUP(B98,CRN!G:G,CRN!K:K,"") -> 0 | G98: =IF(F98=0,0,_xlfn.XLOOKUP(C98,CLIENT_CODE!B:B,CLIENT_CODE!G:G,0)) -> 0 | H98: =_xlfn.XLOOKUP(B98,CRN!G:G,CRN!L:L,"") -> 0 | I98: =IF(H98=0,0,_xlfn.XLOOKUP(C98,CLIENT_CODE!B:B,CLIENT_CODE!H:H,0)) -> 0 | J98: =_xlfn.XLOOKUP(B98,CRN!G:G,CRN!M:M,"") -> 0 | K98: =IF(J98=0,0,_xlfn.XLOOKUP(C98,CLIENT_CODE!B:B,CLIENT_CODE!I:I,0)) -> 0 | L98: =_xlfn.XLOOKUP(B98,CRN!G:G,CRN!N:N,"") -> 0 | M98: =IF(L98=0,0,_xlfn.XLOOKUP(C98,CLIENT_CODE!B:B,CLIENT_CODE!J:J,0)) -> 0 | N98: =_xlfn.XLOOKUP(B98,CRN!G:G,CRN!O:O,"") -> 0 | O98: =IF(N98=0,0,_xlfn.XLOOKUP(C98,CLIENT_CODE!B:B,CLIENT_CODE!K:K,0)) -> 0 | P98: =_xlfn.XLOOKUP(B98,CRN!G:G,CRN!P:P,"") -> 0 | Q98: =IF(P98=0,0,_xlfn.XLOOKUP(C98,CLIENT_CODE!B:B,CLIENT_CODE!L:L,0)) -> 0 | R98: =_xlfn.XLOOKUP(B98,CRN!G:G,CRN!Q:Q,"") -> 0 | S98: =IF(R98=0,0,_xlfn.XLOOKUP(C98,CLIENT_CODE!B:B,CLIENT_CODE!M:M,0)) -> 0 | T98: =_xlfn.XLOOKUP(B98,CRN!G:G,CRN!R:R,"") -> 0 | U98: =IF(T98=0,0,_xlfn.XLOOKUP(C98,CLIENT_CODE!B:B,CLIENT_CODE!N:N,0)) -> 0 | V98: =_xlfn.XLOOKUP(B98,CRN!G:G,CRN!S:S,"") -> 0 | W98: =IF(V98=0,0,_xlfn.XLOOKUP(C98,CLIENT_CODE!B:B,CLIENT_CODE!O:O,0)) -> 0 | X98: =_xlfn.XLOOKUP(B98,CRN!G:G,CRN!T:T,"") -> 0 | Y98: =IF(X98=0,0,_xlfn.XLOOKUP(C98,CLIENT_CODE!B:B,CLIENT_CODE!P:P,0)) -> 0 | Z98: =_xlfn.XLOOKUP(B98,CRN!G:G,CRN!U:U,"") -> 0 | AA98: =IF(X98=0,0,_xlfn.XLOOKUP(C98,CLIENT_CODE!B:B,CLIENT_CODE!P:P,0)) -> 0 | AB98: =_xlfn.XLOOKUP(B98,CRN!G:G,CRN!V:V,"") -> 0 | AC98: =IF(AB98=0,0,_xlfn.XLOOKUP(C98,CLIENT_CODE!B:B,CLIENT_CODE!R:R,0)) -> 0 | AD98: =SUM(E98,G98,I98,K98,M98,O98,Q98,S98,U98,W98,Y98,AA98,AC98,) -> 0
A99: 98 | E99: =IF(D99=0,0,_xlfn.XLOOKUP(C99,CLIENT_CODE!B:B,CLIENT_CODE!F:F,0)) -> 0 | F99: =_xlfn.XLOOKUP(B99,CRN!G:G,CRN!K:K,"") -> 0 | G99: =IF(F99=0,0,_xlfn.XLOOKUP(C99,CLIENT_CODE!B:B,CLIENT_CODE!G:G,0)) -> 0 | H99: =_xlfn.XLOOKUP(B99,CRN!G:G,CRN!L:L,"") -> 0 | I99: =IF(H99=0,0,_xlfn.XLOOKUP(C99,CLIENT_CODE!B:B,CLIENT_CODE!H:H,0)) -> 0 | J99: =_xlfn.XLOOKUP(B99,CRN!G:G,CRN!M:M,"") -> 0 | K99: =IF(J99=0,0,_xlfn.XLOOKUP(C99,CLIENT_CODE!B:B,CLIENT_CODE!I:I,0)) -> 0 | L99: =_xlfn.XLOOKUP(B99,CRN!G:G,CRN!N:N,"") -> 0 | M99: =IF(L99=0,0,_xlfn.XLOOKUP(C99,CLIENT_CODE!B:B,CLIENT_CODE!J:J,0)) -> 0 | N99: =_xlfn.XLOOKUP(B99,CRN!G:G,CRN!O:O,"") -> 0 | O99: =IF(N99=0,0,_xlfn.XLOOKUP(C99,CLIENT_CODE!B:B,CLIENT_CODE!K:K,0)) -> 0 | P99: =_xlfn.XLOOKUP(B99,CRN!G:G,CRN!P:P,"") -> 0 | Q99: =IF(P99=0,0,_xlfn.XLOOKUP(C99,CLIENT_CODE!B:B,CLIENT_CODE!L:L,0)) -> 0 | R99: =_xlfn.XLOOKUP(B99,CRN!G:G,CRN!Q:Q,"") -> 0 | S99: =IF(R99=0,0,_xlfn.XLOOKUP(C99,CLIENT_CODE!B:B,CLIENT_CODE!M:M,0)) -> 0 | T99: =_xlfn.XLOOKUP(B99,CRN!G:G,CRN!R:R,"") -> 0 | U99: =IF(T99=0,0,_xlfn.XLOOKUP(C99,CLIENT_CODE!B:B,CLIENT_CODE!N:N,0)) -> 0 | V99: =_xlfn.XLOOKUP(B99,CRN!G:G,CRN!S:S,"") -> 0 | W99: =IF(V99=0,0,_xlfn.XLOOKUP(C99,CLIENT_CODE!B:B,CLIENT_CODE!O:O,0)) -> 0 | X99: =_xlfn.XLOOKUP(B99,CRN!G:G,CRN!T:T,"") -> 0 | Y99: =IF(X99=0,0,_xlfn.XLOOKUP(C99,CLIENT_CODE!B:B,CLIENT_CODE!P:P,0)) -> 0 | Z99: =_xlfn.XLOOKUP(B99,CRN!G:G,CRN!U:U,"") -> 0 | AA99: =IF(X99=0,0,_xlfn.XLOOKUP(C99,CLIENT_CODE!B:B,CLIENT_CODE!P:P,0)) -> 0 | AB99: =_xlfn.XLOOKUP(B99,CRN!G:G,CRN!V:V,"") -> 0 | AC99: =IF(AB99=0,0,_xlfn.XLOOKUP(C99,CLIENT_CODE!B:B,CLIENT_CODE!R:R,0)) -> 0 | AD99: =SUM(E99,G99,I99,K99,M99,O99,Q99,S99,U99,W99,Y99,AA99,AC99,) -> 0
A100: 99 | E100: =IF(D100=0,0,_xlfn.XLOOKUP(C100,CLIENT_CODE!B:B,CLIENT_CODE!F:F,0)) -> 0 | F100: =_xlfn.XLOOKUP(B100,CRN!G:G,CRN!K:K,"") -> 0 | G100: =IF(F100=0,0,_xlfn.XLOOKUP(C100,CLIENT_CODE!B:B,CLIENT_CODE!G:G,0)) -> 0 | H100: =_xlfn.XLOOKUP(B100,CRN!G:G,CRN!L:L,"") -> 0 | I100: =IF(H100=0,0,_xlfn.XLOOKUP(C100,CLIENT_CODE!B:B,CLIENT_CODE!H:H,0)) -> 0 | J100: =_xlfn.XLOOKUP(B100,CRN!G:G,CRN!M:M,"") -> 0 | K100: =IF(J100=0,0,_xlfn.XLOOKUP(C100,CLIENT_CODE!B:B,CLIENT_CODE!I:I,0)) -> 0 | L100: =_xlfn.XLOOKUP(B100,CRN!G:G,CRN!N:N,"") -> 0 | M100: =IF(L100=0,0,_xlfn.XLOOKUP(C100,CLIENT_CODE!B:B,CLIENT_CODE!J:J,0)) -> 0 | N100: =_xlfn.XLOOKUP(B100,CRN!G:G,CRN!O:O,"") -> 0 | O100: =IF(N100=0,0,_xlfn.XLOOKUP(C100,CLIENT_CODE!B:B,CLIENT_CODE!K:K,0)) -> 0 | P100: =_xlfn.XLOOKUP(B100,CRN!G:G,CRN!P:P,"") -> 0 | Q100: =IF(P100=0,0,_xlfn.XLOOKUP(C100,CLIENT_CODE!B:B,CLIENT_CODE!L:L,0)) -> 0 | R100: =_xlfn.XLOOKUP(B100,CRN!G:G,CRN!Q:Q,"") -> 0 | S100: =IF(R100=0,0,_xlfn.XLOOKUP(C100,CLIENT_CODE!B:B,CLIENT_CODE!M:M,0)) -> 0 | T100: =_xlfn.XLOOKUP(B100,CRN!G:G,CRN!R:R,"") -> 0 | U100: =IF(T100=0,0,_xlfn.XLOOKUP(C100,CLIENT_CODE!B:B,CLIENT_CODE!N:N,0)) -> 0 | V100: =_xlfn.XLOOKUP(B100,CRN!G:G,CRN!S:S,"") -> 0 | W100: =IF(V100=0,0,_xlfn.XLOOKUP(C100,CLIENT_CODE!B:B,CLIENT_CODE!O:O,0)) -> 0 | X100: =_xlfn.XLOOKUP(B100,CRN!G:G,CRN!T:T,"") -> 0 | Y100: =IF(X100=0,0,_xlfn.XLOOKUP(C100,CLIENT_CODE!B:B,CLIENT_CODE!P:P,0)) -> 0 | Z100: =_xlfn.XLOOKUP(B100,CRN!G:G,CRN!U:U,"") -> 0 | AA100: =IF(X100=0,0,_xlfn.XLOOKUP(C100,CLIENT_CODE!B:B,CLIENT_CODE!P:P,0)) -> 0 | AB100: =_xlfn.XLOOKUP(B100,CRN!G:G,CRN!V:V,"") -> 0 | AC100: =IF(AB100=0,0,_xlfn.XLOOKUP(C100,CLIENT_CODE!B:B,CLIENT_CODE!R:R,0)) -> 0 | AD100: =SUM(E100,G100,I100,K100,M100,O100,Q100,S100,U100,W100,Y100,AA100,AC100,) -> 0
A101: 100 | E101: =IF(D101=0,0,_xlfn.XLOOKUP(C101,CLIENT_CODE!B:B,CLIENT_CODE!F:F,0)) -> 0 | F101: =_xlfn.XLOOKUP(B101,CRN!G:G,CRN!K:K,"") -> 0 | G101: =IF(F101=0,0,_xlfn.XLOOKUP(C101,CLIENT_CODE!B:B,CLIENT_CODE!G:G,0)) -> 0 | H101: =_xlfn.XLOOKUP(B101,CRN!G:G,CRN!L:L,"") -> 0 | I101: =IF(H101=0,0,_xlfn.XLOOKUP(C101,CLIENT_CODE!B:B,CLIENT_CODE!H:H,0)) -> 0 | J101: =_xlfn.XLOOKUP(B101,CRN!G:G,CRN!M:M,"") -> 0 | K101: =IF(J101=0,0,_xlfn.XLOOKUP(C101,CLIENT_CODE!B:B,CLIENT_CODE!I:I,0)) -> 0 | L101: =_xlfn.XLOOKUP(B101,CRN!G:G,CRN!N:N,"") -> 0 | M101: =IF(L101=0,0,_xlfn.XLOOKUP(C101,CLIENT_CODE!B:B,CLIENT_CODE!J:J,0)) -> 0 | N101: =_xlfn.XLOOKUP(B101,CRN!G:G,CRN!O:O,"") -> 0 | O101: =IF(N101=0,0,_xlfn.XLOOKUP(C101,CLIENT_CODE!B:B,CLIENT_CODE!K:K,0)) -> 0 | P101: =_xlfn.XLOOKUP(B101,CRN!G:G,CRN!P:P,"") -> 0 | Q101: =IF(P101=0,0,_xlfn.XLOOKUP(C101,CLIENT_CODE!B:B,CLIENT_CODE!L:L,0)) -> 0 | R101: =_xlfn.XLOOKUP(B101,CRN!G:G,CRN!Q:Q,"") -> 0 | S101: =IF(R101=0,0,_xlfn.XLOOKUP(C101,CLIENT_CODE!B:B,CLIENT_CODE!M:M,0)) -> 0 | T101: =_xlfn.XLOOKUP(B101,CRN!G:G,CRN!R:R,"") -> 0 | U101: =IF(T101=0,0,_xlfn.XLOOKUP(C101,CLIENT_CODE!B:B,CLIENT_CODE!N:N,0)) -> 0 | V101: =_xlfn.XLOOKUP(B101,CRN!G:G,CRN!S:S,"") -> 0 | W101: =IF(V101=0,0,_xlfn.XLOOKUP(C101,CLIENT_CODE!B:B,CLIENT_CODE!O:O,0)) -> 0 | X101: =_xlfn.XLOOKUP(B101,CRN!G:G,CRN!T:T,"") -> 0 | Y101: =IF(X101=0,0,_xlfn.XLOOKUP(C101,CLIENT_CODE!B:B,CLIENT_CODE!P:P,0)) -> 0 | Z101: =_xlfn.XLOOKUP(B101,CRN!G:G,CRN!U:U,"") -> 0 | AA101: =IF(X101=0,0,_xlfn.XLOOKUP(C101,CLIENT_CODE!B:B,CLIENT_CODE!P:P,0)) -> 0 | AB101: =_xlfn.XLOOKUP(B101,CRN!G:G,CRN!V:V,"") -> 0 | AC101: =IF(AB101=0,0,_xlfn.XLOOKUP(C101,CLIENT_CODE!B:B,CLIENT_CODE!R:R,0)) -> 0 | AD101: =SUM(E101,G101,I101,K101,M101,O101,Q101,S101,U101,W101,Y101,AA101,AC101,) -> 0
... A500: 499 | E500: =IF(D500=0,0,_xlfn.XLOOKUP(C500,CLIENT_CODE!B:B,CLIENT_CODE!F:F,0)) -> 0 | F500: =_xlfn.XLOOKUP(B500,CRN!G:G,CRN!K:K,"") -> 0 | G500: =IF(F500=0,0,_xlfn.XLOOKUP(C500,CLIENT_CODE!B:B,CLIENT_CODE!G:G,0)) -> 0 | H500: =_xlfn.XLOOKUP(B500,CRN!G:G,CRN!L:L,"") -> 0 | I500: =IF(H500=0,0,_xlfn.XLOOKUP(C500,CLIENT_CODE!B:B,CLIENT_CODE!H:H,0)) -> 0 | J500: =_xlfn.XLOOKUP(B500,CRN!G:G,CRN!M:M,"") -> 0 | K500: =IF(J500=0,0,_xlfn.XLOOKUP(C500,CLIENT_CODE!B:B,CLIENT_CODE!I:I,0)) -> 0 | L500: =_xlfn.XLOOKUP(B500,CRN!G:G,CRN!N:N,"") -> 0 | M500: =IF(L500=0,0,_xlfn.XLOOKUP(C500,CLIENT_CODE!B:B,CLIENT_CODE!J:J,0)) -> 0 | N500: =_xlfn.XLOOKUP(B500,CRN!G:G,CRN!O:O,"") -> 0 | O500: =IF(N500=0,0,_xlfn.XLOOKUP(C500,CLIENT_CODE!B:B,CLIENT_CODE!K:K,0)) -> 0 | P500: =_xlfn.XLOOKUP(B500,CRN!G:G,CRN!P:P,"") -> 0 | Q500: =IF(P500=0,0,_xlfn.XLOOKUP(C500,CLIENT_CODE!B:B,CLIENT_CODE!L:L,0)) -> 0 | R500: =_xlfn.XLOOKUP(B500,CRN!G:G,CRN!Q:Q,"") -> 0 | S500: =IF(R500=0,0,_xlfn.XLOOKUP(C500,CLIENT_CODE!B:B,CLIENT_CODE!M:M,0)) -> 0 | T500: =_xlfn.XLOOKUP(B500,CRN!G:G,CRN!R:R,"") -> 0 | U500: =IF(T500=0,0,_xlfn.XLOOKUP(C500,CLIENT_CODE!B:B,CLIENT_CODE!N:N,0)) -> 0 | V500: =_xlfn.XLOOKUP(B500,CRN!G:G,CRN!S:S,"") -> 0 | W500: =IF(V500=0,0,_xlfn.XLOOKUP(C500,CLIENT_CODE!B:B,CLIENT_CODE!O:O,0)) -> 0 | X500: =_xlfn.XLOOKUP(B500,CRN!G:G,CRN!T:T,"") -> 0 | Y500: =IF(X500=0,0,_xlfn.XLOOKUP(C500,CLIENT_CODE!B:B,CLIENT_CODE!P:P,0)) -> 0 | Z500: =_xlfn.XLOOKUP(B500,CRN!G:G,CRN!U:U,"") -> 0 | AA500: =IF(X500=0,0,_xlfn.XLOOKUP(C500,CLIENT_CODE!B:B,CLIENT_CODE!P:P,0)) -> 0 | AB500: =_xlfn.XLOOKUP(B500,CRN!G:G,CRN!V:V,"") -> 0 | AC500: =IF(AB500=0,0,_xlfn.XLOOKUP(C500,CLIENT_CODE!B:B,CLIENT_CODE!R:R,0)) -> 0 | AD500: =SUM(E500,G500,I500,K500,M500,O500,Q500,S500,U500,W500,Y500,AA500,AC500,) -> 0

Sheet Back_End_Data
B2: {=_xlfn._xlws.FILTER(_xlfn.CHOOSECOLS(MIS_Backend_Data!B:AC,1,2,4,10), MIS_Backend_Data!E:E<>"")} -> CLAIM NUMBER | C2: CLIENT NAME | D2: CRN | E2: TAT | F2: Full Case Status | G2: Claimant | H2: Income | I2: Insured | J2: 134 Notice | K2: Driver | L2: DL | M2: RC | N2: Permit | O2: Fitness | P2: Spot | Q2: Chargesheet | R2: HOSPITAL | S2: RTI | T2: IR Status | U2: 2 - CP | V2: 1 - CP | W2: Good To Go
B3: C2264103101203-00 | C3: Magma HDI General Insurance Company Ltd | D3: M002-1001-SS-2025 | E3: 152 | F3: =IF(MIS_Backend_Data!O2="", "", MIS_Backend_Data!O2) -> Completed | G3: =IF(MIS_Backend_Data!T2="", "", MIS_Backend_Data!T2) -> Completed | H3: =IF(MIS_Backend_Data!X2="", "", MIS_Backend_Data!X2) -> NA | I3: =IF(MIS_Backend_Data!AC2="", "", MIS_Backend_Data!AC2) -> Completed | J3: =IF(MIS_Backend_Data!AB2="", "", MIS_Backend_Data!AB2) -> NA | K3: =IF(MIS_Backend_Data!AG2="", "", MIS_Backend_Data!AG2) -> NA | L3: =IF(MIS_Backend_Data!AI2="", "", MIS_Backend_Data!AI2) -> NA | M3: =IF(MIS_Backend_Data!AK2="", "", MIS_Backend_Data!AK2) -> NA | N3: =IF(MIS_Backend_Data!AM2="", "", MIS_Backend_Data!AM2) -> NA | O3: =IF(MIS_Backend_Data!AO2="", "", MIS_Backend_Data!AO2) -> NA | P3: =IF(MIS_Backend_Data!AS2="", "", MIS_Backend_Data!AS2) -> Completed | Q3: =IF(MIS_Backend_Data!AX2="", "", MIS_Backend_Data!AX2) -> Completed | R3: =IF(MIS_Backend_Data!BB2="", "", MIS_Backend_Data!BB2) -> NA | S3: =IF(MIS_Backend_Data!AW2="", "", MIS_Backend_Data!AW2) -> NA | T3: =IF(MIS_Backend_Data!N2="Dispatch","Completed","NA") -> Completed | U3: =IF(F3="WIP", IF(COUNTIF(G3:R3, "WIP")=2, 2, ""), "") | V3: =IF(F3="WIP", IF(COUNTIF(G3:R3, "WIP")=1, 1, ""), "") | W3: =IF(OR(F3="WIP",F3="Pending for CS"), IF(COUNTIFS(G3:R3,"<>Completed",G3:R3,"<>NA")=0,"GTG",""), "")
B4: C2264191100006-00 | C4: Magma HDI General Insurance Company Ltd | D4: M002-1002-SS-2025 | E4: 154 | F4: =IF(MIS_Backend_Data!O3="", "", MIS_Backend_Data!O3) -> WIP | G4: =IF(MIS_Backend_Data!T3="", "", MIS_Backend_Data!T3) -> WIP | H4: =IF(MIS_Backend_Data!X3="", "", MIS_Backend_Data!X3) -> NA | I4: =IF(MIS_Backend_Data!AC3="", "", MIS_Backend_Data!AC3) -> WIP | J4: =IF(MIS_Backend_Data!AB3="", "", MIS_Backend_Data!AB3) -> NA | K4: =IF(MIS_Backend_Data!AG3="", "", MIS_Backend_Data!AG3) -> NA | L4: =IF(MIS_Backend_Data!AI3="", "", MIS_Backend_Data!AI3) -> NA | M4: =IF(MIS_Backend_Data!AK3="", "", MIS_Backend_Data!AK3) -> NA | N4: =IF(MIS_Backend_Data!AM3="", "", MIS_Backend_Data!AM3) -> NA | O4: =IF(MIS_Backend_Data!AO3="", "", MIS_Backend_Data!AO3) -> NA | P4: =IF(MIS_Backend_Data!AS3="", "", MIS_Backend_Data!AS3) -> WIP | Q4: =IF(MIS_Backend_Data!AX3="", "", MIS_Backend_Data!AX3) -> Completed | R4: =IF(MIS_Backend_Data!BB3="", "", MIS_Backend_Data!BB3) -> NA | S4: =IF(MIS_Backend_Data!AW3="", "", MIS_Backend_Data!AW3) -> NA | T4: =IF(MIS_Backend_Data!N3="Dispatch","Completed","NA") -> NA | U4: =IF(F4="WIP", IF(COUNTIF(G4:R4, "WIP")=2, 2, ""), "") | V4: =IF(F4="WIP", IF(COUNTIF(G4:R4, "WIP")=1, 1, ""), "") | W4: =IF(OR(F4="WIP",F4="Pending for CS"), IF(COUNTIFS(G4:R4,"<>Completed",G4:R4,"<>NA")=0,"GTG",""), "")
B5: C2264103101217-04 | C5: Magma HDI General Insurance Company Ltd | D5: M002-1003-SS-2025 | E5: 138 | F5: =IF(MIS_Backend_Data!O4="", "", MIS_Backend_Data!O4) -> Completed | G5: =IF(MIS_Backend_Data!T4="", "", MIS_Backend_Data!T4) -> Completed | H5: =IF(MIS_Backend_Data!X4="", "", MIS_Backend_Data!X4) -> NA | I5: =IF(MIS_Backend_Data!AC4="", "", MIS_Backend_Data!AC4) -> Completed | J5: =IF(MIS_Backend_Data!AB4="", "", MIS_Backend_Data!AB4) -> NA | K5: =IF(MIS_Backend_Data!AG4="", "", MIS_Backend_Data!AG4) -> Completed | L5: =IF(MIS_Backend_Data!AI4="", "", MIS_Backend_Data!AI4) -> NA | M5: =IF(MIS_Backend_Data!AK4="", "", MIS_Backend_Data!AK4) -> NA | N5: =IF(MIS_Backend_Data!AM4="", "", MIS_Backend_Data!AM4) -> NA | O5: =IF(MIS_Backend_Data!AO4="", "", MIS_Backend_Data!AO4) -> NA | P5: =IF(MIS_Backend_Data!AS4="", "", MIS_Backend_Data!AS4) -> Completed | Q5: =IF(MIS_Backend_Data!AX4="", "", MIS_Backend_Data!AX4) -> Completed | R5: =IF(MIS_Backend_Data!BB4="", "", MIS_Backend_Data!BB4) -> NA | S5: =IF(MIS_Backend_Data!AW4="", "", MIS_Backend_Data!AW4) -> NA | T5: =IF(MIS_Backend_Data!N4="Dispatch","Completed","NA") -> Completed | U5: =IF(F5="WIP", IF(COUNTIF(G5:R5, "WIP")=2, 2, ""), "") | V5: =IF(F5="WIP", IF(COUNTIF(G5:R5, "WIP")=1, 1, ""), "") | W5: =IF(OR(F5="WIP",F5="Pending for CS"), IF(COUNTIFS(G5:R5,"<>Completed",G5:R5,"<>NA")=0,"GTG",""), "")
B6: MTP-N-2526-002724 | C6: Generali Central Insurance Company Limited | D6: F001-1004-SS-2025 | E6: 28 | F6: =IF(MIS_Backend_Data!O5="", "", MIS_Backend_Data!O5) -> Completed | G6: =IF(MIS_Backend_Data!T5="", "", MIS_Backend_Data!T5) -> Completed | H6: =IF(MIS_Backend_Data!X5="", "", MIS_Backend_Data!X5) -> NA | I6: =IF(MIS_Backend_Data!AC5="", "", MIS_Backend_Data!AC5) -> Completed | J6: =IF(MIS_Backend_Data!AB5="", "", MIS_Backend_Data!AB5) -> NA | K6: =IF(MIS_Backend_Data!AG5="", "", MIS_Backend_Data!AG5) -> Completed | L6: =IF(MIS_Backend_Data!AI5="", "", MIS_Backend_Data!AI5) -> WIP | M6: =IF(MIS_Backend_Data!AK5="", "", MIS_Backend_Data!AK5) -> WIP | N6: =IF(MIS_Backend_Data!AM5="", "", MIS_Backend_Data!AM5) -> NA | O6: =IF(MIS_Backend_Data!AO5="", "", MIS_Backend_Data!AO5) -> NA | P6: =IF(MIS_Backend_Data!AS5="", "", MIS_Backend_Data!AS5) -> Completed | Q6: =IF(MIS_Backend_Data!AX5="", "", MIS_Backend_Data!AX5) -> NA | R6: =IF(MIS_Backend_Data!BB5="", "", MIS_Backend_Data!BB5) -> Completed | S6: =IF(MIS_Backend_Data!AW5="", "", MIS_Backend_Data!AW5) -> NA | T6: =IF(MIS_Backend_Data!N5="Dispatch","Completed","NA") -> Completed | U6: =IF(F6="WIP", IF(COUNTIF(G6:R6, "WIP")=2, 2, ""), "") | V6: =IF(F6="WIP", IF(COUNTIF(G6:R6, "WIP")=1, 1, ""), "") | W6: =IF(OR(F6="WIP",F6="Pending for CS"), IF(COUNTIFS(G6:R6,"<>Completed",G6:R6,"<>NA")=0,"GTG",""), "")
B7: MTP-N-2526-002725 | C7: Generali Central Insurance Company Limited | D7: F001-1005-SS-2025 | E7: 28 | F7: =IF(MIS_Backend_Data!O6="", "", MIS_Backend_Data!O6) -> Completed | G7: =IF(MIS_Backend_Data!T6="", "", MIS_Backend_Data!T6) -> Completed | H7: =IF(MIS_Backend_Data!X6="", "", MIS_Backend_Data!X6) -> NA | I7: =IF(MIS_Backend_Data!AC6="", "", MIS_Backend_Data!AC6) -> NA | J7: =IF(MIS_Backend_Data!AB6="", "", MIS_Backend_Data!AB6) -> NA | K7: =IF(MIS_Backend_Data!AG6="", "", MIS_Backend_Data!AG6) -> NA | L7: =IF(MIS_Backend_Data!AI6="", "", MIS_Backend_Data!AI6) -> NA | M7: =IF(MIS_Backend_Data!AK6="", "", MIS_Backend_Data!AK6) -> NA | N7: =IF(MIS_Backend_Data!AM6="", "", MIS_Backend_Data!AM6) -> NA | O7: =IF(MIS_Backend_Data!AO6="", "", MIS_Backend_Data!AO6) -> NA | P7: =IF(MIS_Backend_Data!AS6="", "", MIS_Backend_Data!AS6) -> STOP | Q7: =IF(MIS_Backend_Data!AX6="", "", MIS_Backend_Data!AX6) -> NA | R7: =IF(MIS_Backend_Data!BB6="", "", MIS_Backend_Data!BB6) -> NA | S7: =IF(MIS_Backend_Data!AW6="", "", MIS_Backend_Data!AW6) | T7: =IF(MIS_Backend_Data!N6="Dispatch","Completed","NA") -> Completed | U7: =IF(F7="WIP", IF(COUNTIF(G7:R7, "WIP")=2, 2, ""), "") | V7: =IF(F7="WIP", IF(COUNTIF(G7:R7, "WIP")=1, 1, ""), "") | W7: =IF(OR(F7="WIP",F7="Pending for CS"), IF(COUNTIFS(G7:R7,"<>Completed",G7:R7,"<>NA")=0,"GTG",""), "")
B8: MTP-N-2526-002726 | C8: Generali Central Insurance Company Limited | D8: F001-1006-SS-2025 | E8: 28 | F8: =IF(MIS_Backend_Data!O7="", "", MIS_Backend_Data!O7) -> Completed | G8: =IF(MIS_Backend_Data!T7="", "", MIS_Backend_Data!T7) -> Completed | H8: =IF(MIS_Backend_Data!X7="", "", MIS_Backend_Data!X7) -> NA | I8: =IF(MIS_Backend_Data!AC7="", "", MIS_Backend_Data!AC7) -> Completed | J8: =IF(MIS_Backend_Data!AB7="", "", MIS_Backend_Data!AB7) -> NA | K8: =IF(MIS_Backend_Data!AG7="", "", MIS_Backend_Data!AG7) -> NA | L8: =IF(MIS_Backend_Data!AI7="", "", MIS_Backend_Data!AI7) -> NA | M8: =IF(MIS_Backend_Data!AK7="", "", MIS_Backend_Data!AK7) -> NA | N8: =IF(MIS_Backend_Data!AM7="", "", MIS_Backend_Data!AM7) -> NA | O8: =IF(MIS_Backend_Data!AO7="", "", MIS_Backend_Data!AO7) -> NA | P8: =IF(MIS_Backend_Data!AS7="", "", MIS_Backend_Data!AS7) -> Completed | Q8: =IF(MIS_Backend_Data!AX7="", "", MIS_Backend_Data!AX7) -> Completed | R8: =IF(MIS_Backend_Data!BB7="", "", MIS_Backend_Data!BB7) -> NA | S8: =IF(MIS_Backend_Data!AW7="", "", MIS_Backend_Data!AW7) | T8: =IF(MIS_Backend_Data!N7="Dispatch","Completed","NA") -> Completed | U8: =IF(F8="WIP", IF(COUNTIF(G8:R8, "WIP")=2, 2, ""), "") | V8: =IF(F8="WIP", IF(COUNTIF(G8:R8, "WIP")=1, 1, ""), "") | W8: =IF(OR(F8="WIP",F8="Pending for CS"), IF(COUNTIFS(G8:R8,"<>Completed",G8:R8,"<>NA")=0,"GTG",""), "")
B9: MTP-N-2526-002845 | C9: Generali Central Insurance Company Limited | D9: F001-1007-SS-2025 | E9: 51 | F9: =IF(MIS_Backend_Data!O8="", "", MIS_Backend_Data!O8) -> Pending CS | G9: =IF(MIS_Backend_Data!T8="", "", MIS_Backend_Data!T8) -> NA | H9: =IF(MIS_Backend_Data!X8="", "", MIS_Backend_Data!X8) -> NA | I9: =IF(MIS_Backend_Data!AC8="", "", MIS_Backend_Data!AC8) -> Completed | J9: =IF(MIS_Backend_Data!AB8="", "", MIS_Backend_Data!AB8) -> NA | K9: =IF(MIS_Backend_Data!AG8="", "", MIS_Backend_Data!AG8) -> Completed | L9: =IF(MIS_Backend_Data!AI8="", "", MIS_Backend_Data!AI8) -> Completed | M9: =IF(MIS_Backend_Data!AK8="", "", MIS_Backend_Data!AK8) -> Completed | N9: =IF(MIS_Backend_Data!AM8="", "", MIS_Backend_Data!AM8) -> NA | O9: =IF(MIS_Backend_Data!AO8="", "", MIS_Backend_Data!AO8) -> NA | P9: =IF(MIS_Backend_Data!AS8="", "", MIS_Backend_Data!AS8) -> Completed | Q9: =IF(MIS_Backend_Data!AX8="", "", MIS_Backend_Data!AX8) -> WIP | R9: =IF(MIS_Backend_Data!BB8="", "", MIS_Backend_Data!BB8) -> NA | S9: =IF(MIS_Backend_Data!AW8="", "", MIS_Backend_Data!AW8) | T9: =IF(MIS_Backend_Data!N8="Dispatch","Completed","NA") -> NA | U9: =IF(F9="WIP", IF(COUNTIF(G9:R9, "WIP")=2, 2, ""), "") | V9: =IF(F9="WIP", IF(COUNTIF(G9:R9, "WIP")=1, 1, ""), "") | W9: =IF(OR(F9="WIP",F9="Pending for CS"), IF(COUNTIFS(G9:R9,"<>Completed",G9:R9,"<>NA")=0,"GTG",""), "")
B10: MTP-N-2526-003010 | C10: Generali Central Insurance Company Limited | D10: F001-1008-SS-2025 | E10: 66 | F10: =IF(MIS_Backend_Data!O9="", "", MIS_Backend_Data!O9) -> Completed | G10: =IF(MIS_Backend_Data!T9="", "", MIS_Backend_Data!T9) -> Completed | H10: =IF(MIS_Backend_Data!X9="", "", MIS_Backend_Data!X9) -> NA | I10: =IF(MIS_Backend_Data!AC9="", "", MIS_Backend_Data!AC9) -> Completed | J10: =IF(MIS_Backend_Data!AB9="", "", MIS_Backend_Data!AB9) -> NA | K10: =IF(MIS_Backend_Data!AG9="", "", MIS_Backend_Data!AG9) -> Completed | L10: =IF(MIS_Backend_Data!AI9="", "", MIS_Backend_Data!AI9) -> Completed | M10: =IF(MIS_Backend_Data!AK9="", "", MIS_Backend_Data!AK9) -> Completed | N10: =IF(MIS_Backend_Data!AM9="", "", MIS_Backend_Data!AM9) -> Completed | O10: =IF(MIS_Backend_Data!AO9="", "", MIS_Backend_Data!AO9) -> NA | P10: =IF(MIS_Backend_Data!AS9="", "", MIS_Backend_Data!AS9) -> Completed | Q10: =IF(MIS_Backend_Data!AX9="", "", MIS_Backend_Data!AX9) -> Completed | R10: =IF(MIS_Backend_Data!BB9="", "", MIS_Backend_Data!BB9) -> NA | S10: =IF(MIS_Backend_Data!AW9="", "", MIS_Backend_Data!AW9) -> NA | T10: =IF(MIS_Backend_Data!N9="Dispatch","Completed","NA") -> Completed | U10: =IF(F10="WIP", IF(COUNTIF(G10:R10, "WIP")=2, 2, ""), "") | V10: =IF(F10="WIP", IF(COUNTIF(G10:R10, "WIP")=1, 1, ""), "") | W10: =IF(OR(F10="WIP",F10="Pending for CS"), IF(COUNTIFS(G10:R10,"<>Completed",G10:R10,"<>NA")=0,"GTG",""), "")
B11: 2025209111 | C11: Indusind General Insurance Co Ltd | D11: R001-1009-SS-2025 | E11: 54 | F11: =IF(MIS_Backend_Data!O10="", "", MIS_Backend_Data!O10) -> Completed | G11: =IF(MIS_Backend_Data!T10="", "", MIS_Backend_Data!T10) -> Completed | H11: =IF(MIS_Backend_Data!X10="", "", MIS_Backend_Data!X10) -> NA | I11: =IF(MIS_Backend_Data!AC10="", "", MIS_Backend_Data!AC10) -> Completed | J11: =IF(MIS_Backend_Data!AB10="", "", MIS_Backend_Data!AB10) -> NA | K11: =IF(MIS_Backend_Data!AG10="", "", MIS_Backend_Data!AG10) -> Completed | L11: =IF(MIS_Backend_Data!AI10="", "", MIS_Backend_Data!AI10) -> NA | M11: =IF(MIS_Backend_Data!AK10="", "", MIS_Backend_Data!AK10) -> NA | N11: =IF(MIS_Backend_Data!AM10="", "", MIS_Backend_Data!AM10) -> NA | O11: =IF(MIS_Backend_Data!AO10="", "", MIS_Backend_Data!AO10) -> NA | P11: =IF(MIS_Backend_Data!AS10="", "", MIS_Backend_Data!AS10) -> Completed | Q11: =IF(MIS_Backend_Data!AX10="", "", MIS_Backend_Data!AX10) -> Completed | R11: =IF(MIS_Backend_Data!BB10="", "", MIS_Backend_Data!BB10) -> NA | S11: =IF(MIS_Backend_Data!AW10="", "", MIS_Backend_Data!AW10) | T11: =IF(MIS_Backend_Data!N10="Dispatch","Completed","NA") -> Completed | U11: =IF(F11="WIP", IF(COUNTIF(G11:R11, "WIP")=2, 2, ""), "") | V11: =IF(F11="WIP", IF(COUNTIF(G11:R11, "WIP")=1, 1, ""), "") | W11: =IF(OR(F11="WIP",F11="Pending for CS"), IF(COUNTIFS(G11:R11,"<>Completed",G11:R11,"<>NA")=0,"GTG",""), "")
B12: CN064878 | C12: Generali Central Insurance Company Limited | D12: F001-1010-SS-2025 | E12: 54 | F12: =IF(MIS_Backend_Data!O11="", "", MIS_Backend_Data!O11) -> Completed | G12: =IF(MIS_Backend_Data!T11="", "", MIS_Backend_Data!T11) -> Completed | H12: =IF(MIS_Backend_Data!X11="", "", MIS_Backend_Data!X11) -> Completed | I12: =IF(MIS_Backend_Data!AC11="", "", MIS_Backend_Data!AC11) -> Completed | J12: =IF(MIS_Backend_Data!AB11="", "", MIS_Backend_Data!AB11) -> NA | K12: =IF(MIS_Backend_Data!AG11="", "", MIS_Backend_Data!AG11) -> Completed | L12: =IF(MIS_Backend_Data!AI11="", "", MIS_Backend_Data!AI11) -> Completed | M12: =IF(MIS_Backend_Data!AK11="", "", MIS_Backend_Data!AK11) -> WIP | N12: =IF(MIS_Backend_Data!AM11="", "", MIS_Backend_Data!AM11) -> NA | O12: =IF(MIS_Backend_Data!AO11="", "", MIS_Backend_Data!AO11) -> NA | P12: =IF(MIS_Backend_Data!AS11="", "", MIS_Backend_Data!AS11) -> Completed | Q12: =IF(MIS_Backend_Data!AX11="", "", MIS_Backend_Data!AX11) -> Completed | R12: =IF(MIS_Backend_Data!BB11="", "", MIS_Backend_Data!BB11) -> Completed | S12: =IF(MIS_Backend_Data!AW11="", "", MIS_Backend_Data!AW11) | T12: =IF(MIS_Backend_Data!N11="Dispatch","Completed","NA") -> Completed | U12: =IF(F12="WIP", IF(COUNTIF(G12:R12, "WIP")=2, 2, ""), "") | V12: =IF(F12="WIP", IF(COUNTIF(G12:R12, "WIP")=1, 1, ""), "") | W12: =IF(OR(F12="WIP",F12="Pending for CS"), IF(COUNTIFS(G12:R12,"<>Completed",G12:R12,"<>NA")=0,"GTG",""), "")
B13: 2025201119 | C13: Indusind General Insurance Co Ltd | D13: R001-1011-SS-2025 | E13: 111 | F13: =IF(MIS_Backend_Data!O12="", "", MIS_Backend_Data!O12) -> Pending CS | G13: =IF(MIS_Backend_Data!T12="", "", MIS_Backend_Data!T12) -> NA | H13: =IF(MIS_Backend_Data!X12="", "", MIS_Backend_Data!X12) -> NA | I13: =IF(MIS_Backend_Data!AC12="", "", MIS_Backend_Data!AC12) -> NA | J13: =IF(MIS_Backend_Data!AB12="", "", MIS_Backend_Data!AB12) -> NA | K13: =IF(MIS_Backend_Data!AG12="", "", MIS_Backend_Data!AG12) -> NA | L13: =IF(MIS_Backend_Data!AI12="", "", MIS_Backend_Data!AI12) -> NA | M13: =IF(MIS_Backend_Data!AK12="", "", MIS_Backend_Data!AK12) -> NA | N13: =IF(MIS_Backend_Data!AM12="", "", MIS_Backend_Data!AM12) -> NA | O13: =IF(MIS_Backend_Data!AO12="", "", MIS_Backend_Data!AO12) -> NA | P13: =IF(MIS_Backend_Data!AS12="", "", MIS_Backend_Data!AS12) -> NA | Q13: =IF(MIS_Backend_Data!AX12="", "", MIS_Backend_Data!AX12) -> WIP | R13: =IF(MIS_Backend_Data!BB12="", "", MIS_Backend_Data!BB12) -> NI | S13: =IF(MIS_Backend_Data!AW12="", "", MIS_Backend_Data!AW12) | T13: =IF(MIS_Backend_Data!N12="Dispatch","Completed","NA") -> NA | U13: =IF(F13="WIP", IF(COUNTIF(G13:R13, "WIP")=2, 2, ""), "") | V13: =IF(F13="WIP", IF(COUNTIF(G13:R13, "WIP")=1, 1, ""), "") | W13: =IF(OR(F13="WIP",F13="Pending for CS"), IF(COUNTIFS(G13:R13,"<>Completed",G13:R13,"<>NA")=0,"GTG",""), "")
B14: 2025210107 | C14: Indusind General Insurance Co Ltd | D14: R001-1012-SS-2025 | E14: 59 | F14: =IF(MIS_Backend_Data!O13="", "", MIS_Backend_Data!O13) -> Completed | G14: =IF(MIS_Backend_Data!T13="", "", MIS_Backend_Data!T13) -> Completed | H14: =IF(MIS_Backend_Data!X13="", "", MIS_Backend_Data!X13) -> NA | I14: =IF(MIS_Backend_Data!AC13="", "", MIS_Backend_Data!AC13) -> Completed | J14: =IF(MIS_Backend_Data!AB13="", "", MIS_Backend_Data!AB13) -> NA | K14: =IF(MIS_Backend_Data!AG13="", "", MIS_Backend_Data!AG13) -> Completed | L14: =IF(MIS_Backend_Data!AI13="", "", MIS_Backend_Data!AI13) -> NA | M14: =IF(MIS_Backend_Data!AK13="", "", MIS_Backend_Data!AK13) -> NA | N14: =IF(MIS_Backend_Data!AM13="", "", MIS_Backend_Data!AM13) -> NA | O14: =IF(MIS_Backend_Data!AO13="", "", MIS_Backend_Data!AO13) -> NA | P14: =IF(MIS_Backend_Data!AS13="", "", MIS_Backend_Data!AS13) -> Completed | Q14: =IF(MIS_Backend_Data!AX13="", "", MIS_Backend_Data!AX13) -> Completed | R14: =IF(MIS_Backend_Data!BB13="", "", MIS_Backend_Data!BB13) -> NA | S14: =IF(MIS_Backend_Data!AW13="", "", MIS_Backend_Data!AW13) | T14: =IF(MIS_Backend_Data!N13="Dispatch","Completed","NA") -> Completed | U14: =IF(F14="WIP", IF(COUNTIF(G14:R14, "WIP")=2, 2, ""), "") | V14: =IF(F14="WIP", IF(COUNTIF(G14:R14, "WIP")=1, 1, ""), "") | W14: =IF(OR(F14="WIP",F14="Pending for CS"), IF(COUNTIFS(G14:R14,"<>Completed",G14:R14,"<>NA")=0,"GTG",""), "")
... B49: 2025212053 | C49: Indusind General Insurance Co Ltd | D49: R001-1047-SS-2025 | E49: 66 | F49: =IF(MIS_Backend_Data!O48="", "", MIS_Backend_Data!O48) -> WIP | G49: =IF(MIS_Backend_Data!T48="", "", MIS_Backend_Data!T48) -> Completed | H49: =IF(MIS_Backend_Data!X48="", "", MIS_Backend_Data!X48) -> NA | I49: =IF(MIS_Backend_Data!AC48="", "", MIS_Backend_Data!AC48) -> WIP | J49: =IF(MIS_Backend_Data!AB48="", "", MIS_Backend_Data!AB48) -> NA | K49: =IF(MIS_Backend_Data!AG48="", "", MIS_Backend_Data!AG48) -> Completed | L49: =IF(MIS_Backend_Data!AI48="", "", MIS_Backend_Data!AI48) -> NA | M49: =IF(MIS_Backend_Data!AK48="", "", MIS_Backend_Data!AK48) -> NA | N49: =IF(MIS_Backend_Data!AM48="", "", MIS_Backend_Data!AM48) -> NA | O49: =IF(MIS_Backend_Data!AO48="", "", MIS_Backend_Data!AO48) -> NA | P49: =IF(MIS_Backend_Data!AS48="", "", MIS_Backend_Data!AS48) -> WIP | Q49: =IF(MIS_Backend_Data!AX48="", "", MIS_Backend_Data!AX48) -> WIP | R49: =IF(MIS_Backend_Data!BB48="", "", MIS_Backend_Data!BB48) -> NA | S49: =IF(MIS_Backend_Data!AW48="", "", MIS_Backend_Data!AW48) -> NA | T49: =IF(MIS_Backend_Data!N48="Dispatch","Completed","NA") -> NA | U49: =IF(F49="WIP", IF(COUNTIF(G49:R49, "WIP")=2, 2, ""), "") | V49: =IF(F49="WIP", IF(COUNTIF(G49:R49, "WIP")=1, 1, ""), "") | W49: =IF(OR(F49="WIP",F49="Pending for CS"), IF(COUNTIFS(G49:R49,"<>Completed",G49:R49,"<>NA")=0,"GTG",""), "")
B50: 2025212050 | C50: Indusind General Insurance Co Ltd | D50: R001-1048-SS-2025 | E50: 66 | F50: =IF(MIS_Backend_Data!O49="", "", MIS_Backend_Data!O49) -> WIP | G50: =IF(MIS_Backend_Data!T49="", "", MIS_Backend_Data!T49) -> Completed | H50: =IF(MIS_Backend_Data!X49="", "", MIS_Backend_Data!X49) -> NA | I50: =IF(MIS_Backend_Data!AC49="", "", MIS_Backend_Data!AC49) -> Completed | J50: =IF(MIS_Backend_Data!AB49="", "", MIS_Backend_Data!AB49) -> NA | K50: =IF(MIS_Backend_Data!AG49="", "", MIS_Backend_Data!AG49) -> Completed | L50: =IF(MIS_Backend_Data!AI49="", "", MIS_Backend_Data!AI49) -> NA | M50: =IF(MIS_Backend_Data!AK49="", "", MIS_Backend_Data!AK49) -> NA | N50: =IF(MIS_Backend_Data!AM49="", "", MIS_Backend_Data!AM49) -> NA | O50: =IF(MIS_Backend_Data!AO49="", "", MIS_Backend_Data!AO49) -> NA | P50: =IF(MIS_Backend_Data!AS49="", "", MIS_Backend_Data!AS49) -> Completed | Q50: =IF(MIS_Backend_Data!AX49="", "", MIS_Backend_Data!AX49) -> Completed | R50: =IF(MIS_Backend_Data!BB49="", "", MIS_Backend_Data!BB49) -> NA | S50: =IF(MIS_Backend_Data!AW49="", "", MIS_Backend_Data!AW49) -> NA | T50: =IF(MIS_Backend_Data!N49="Dispatch","Completed","NA") -> NA | U50: =IF(F50="WIP", IF(COUNTIF(G50:R50, "WIP")=2, 2, ""), "") | V50: =IF(F50="WIP", IF(COUNTIF(G50:R50, "WIP")=1, 1, ""), "") | W50: =IF(OR(F50="WIP",F50="Pending for CS"), IF(COUNTIFS(G50:R50,"<>Completed",G50:R50,"<>NA")=0,"GTG",""), "") -> GTG
B51: 2025212047 | C51: Indusind General Insurance Co Ltd | D51: R001-1049-SS-2025 | E51: 66 | F51: =IF(MIS_Backend_Data!O50="", "", MIS_Backend_Data!O50) -> Pending CS | G51: =IF(MIS_Backend_Data!T50="", "", MIS_Backend_Data!T50) -> Completed | H51: =IF(MIS_Backend_Data!X50="", "", MIS_Backend_Data!X50) -> NA | I51: =IF(MIS_Backend_Data!AC50="", "", MIS_Backend_Data!AC50) -> Completed | J51: =IF(MIS_Backend_Data!AB50="", "", MIS_Backend_Data!AB50) -> NA | K51: =IF(MIS_Backend_Data!AG50="", "", MIS_Backend_Data!AG50) -> Completed | L51: =IF(MIS_Backend_Data!AI50="", "", MIS_Backend_Data!AI50) -> NA | M51: =IF(MIS_Backend_Data!AK50="", "", MIS_Backend_Data!AK50) -> NA | N51: =IF(MIS_Backend_Data!AM50="", "", MIS_Backend_Data!AM50) -> NA | O51: =IF(MIS_Backend_Data!AO50="", "", MIS_Backend_Data!AO50) -> NA | P51: =IF(MIS_Backend_Data!AS50="", "", MIS_Backend_Data!AS50) -> Completed | Q51: =IF(MIS_Backend_Data!AX50="", "", MIS_Backend_Data!AX50) -> NI | R51: =IF(MIS_Backend_Data!BB50="", "", MIS_Backend_Data!BB50) -> NA | S51: =IF(MIS_Backend_Data!AW50="", "", MIS_Backend_Data!AW50) -> NA | T51: =IF(MIS_Backend_Data!N50="Dispatch","Completed","NA") -> NA | U51: =IF(F51="WIP", IF(COUNTIF(G51:R51, "WIP")=2, 2, ""), "") | V51: =IF(F51="WIP", IF(COUNTIF(G51:R51, "WIP")=1, 1, ""), "") | W51: =IF(OR(F51="WIP",F51="Pending for CS"), IF(COUNTIFS(G51:R51,"<>Completed",G51:R51,"<>NA")=0,"GTG",""), "")
B52: MTP-N-2526-004166 | C52: Generali Central Insurance Company Limited | D52: F001-1050-SS-2025 | E52: 46 | F52: =IF(MIS_Backend_Data!O51="", "", MIS_Backend_Data!O51) -> Completed | G52: =IF(MIS_Backend_Data!T51="", "", MIS_Backend_Data!T51) -> Completed | H52: =IF(MIS_Backend_Data!X51="", "", MIS_Backend_Data!X51) -> WIP | I52: =IF(MIS_Backend_Data!AC51="", "", MIS_Backend_Data!AC51) -> NA | J52: =IF(MIS_Backend_Data!AB51="", "", MIS_Backend_Data!AB51) -> NA | K52: =IF(MIS_Backend_Data!AG51="", "", MIS_Backend_Data!AG51) -> NA | L52: =IF(MIS_Backend_Data!AI51="", "", MIS_Backend_Data!AI51) -> NA | M52: =IF(MIS_Backend_Data!AK51="", "", MIS_Backend_Data!AK51) -> NA | N52: =IF(MIS_Backend_Data!AM51="", "", MIS_Backend_Data!AM51) -> NA | O52: =IF(MIS_Backend_Data!AO51="", "", MIS_Backend_Data!AO51) -> NA | P52: =IF(MIS_Backend_Data!AS51="", "", MIS_Backend_Data!AS51) -> NA | Q52: =IF(MIS_Backend_Data!AX51="", "", MIS_Backend_Data!AX51) -> NA | R52: =IF(MIS_Backend_Data!BB51="", "", MIS_Backend_Data!BB51) -> WIP | S52: =IF(MIS_Backend_Data!AW51="", "", MIS_Backend_Data!AW51) -> NA | T52: =IF(MIS_Backend_Data!N51="Dispatch","Completed","NA") -> NA | U52: =IF(F52="WIP", IF(COUNTIF(G52:R52, "WIP")=2, 2, ""), "") | V52: =IF(F52="WIP", IF(COUNTIF(G52:R52, "WIP")=1, 1, ""), "") | W52: =IF(OR(F52="WIP",F52="Pending for CS"), IF(COUNTIFS(G52:R52,"<>Completed",G52:R52,"<>NA")=0,"GTG",""), "")
B53: 2025212181 | C53: Indusind General Insurance Co Ltd | D53: R001-1051-SS-2025 | E53: 63 | F53: =IF(MIS_Backend_Data!O52="", "", MIS_Backend_Data!O52) -> Pending CS | G53: =IF(MIS_Backend_Data!T52="", "", MIS_Backend_Data!T52) -> Completed | H53: =IF(MIS_Backend_Data!X52="", "", MIS_Backend_Data!X52) -> NA | I53: =IF(MIS_Backend_Data!AC52="", "", MIS_Backend_Data!AC52) -> Completed | J53: =IF(MIS_Backend_Data!AB52="", "", MIS_Backend_Data!AB52) -> NA | K53: =IF(MIS_Backend_Data!AG52="", "", MIS_Backend_Data!AG52) -> Completed | L53: =IF(MIS_Backend_Data!AI52="", "", MIS_Backend_Data!AI52) -> NA | M53: =IF(MIS_Backend_Data!AK52="", "", MIS_Backend_Data!AK52) -> NA | N53: =IF(MIS_Backend_Data!AM52="", "", MIS_Backend_Data!AM52) -> NA | O53: =IF(MIS_Backend_Data!AO52="", "", MIS_Backend_Data!AO52) -> NA | P53: =IF(MIS_Backend_Data!AS52="", "", MIS_Backend_Data!AS52) -> Completed | Q53: =IF(MIS_Backend_Data!AX52="", "", MIS_Backend_Data!AX52) -> NI | R53: =IF(MIS_Backend_Data!BB52="", "", MIS_Backend_Data!BB52) -> NA | S53: =IF(MIS_Backend_Data!AW52="", "", MIS_Backend_Data!AW52) -> NA | T53: =IF(MIS_Backend_Data!N52="Dispatch","Completed","NA") -> NA | U53: =IF(F53="WIP", IF(COUNTIF(G53:R53, "WIP")=2, 2, ""), "") | V53: =IF(F53="WIP", IF(COUNTIF(G53:R53, "WIP")=1, 1, ""), "") | W53: =IF(OR(F53="WIP",F53="Pending for CS"), IF(COUNTIFS(G53:R53,"<>Completed",G53:R53,"<>NA")=0,"GTG",""), "")
B54: 2025212170 | C54: Indusind General Insurance Co Ltd | D54: R001-1052-SS-2025 | E54: 58 | F54: =IF(MIS_Backend_Data!O53="", "", MIS_Backend_Data!O53) -> Completed | G54: =IF(MIS_Backend_Data!T53="", "", MIS_Backend_Data!T53) -> Completed | H54: =IF(MIS_Backend_Data!X53="", "", MIS_Backend_Data!X53) -> NA | I54: =IF(MIS_Backend_Data!AC53="", "", MIS_Backend_Data!AC53) -> Completed | J54: =IF(MIS_Backend_Data!AB53="", "", MIS_Backend_Data!AB53) -> NA | K54: =IF(MIS_Backend_Data!AG53="", "", MIS_Backend_Data!AG53) -> Completed | L54: =IF(MIS_Backend_Data!AI53="", "", MIS_Backend_Data!AI53) -> NA | M54: =IF(MIS_Backend_Data!AK53="", "", MIS_Backend_Data!AK53) -> NA | N54: =IF(MIS_Backend_Data!AM53="", "", MIS_Backend_Data!AM53) -> NA | O54: =IF(MIS_Backend_Data!AO53="", "", MIS_Backend_Data!AO53) -> NA | P54: =IF(MIS_Backend_Data!AS53="", "", MIS_Backend_Data!AS53) -> Completed | Q54: =IF(MIS_Backend_Data!AX53="", "", MIS_Backend_Data!AX53) -> Completed | R54: =IF(MIS_Backend_Data!BB53="", "", MIS_Backend_Data!BB53) -> NA | S54: =IF(MIS_Backend_Data!AW53="", "", MIS_Backend_Data!AW53) -> NA | T54: =IF(MIS_Backend_Data!N53="Dispatch","Completed","NA") -> NA | U54: =IF(F54="WIP", IF(COUNTIF(G54:R54, "WIP")=2, 2, ""), "") | V54: =IF(F54="WIP", IF(COUNTIF(G54:R54, "WIP")=1, 1, ""), "") | W54: =IF(OR(F54="WIP",F54="Pending for CS"), IF(COUNTIFS(G54:R54,"<>Completed",G54:R54,"<>NA")=0,"GTG",""), "")
B55: 2025212168 | C55: Indusind General Insurance Co Ltd | D55: R001-1053-SS-2025 | E55: 63 | F55: =IF(MIS_Backend_Data!O54="", "", MIS_Backend_Data!O54) -> Pending CS | G55: =IF(MIS_Backend_Data!T54="", "", MIS_Backend_Data!T54) -> Completed | H55: =IF(MIS_Backend_Data!X54="", "", MIS_Backend_Data!X54) -> NA | I55: =IF(MIS_Backend_Data!AC54="", "", MIS_Backend_Data!AC54) -> Completed | J55: =IF(MIS_Backend_Data!AB54="", "", MIS_Backend_Data!AB54) -> NA | K55: =IF(MIS_Backend_Data!AG54="", "", MIS_Backend_Data!AG54) -> Completed | L55: =IF(MIS_Backend_Data!AI54="", "", MIS_Backend_Data!AI54) -> NA | M55: =IF(MIS_Backend_Data!AK54="", "", MIS_Backend_Data!AK54) -> NA | N55: =IF(MIS_Backend_Data!AM54="", "", MIS_Backend_Data!AM54) -> NA | O55: =IF(MIS_Backend_Data!AO54="", "", MIS_Backend_Data!AO54) -> NA | P55: =IF(MIS_Backend_Data!AS54="", "", MIS_Backend_Data!AS54) -> Completed | Q55: =IF(MIS_Backend_Data!AX54="", "", MIS_Backend_Data!AX54) -> WIP | R55: =IF(MIS_Backend_Data!BB54="", "", MIS_Backend_Data!BB54) -> NA | S55: =IF(MIS_Backend_Data!AW54="", "", MIS_Backend_Data!AW54) -> NA | T55: =IF(MIS_Backend_Data!N54="Dispatch","Completed","NA") -> NA | U55: =IF(F55="WIP", IF(COUNTIF(G55:R55, "WIP")=2, 2, ""), "") | V55: =IF(F55="WIP", IF(COUNTIF(G55:R55, "WIP")=1, 1, ""), "") | W55: =IF(OR(F55="WIP",F55="Pending for CS"), IF(COUNTIFS(G55:R55,"<>Completed",G55:R55,"<>NA")=0,"GTG",""), "")
B56: 2025212148 | C56: Indusind General Insurance Co Ltd | D56: R001-1054-SS-2025 | E56: 63 | F56: =IF(MIS_Backend_Data!O55="", "", MIS_Backend_Data!O55) -> Pending CS | G56: =IF(MIS_Backend_Data!T55="", "", MIS_Backend_Data!T55) -> Completed | H56: =IF(MIS_Backend_Data!X55="", "", MIS_Backend_Data!X55) -> NA | I56: =IF(MIS_Backend_Data!AC55="", "", MIS_Backend_Data!AC55) -> Completed | J56: =IF(MIS_Backend_Data!AB55="", "", MIS_Backend_Data!AB55) -> NA | K56: =IF(MIS_Backend_Data!AG55="", "", MIS_Backend_Data!AG55) -> Completed | L56: =IF(MIS_Backend_Data!AI55="", "", MIS_Backend_Data!AI55) -> NA | M56: =IF(MIS_Backend_Data!AK55="", "", MIS_Backend_Data!AK55) -> NA | N56: =IF(MIS_Backend_Data!AM55="", "", MIS_Backend_Data!AM55) -> NA | O56: =IF(MIS_Backend_Data!AO55="", "", MIS_Backend_Data!AO55) -> NA | P56: =IF(MIS_Backend_Data!AS55="", "", MIS_Backend_Data!AS55) -> Completed | Q56: =IF(MIS_Backend_Data!AX55="", "", MIS_Backend_Data!AX55) -> WIP | R56: =IF(MIS_Backend_Data!BB55="", "", MIS_Backend_Data!BB55) -> NA | S56: =IF(MIS_Backend_Data!AW55="", "", MIS_Backend_Data!AW55) -> NA | T56: =IF(MIS_Backend_Data!N55="Dispatch","Completed","NA") -> NA | U56: =IF(F56="WIP", IF(COUNTIF(G56:R56, "WIP")=2, 2, ""), "") | V56: =IF(F56="WIP", IF(COUNTIF(G56:R56, "WIP")=1, 1, ""), "") | W56: =IF(OR(F56="WIP",F56="Pending for CS"), IF(COUNTIFS(G56:R56,"<>Completed",G56:R56,"<>NA")=0,"GTG",""), "")
B57: 2025212191 | C57: Indusind General Insurance Co Ltd | D57: R001-1055-SS-2025 | E57: 63 | F57: =IF(MIS_Backend_Data!O56="", "", MIS_Backend_Data!O56) -> WIP | G57: =IF(MIS_Backend_Data!T56="", "", MIS_Backend_Data!T56) -> WIP | H57: =IF(MIS_Backend_Data!X56="", "", MIS_Backend_Data!X56) -> NA | I57: =IF(MIS_Backend_Data!AC56="", "", MIS_Backend_Data!AC56) -> WIP | J57: =IF(MIS_Backend_Data!AB56="", "", MIS_Backend_Data!AB56) -> NA | K57: =IF(MIS_Backend_Data!AG56="", "", MIS_Backend_Data!AG56) -> WIP | L57: =IF(MIS_Backend_Data!AI56="", "", MIS_Backend_Data!AI56) -> NA | M57: =IF(MIS_Backend_Data!AK56="", "", MIS_Backend_Data!AK56) -> NA | N57: =IF(MIS_Backend_Data!AM56="", "", MIS_Backend_Data!AM56) -> NA | O57: =IF(MIS_Backend_Data!AO56="", "", MIS_Backend_Data!AO56) -> NA | P57: =IF(MIS_Backend_Data!AS56="", "", MIS_Backend_Data!AS56) -> WIP | Q57: =IF(MIS_Backend_Data!AX56="", "", MIS_Backend_Data!AX56) -> NA | R57: =IF(MIS_Backend_Data!BB56="", "", MIS_Backend_Data!BB56) -> NA | S57: =IF(MIS_Backend_Data!AW56="", "", MIS_Backend_Data!AW56) -> NA | T57: =IF(MIS_Backend_Data!N56="Dispatch","Completed","NA") -> NA | U57: =IF(F57="WIP", IF(COUNTIF(G57:R57, "WIP")=2, 2, ""), "") | V57: =IF(F57="WIP", IF(COUNTIF(G57:R57, "WIP")=1, 1, ""), "") | W57: =IF(OR(F57="WIP",F57="Pending for CS"), IF(COUNTIFS(G57:R57,"<>Completed",G57:R57,"<>NA")=0,"GTG",""), "")
B58: 2025212189 | C58: Indusind General Insurance Co Ltd | D58: R001-1056-SS-2025 | E58: 63 | F58: =IF(MIS_Backend_Data!O57="", "", MIS_Backend_Data!O57) -> WIP | G58: =IF(MIS_Backend_Data!T57="", "", MIS_Backend_Data!T57) -> WIP | H58: =IF(MIS_Backend_Data!X57="", "", MIS_Backend_Data!X57) -> NA | I58: =IF(MIS_Backend_Data!AC57="", "", MIS_Backend_Data!AC57) -> WIP | J58: =IF(MIS_Backend_Data!AB57="", "", MIS_Backend_Data!AB57) -> NA | K58: =IF(MIS_Backend_Data!AG57="", "", MIS_Backend_Data!AG57) -> WIP | L58: =IF(MIS_Backend_Data!AI57="", "", MIS_Backend_Data!AI57) -> NA | M58: =IF(MIS_Backend_Data!AK57="", "", MIS_Backend_Data!AK57) -> NA | N58: =IF(MIS_Backend_Data!AM57="", "", MIS_Backend_Data!AM57) -> NA | O58: =IF(MIS_Backend_Data!AO57="", "", MIS_Backend_Data!AO57) -> NA | P58: =IF(MIS_Backend_Data!AS57="", "", MIS_Backend_Data!AS57) -> Completed | Q58: =IF(MIS_Backend_Data!AX57="", "", MIS_Backend_Data!AX57) -> STOP | R58: =IF(MIS_Backend_Data!BB57="", "", MIS_Backend_Data!BB57) -> NA | S58: =IF(MIS_Backend_Data!AW57="", "", MIS_Backend_Data!AW57) -> NA | T58: =IF(MIS_Backend_Data!N57="Dispatch","Completed","NA") -> NA | U58: =IF(F58="WIP", IF(COUNTIF(G58:R58, "WIP")=2, 2, ""), "") | V58: =IF(F58="WIP", IF(COUNTIF(G58:R58, "WIP")=1, 1, ""), "") | W58: =IF(OR(F58="WIP",F58="Pending for CS"), IF(COUNTIFS(G58:R58,"<>Completed",G58:R58,"<>NA")=0,"GTG",""), "")
B59: 2025212179 | C59: Indusind General Insurance Co Ltd | D59: R001-1057-SS-2025 | E59: 63 | F59: =IF(MIS_Backend_Data!O58="", "", MIS_Backend_Data!O58) -> IR - Wiritng | G59: =IF(MIS_Backend_Data!T58="", "", MIS_Backend_Data!T58) -> Completed | H59: =IF(MIS_Backend_Data!X58="", "", MIS_Backend_Data!X58) -> NA | I59: =IF(MIS_Backend_Data!AC58="", "", MIS_Backend_Data!AC58) -> Completed | J59: =IF(MIS_Backend_Data!AB58="", "", MIS_Backend_Data!AB58) -> NA | K59: =IF(MIS_Backend_Data!AG58="", "", MIS_Backend_Data!AG58) -> Completed | L59: =IF(MIS_Backend_Data!AI58="", "", MIS_Backend_Data!AI58) -> NA | M59: =IF(MIS_Backend_Data!AK58="", "", MIS_Backend_Data!AK58) -> NA | N59: =IF(MIS_Backend_Data!AM58="", "", MIS_Backend_Data!AM58) -> NA | O59: =IF(MIS_Backend_Data!AO58="", "", MIS_Backend_Data!AO58) -> NA | P59: =IF(MIS_Backend_Data!AS58="", "", MIS_Backend_Data!AS58) -> Completed | Q59: =IF(MIS_Backend_Data!AX58="", "", MIS_Backend_Data!AX58) -> Not Filed | R59: =IF(MIS_Backend_Data!BB58="", "", MIS_Backend_Data!BB58) -> NA | S59: =IF(MIS_Backend_Data!AW58="", "", MIS_Backend_Data!AW58) -> NA | T59: =IF(MIS_Backend_Data!N58="Dispatch","Completed","NA") -> NA | U59: =IF(F59="WIP", IF(COUNTIF(G59:R59, "WIP")=2, 2, ""), "") | V59: =IF(F59="WIP", IF(COUNTIF(G59:R59, "WIP")=1, 1, ""), "") | W59: =IF(OR(F59="WIP",F59="Pending for CS"), IF(COUNTIFS(G59:R59,"<>Completed",G59:R59,"<>NA")=0,"GTG",""), "")
B60: 2025212145 | C60: Indusind General Insurance Co Ltd | D60: R001-1058-SS-2025 | E60: 63 | F60: =IF(MIS_Backend_Data!O59="", "", MIS_Backend_Data!O59) -> Pending CS | G60: =IF(MIS_Backend_Data!T59="", "", MIS_Backend_Data!T59) -> Completed | H60: =IF(MIS_Backend_Data!X59="", "", MIS_Backend_Data!X59) -> NA | I60: =IF(MIS_Backend_Data!AC59="", "", MIS_Backend_Data!AC59) -> Completed | J60: =IF(MIS_Backend_Data!AB59="", "", MIS_Backend_Data!AB59) -> NA | K60: =IF(MIS_Backend_Data!AG59="", "", MIS_Backend_Data!AG59) -> Completed | L60: =IF(MIS_Backend_Data!AI59="", "", MIS_Backend_Data!AI59) -> NA | M60: =IF(MIS_Backend_Data!AK59="", "", MIS_Backend_Data!AK59) -> NA | N60: =IF(MIS_Backend_Data!AM59="", "", MIS_Backend_Data!AM59) -> NA | O60: =IF(MIS_Backend_Data!AO59="", "", MIS_Backend_Data!AO59) -> NA | P60: =IF(MIS_Backend_Data!AS59="", "", MIS_Backend_Data!AS59) -> Completed | Q60: =IF(MIS_Backend_Data!AX59="", "", MIS_Backend_Data!AX59) -> NA | R60: =IF(MIS_Backend_Data!BB59="", "", MIS_Backend_Data!BB59) -> NA | S60: =IF(MIS_Backend_Data!AW59="", "", MIS_Backend_Data!AW59) -> NA | T60: =IF(MIS_Backend_Data!N59="Dispatch","Completed","NA") -> NA | U60: =IF(F60="WIP", IF(COUNTIF(G60:R60, "WIP")=2, 2, ""), "") | V60: =IF(F60="WIP", IF(COUNTIF(G60:R60, "WIP")=1, 1, ""), "") | W60: =IF(OR(F60="WIP",F60="Pending for CS"), IF(COUNTIFS(G60:R60,"<>Completed",G60:R60,"<>NA")=0,"GTG",""), "")
B61: 2025212140 | C61: Indusind General Insurance Co Ltd | D61: R001-1059-SS-2025 | E61: 57 | F61: =IF(MIS_Backend_Data!O60="", "", MIS_Backend_Data!O60) -> Completed | G61: =IF(MIS_Backend_Data!T60="", "", MIS_Backend_Data!T60) -> Completed | H61: =IF(MIS_Backend_Data!X60="", "", MIS_Backend_Data!X60) -> NA | I61: =IF(MIS_Backend_Data!AC60="", "", MIS_Backend_Data!AC60) -> Completed | J61: =IF(MIS_Backend_Data!AB60="", "", MIS_Backend_Data!AB60) -> NA | K61: =IF(MIS_Backend_Data!AG60="", "", MIS_Backend_Data!AG60) -> NA | L61: =IF(MIS_Backend_Data!AI60="", "", MIS_Backend_Data!AI60) -> NA | M61: =IF(MIS_Backend_Data!AK60="", "", MIS_Backend_Data!AK60) -> NA | N61: =IF(MIS_Backend_Data!AM60="", "", MIS_Backend_Data!AM60) -> NA | O61: =IF(MIS_Backend_Data!AO60="", "", MIS_Backend_Data!AO60) -> NA | P61: =IF(MIS_Backend_Data!AS60="", "", MIS_Backend_Data!AS60) -> Completed | Q61: =IF(MIS_Backend_Data!AX60="", "", MIS_Backend_Data!AX60) -> Completed | R61: =IF(MIS_Backend_Data!BB60="", "", MIS_Backend_Data!BB60) -> NA | S61: =IF(MIS_Backend_Data!AW60="", "", MIS_Backend_Data!AW60) -> NA | T61: =IF(MIS_Backend_Data!N60="Dispatch","Completed","NA") -> NA | U61: =IF(F61="WIP", IF(COUNTIF(G61:R61, "WIP")=2, 2, ""), "") | V61: =IF(F61="WIP", IF(COUNTIF(G61:R61, "WIP")=1, 1, ""), "") | W61: =IF(OR(F61="WIP",F61="Pending for CS"), IF(COUNTIFS(G61:R61,"<>Completed",G61:R61,"<>NA")=0,"GTG",""), "")
B62: 2025212028 | C62: Indusind General Insurance Co Ltd | D62: R001-1060-SS-2025 | E62: 51 | F62: =IF(MIS_Backend_Data!O61="", "", MIS_Backend_Data!O61) -> Completed | G62: =IF(MIS_Backend_Data!T61="", "", MIS_Backend_Data!T61) -> NA | H62: =IF(MIS_Backend_Data!X61="", "", MIS_Backend_Data!X61) -> NA | I62: =IF(MIS_Backend_Data!AC61="", "", MIS_Backend_Data!AC61) -> Completed | J62: =IF(MIS_Backend_Data!AB61="", "", MIS_Backend_Data!AB61) -> NA | K62: =IF(MIS_Backend_Data!AG61="", "", MIS_Backend_Data!AG61) -> NA | L62: =IF(MIS_Backend_Data!AI61="", "", MIS_Backend_Data!AI61) -> NA | M62: =IF(MIS_Backend_Data!AK61="", "", MIS_Backend_Data!AK61) -> NA | N62: =IF(MIS_Backend_Data!AM61="", "", MIS_Backend_Data!AM61) -> NA | O62: =IF(MIS_Backend_Data!AO61="", "", MIS_Backend_Data!AO61) -> NA | P62: =IF(MIS_Backend_Data!AS61="", "", MIS_Backend_Data!AS61) -> NA | Q62: =IF(MIS_Backend_Data!AX61="", "", MIS_Backend_Data!AX61) -> NA | R62: =IF(MIS_Backend_Data!BB61="", "", MIS_Backend_Data!BB61) -> NA | S62: =IF(MIS_Backend_Data!AW61="", "", MIS_Backend_Data!AW61) -> NA | T62: =IF(MIS_Backend_Data!N61="Dispatch","Completed","NA") -> Completed | U62: =IF(F62="WIP", IF(COUNTIF(G62:R62, "WIP")=2, 2, ""), "") | V62: =IF(F62="WIP", IF(COUNTIF(G62:R62, "WIP")=1, 1, ""), "") | W62: =IF(OR(F62="WIP",F62="Pending for CS"), IF(COUNTIFS(G62:R62,"<>Completed",G62:R62,"<>NA")=0,"GTG",""), "")
... B210: 2024213331 | C210: Indusind General Insurance Co Ltd | D210: R001-1208-SS-2025 | E210: 49 | F210: =IF(MIS_Backend_Data!O209="", "", MIS_Backend_Data!O209) -> Completed | G210: =IF(MIS_Backend_Data!T209="", "", MIS_Backend_Data!T209) -> Completed | H210: =IF(MIS_Backend_Data!X209="", "", MIS_Backend_Data!X209) -> NA | I210: =IF(MIS_Backend_Data!AC209="", "", MIS_Backend_Data!AC209) -> NA | J210: =IF(MIS_Backend_Data!AB209="", "", MIS_Backend_Data!AB209) | K210: =IF(MIS_Backend_Data!AG209="", "", MIS_Backend_Data!AG209) -> NA | L210: =IF(MIS_Backend_Data!AI209="", "", MIS_Backend_Data!AI209) | M210: =IF(MIS_Backend_Data!AK209="", "", MIS_Backend_Data!AK209) | N210: =IF(MIS_Backend_Data!AM209="", "", MIS_Backend_Data!AM209) | O210: =IF(MIS_Backend_Data!AO209="", "", MIS_Backend_Data!AO209) | P210: =IF(MIS_Backend_Data!AS209="", "", MIS_Backend_Data!AS209) -> NA | Q210: =IF(MIS_Backend_Data!AX209="", "", MIS_Backend_Data!AX209) -> NA | R210: =IF(MIS_Backend_Data!BB209="", "", MIS_Backend_Data!BB209) -> NA | S210: =IF(MIS_Backend_Data!AW209="", "", MIS_Backend_Data!AW209) | T210: =IF(MIS_Backend_Data!N209="Dispatch","Completed","NA") -> Completed | U210: =IF(F210="WIP", IF(COUNTIF(G210:R210, "WIP")=2, 2, ""), "") | V210: =IF(F210="WIP", IF(COUNTIF(G210:R210, "WIP")=1, 1, ""), "") | W210: =IF(OR(F210="WIP",F210="Pending for CS"), IF(COUNTIFS(G210:R210,"<>Completed",G210:R210,"<>NA")=0,"GTG",""), "")
B211: 2024210698 | C211: Indusind General Insurance Co Ltd | D211: R001-1209-SS-2025 | E211: 466 | F211: =IF(MIS_Backend_Data!O210="", "", MIS_Backend_Data!O210) -> Completed | G211: =IF(MIS_Backend_Data!T210="", "", MIS_Backend_Data!T210) -> Completed | H211: =IF(MIS_Backend_Data!X210="", "", MIS_Backend_Data!X210) -> NA | I211: =IF(MIS_Backend_Data!AC210="", "", MIS_Backend_Data!AC210) -> Completed | J211: =IF(MIS_Backend_Data!AB210="", "", MIS_Backend_Data!AB210) -> NA | K211: =IF(MIS_Backend_Data!AG210="", "", MIS_Backend_Data!AG210) -> NA | L211: =IF(MIS_Backend_Data!AI210="", "", MIS_Backend_Data!AI210) -> NA | M211: =IF(MIS_Backend_Data!AK210="", "", MIS_Backend_Data!AK210) -> NA | N211: =IF(MIS_Backend_Data!AM210="", "", MIS_Backend_Data!AM210) -> NA | O211: =IF(MIS_Backend_Data!AO210="", "", MIS_Backend_Data!AO210) -> NA | P211: =IF(MIS_Backend_Data!AS210="", "", MIS_Backend_Data!AS210) -> Completed | Q211: =IF(MIS_Backend_Data!AX210="", "", MIS_Backend_Data!AX210) -> STOP | R211: =IF(MIS_Backend_Data!BB210="", "", MIS_Backend_Data!BB210) -> NA | S211: =IF(MIS_Backend_Data!AW210="", "", MIS_Backend_Data!AW210) -> NA | T211: =IF(MIS_Backend_Data!N210="Dispatch","Completed","NA") -> Completed | U211: =IF(F211="WIP", IF(COUNTIF(G211:R211, "WIP")=2, 2, ""), "") | V211: =IF(F211="WIP", IF(COUNTIF(G211:R211, "WIP")=1, 1, ""), "") | W211: =IF(OR(F211="WIP",F211="Pending for CS"), IF(COUNTIFS(G211:R211,"<>Completed",G211:R211,"<>NA")=0,"GTG",""), "")
B212: 2759892 | C212: SBI General Insurance Company Ltd | D212: S002-1210-SS-2025 | E212: 10 | F212: =IF(MIS_Backend_Data!O211="", "", MIS_Backend_Data!O211) -> WIP | G212: =IF(MIS_Backend_Data!T211="", "", MIS_Backend_Data!T211) -> NI | H212: =IF(MIS_Backend_Data!X211="", "", MIS_Backend_Data!X211) -> NA | I212: =IF(MIS_Backend_Data!AC211="", "", MIS_Backend_Data!AC211) -> NI | J212: =IF(MIS_Backend_Data!AB211="", "", MIS_Backend_Data!AB211) -> NA | K212: =IF(MIS_Backend_Data!AG211="", "", MIS_Backend_Data!AG211) -> NI | L212: =IF(MIS_Backend_Data!AI211="", "", MIS_Backend_Data!AI211) -> NA | M212: =IF(MIS_Backend_Data!AK211="", "", MIS_Backend_Data!AK211) -> NA | N212: =IF(MIS_Backend_Data!AM211="", "", MIS_Backend_Data!AM211) -> NA | O212: =IF(MIS_Backend_Data!AO211="", "", MIS_Backend_Data!AO211) -> NA | P212: =IF(MIS_Backend_Data!AS211="", "", MIS_Backend_Data!AS211) -> NI | Q212: =IF(MIS_Backend_Data!AX211="", "", MIS_Backend_Data!AX211) -> NI | R212: =IF(MIS_Backend_Data!BB211="", "", MIS_Backend_Data!BB211) -> NA | S212: =IF(MIS_Backend_Data!AW211="", "", MIS_Backend_Data!AW211) -> NA | T212: =IF(MIS_Backend_Data!N211="Dispatch","Completed","NA") -> NA | U212: =IF(F212="WIP", IF(COUNTIF(G212:R212, "WIP")=2, 2, ""), "") | V212: =IF(F212="WIP", IF(COUNTIF(G212:R212, "WIP")=1, 1, ""), "") | W212: =IF(OR(F212="WIP",F212="Pending for CS"), IF(COUNTIFS(G212:R212,"<>Completed",G212:R212,"<>NA")=0,"GTG",""), "")
B213: 2759893 | C213: SBI General Insurance Company Ltd | D213: S002-1211-SS-2025 | E213: 10 | F213: =IF(MIS_Backend_Data!O212="", "", MIS_Backend_Data!O212) -> WIP | G213: =IF(MIS_Backend_Data!T212="", "", MIS_Backend_Data!T212) -> NI | H213: =IF(MIS_Backend_Data!X212="", "", MIS_Backend_Data!X212) -> NA | I213: =IF(MIS_Backend_Data!AC212="", "", MIS_Backend_Data!AC212) -> NA | J213: =IF(MIS_Backend_Data!AB212="", "", MIS_Backend_Data!AB212) -> NA | K213: =IF(MIS_Backend_Data!AG212="", "", MIS_Backend_Data!AG212) -> NA | L213: =IF(MIS_Backend_Data!AI212="", "", MIS_Backend_Data!AI212) -> NA | M213: =IF(MIS_Backend_Data!AK212="", "", MIS_Backend_Data!AK212) -> NA | N213: =IF(MIS_Backend_Data!AM212="", "", MIS_Backend_Data!AM212) -> NA | O213: =IF(MIS_Backend_Data!AO212="", "", MIS_Backend_Data!AO212) -> NA | P213: =IF(MIS_Backend_Data!AS212="", "", MIS_Backend_Data!AS212) -> NA | Q213: =IF(MIS_Backend_Data!AX212="", "", MIS_Backend_Data!AX212) -> NA | R213: =IF(MIS_Backend_Data!BB212="", "", MIS_Backend_Data!BB212) -> NA | S213: =IF(MIS_Backend_Data!AW212="", "", MIS_Backend_Data!AW212) -> NA | T213: =IF(MIS_Backend_Data!N212="Dispatch","Completed","NA") -> NA | U213: =IF(F213="WIP", IF(COUNTIF(G213:R213, "WIP")=2, 2, ""), "") | V213: =IF(F213="WIP", IF(COUNTIF(G213:R213, "WIP")=1, 1, ""), "") | W213: =IF(OR(F213="WIP",F213="Pending for CS"), IF(COUNTIFS(G213:R213,"<>Completed",G213:R213,"<>NA")=0,"GTG",""), "")
B214: 2024213740 | C214: Indusind General Insurance Co Ltd | D214: R001-1212-SS-2025 | E214: 9 | F214: =IF(MIS_Backend_Data!O213="", "", MIS_Backend_Data!O213) -> NI | G214: =IF(MIS_Backend_Data!T213="", "", MIS_Backend_Data!T213) -> NA | H214: =IF(MIS_Backend_Data!X213="", "", MIS_Backend_Data!X213) -> NA | I214: =IF(MIS_Backend_Data!AC213="", "", MIS_Backend_Data!AC213) -> NA | J214: =IF(MIS_Backend_Data!AB213="", "", MIS_Backend_Data!AB213) -> NA | K214: =IF(MIS_Backend_Data!AG213="", "", MIS_Backend_Data!AG213) -> NA | L214: =IF(MIS_Backend_Data!AI213="", "", MIS_Backend_Data!AI213) -> NA | M214: =IF(MIS_Backend_Data!AK213="", "", MIS_Backend_Data!AK213) -> NA | N214: =IF(MIS_Backend_Data!AM213="", "", MIS_Backend_Data!AM213) -> NA | O214: =IF(MIS_Backend_Data!AO213="", "", MIS_Backend_Data!AO213) -> NA | P214: =IF(MIS_Backend_Data!AS213="", "", MIS_Backend_Data!AS213) -> NA | Q214: =IF(MIS_Backend_Data!AX213="", "", MIS_Backend_Data!AX213) -> NI | R214: =IF(MIS_Backend_Data!BB213="", "", MIS_Backend_Data!BB213) -> NA | S214: =IF(MIS_Backend_Data!AW213="", "", MIS_Backend_Data!AW213) -> NA | T214: =IF(MIS_Backend_Data!N213="Dispatch","Completed","NA") -> NA | U214: =IF(F214="WIP", IF(COUNTIF(G214:R214, "WIP")=2, 2, ""), "") | V214: =IF(F214="WIP", IF(COUNTIF(G214:R214, "WIP")=1, 1, ""), "") | W214: =IF(OR(F214="WIP",F214="Pending for CS"), IF(COUNTIFS(G214:R214,"<>Completed",G214:R214,"<>NA")=0,"GTG",""), "")
B215: 2024205707 | C215: Indusind General Insurance Co Ltd | D215: R001-1213-SS-2025 | E215: 6 | F215: =IF(MIS_Backend_Data!O214="", "", MIS_Backend_Data!O214) -> NI | G215: =IF(MIS_Backend_Data!T214="", "", MIS_Backend_Data!T214) -> NI | H215: =IF(MIS_Backend_Data!X214="", "", MIS_Backend_Data!X214) -> NA | I215: =IF(MIS_Backend_Data!AC214="", "", MIS_Backend_Data!AC214) -> NA | J215: =IF(MIS_Backend_Data!AB214="", "", MIS_Backend_Data!AB214) -> NA | K215: =IF(MIS_Backend_Data!AG214="", "", MIS_Backend_Data!AG214) -> NA | L215: =IF(MIS_Backend_Data!AI214="", "", MIS_Backend_Data!AI214) -> NA | M215: =IF(MIS_Backend_Data!AK214="", "", MIS_Backend_Data!AK214) -> NA | N215: =IF(MIS_Backend_Data!AM214="", "", MIS_Backend_Data!AM214) -> NA | O215: =IF(MIS_Backend_Data!AO214="", "", MIS_Backend_Data!AO214) -> NA | P215: =IF(MIS_Backend_Data!AS214="", "", MIS_Backend_Data!AS214) -> NA | Q215: =IF(MIS_Backend_Data!AX214="", "", MIS_Backend_Data!AX214) -> NA | R215: =IF(MIS_Backend_Data!BB214="", "", MIS_Backend_Data!BB214) -> NA | S215: =IF(MIS_Backend_Data!AW214="", "", MIS_Backend_Data!AW214) -> NA | T215: =IF(MIS_Backend_Data!N214="Dispatch","Completed","NA") -> NA | U215: =IF(F215="WIP", IF(COUNTIF(G215:R215, "WIP")=2, 2, ""), "") | V215: =IF(F215="WIP", IF(COUNTIF(G215:R215, "WIP")=1, 1, ""), "") | W215: =IF(OR(F215="WIP",F215="Pending for CS"), IF(COUNTIFS(G215:R215,"<>Completed",G215:R215,"<>NA")=0,"GTG",""), "")
B216: 2025214537 | C216: Indusind General Insurance Co Ltd | D216: R001-1214-SS-2025 | E216: 6 | F216: =IF(MIS_Backend_Data!O215="", "", MIS_Backend_Data!O215) -> NI | G216: =IF(MIS_Backend_Data!T215="", "", MIS_Backend_Data!T215) -> NI | H216: =IF(MIS_Backend_Data!X215="", "", MIS_Backend_Data!X215) -> NA | I216: =IF(MIS_Backend_Data!AC215="", "", MIS_Backend_Data!AC215) -> NI | J216: =IF(MIS_Backend_Data!AB215="", "", MIS_Backend_Data!AB215) -> NA | K216: =IF(MIS_Backend_Data!AG215="", "", MIS_Backend_Data!AG215) -> NI | L216: =IF(MIS_Backend_Data!AI215="", "", MIS_Backend_Data!AI215) -> NA | M216: =IF(MIS_Backend_Data!AK215="", "", MIS_Backend_Data!AK215) -> NA | N216: =IF(MIS_Backend_Data!AM215="", "", MIS_Backend_Data!AM215) -> NA | O216: =IF(MIS_Backend_Data!AO215="", "", MIS_Backend_Data!AO215) -> NA | P216: =IF(MIS_Backend_Data!AS215="", "", MIS_Backend_Data!AS215) -> NI | Q216: =IF(MIS_Backend_Data!AX215="", "", MIS_Backend_Data!AX215) -> NI | R216: =IF(MIS_Backend_Data!BB215="", "", MIS_Backend_Data!BB215) -> NA | S216: =IF(MIS_Backend_Data!AW215="", "", MIS_Backend_Data!AW215) -> NA | T216: =IF(MIS_Backend_Data!N215="Dispatch","Completed","NA") -> NA | U216: =IF(F216="WIP", IF(COUNTIF(G216:R216, "WIP")=2, 2, ""), "") | V216: =IF(F216="WIP", IF(COUNTIF(G216:R216, "WIP")=1, 1, ""), "") | W216: =IF(OR(F216="WIP",F216="Pending for CS"), IF(COUNTIFS(G216:R216,"<>Completed",G216:R216,"<>NA")=0,"GTG",""), "")
B217: 2762824 | C217: SBI General Insurance Company Ltd | D217: S002-1215-SS-2025 | E217: 5 | F217: =IF(MIS_Backend_Data!O216="", "", MIS_Backend_Data!O216) -> NI | G217: =IF(MIS_Backend_Data!T216="", "", MIS_Backend_Data!T216) -> NI | H217: =IF(MIS_Backend_Data!X216="", "", MIS_Backend_Data!X216) -> NA | I217: =IF(MIS_Backend_Data!AC216="", "", MIS_Backend_Data!AC216) -> NI | J217: =IF(MIS_Backend_Data!AB216="", "", MIS_Backend_Data!AB216) -> NA | K217: =IF(MIS_Backend_Data!AG216="", "", MIS_Backend_Data!AG216) -> NI | L217: =IF(MIS_Backend_Data!AI216="", "", MIS_Backend_Data!AI216) -> NA | M217: =IF(MIS_Backend_Data!AK216="", "", MIS_Backend_Data!AK216) -> NA | N217: =IF(MIS_Backend_Data!AM216="", "", MIS_Backend_Data!AM216) -> NA | O217: =IF(MIS_Backend_Data!AO216="", "", MIS_Backend_Data!AO216) -> NA | P217: =IF(MIS_Backend_Data!AS216="", "", MIS_Backend_Data!AS216) -> NI | Q217: =IF(MIS_Backend_Data!AX216="", "", MIS_Backend_Data!AX216) -> NI | R217: =IF(MIS_Backend_Data!BB216="", "", MIS_Backend_Data!BB216) -> NA | S217: =IF(MIS_Backend_Data!AW216="", "", MIS_Backend_Data!AW216) -> NA | T217: =IF(MIS_Backend_Data!N216="Dispatch","Completed","NA") -> NA | U217: =IF(F217="WIP", IF(COUNTIF(G217:R217, "WIP")=2, 2, ""), "") | V217: =IF(F217="WIP", IF(COUNTIF(G217:R217, "WIP")=1, 1, ""), "") | W217: =IF(OR(F217="WIP",F217="Pending for CS"), IF(COUNTIFS(G217:R217,"<>Completed",G217:R217,"<>NA")=0,"GTG",""), "")
B218: 2761243 | C218: SBI General Insurance Company Ltd | D218: S002-1216-SS-2025 | E218: 5 | F218: =IF(MIS_Backend_Data!O217="", "", MIS_Backend_Data!O217) -> NI | G218: =IF(MIS_Backend_Data!T217="", "", MIS_Backend_Data!T217) -> NI | H218: =IF(MIS_Backend_Data!X217="", "", MIS_Backend_Data!X217) -> NA | I218: =IF(MIS_Backend_Data!AC217="", "", MIS_Backend_Data!AC217) -> NI | J218: =IF(MIS_Backend_Data!AB217="", "", MIS_Backend_Data!AB217) -> NA | K218: =IF(MIS_Backend_Data!AG217="", "", MIS_Backend_Data!AG217) -> NI | L218: =IF(MIS_Backend_Data!AI217="", "", MIS_Backend_Data!AI217) -> NA | M218: =IF(MIS_Backend_Data!AK217="", "", MIS_Backend_Data!AK217) -> NA | N218: =IF(MIS_Backend_Data!AM217="", "", MIS_Backend_Data!AM217) -> NA | O218: =IF(MIS_Backend_Data!AO217="", "", MIS_Backend_Data!AO217) -> NA | P218: =IF(MIS_Backend_Data!AS217="", "", MIS_Backend_Data!AS217) -> NI | Q218: =IF(MIS_Backend_Data!AX217="", "", MIS_Backend_Data!AX217) -> NA | R218: =IF(MIS_Backend_Data!BB217="", "", MIS_Backend_Data!BB217) -> NA | S218: =IF(MIS_Backend_Data!AW217="", "", MIS_Backend_Data!AW217) -> NA | T218: =IF(MIS_Backend_Data!N217="Dispatch","Completed","NA") -> NA | U218: =IF(F218="WIP", IF(COUNTIF(G218:R218, "WIP")=2, 2, ""), "") | V218: =IF(F218="WIP", IF(COUNTIF(G218:R218, "WIP")=1, 1, ""), "") | W218: =IF(OR(F218="WIP",F218="Pending for CS"), IF(COUNTIFS(G218:R218,"<>Completed",G218:R218,"<>NA")=0,"GTG",""), "")
B219: 2002673 | C219: SBI General Insurance Company Ltd | D219: S002-1217-SS-2025 | E219: 5 | F219: =IF(MIS_Backend_Data!O218="", "", MIS_Backend_Data!O218) -> NI | G219: =IF(MIS_Backend_Data!T218="", "", MIS_Backend_Data!T218) -> NI | H219: =IF(MIS_Backend_Data!X218="", "", MIS_Backend_Data!X218) -> NA | I219: =IF(MIS_Backend_Data!AC218="", "", MIS_Backend_Data!AC218) -> NI | J219: =IF(MIS_Backend_Data!AB218="", "", MIS_Backend_Data!AB218) -> NA | K219: =IF(MIS_Backend_Data!AG218="", "", MIS_Backend_Data!AG218) -> NI | L219: =IF(MIS_Backend_Data!AI218="", "", MIS_Backend_Data!AI218) -> NA | M219: =IF(MIS_Backend_Data!AK218="", "", MIS_Backend_Data!AK218) -> NA | N219: =IF(MIS_Backend_Data!AM218="", "", MIS_Backend_Data!AM218) -> NA | O219: =IF(MIS_Backend_Data!AO218="", "", MIS_Backend_Data!AO218) -> NA | P219: =IF(MIS_Backend_Data!AS218="", "", MIS_Backend_Data!AS218) -> NI | Q219: =IF(MIS_Backend_Data!AX218="", "", MIS_Backend_Data!AX218) -> NA | R219: =IF(MIS_Backend_Data!BB218="", "", MIS_Backend_Data!BB218) -> NA | S219: =IF(MIS_Backend_Data!AW218="", "", MIS_Backend_Data!AW218) -> NA | T219: =IF(MIS_Backend_Data!N218="Dispatch","Completed","NA") -> NA | U219: =IF(F219="WIP", IF(COUNTIF(G219:R219, "WIP")=2, 2, ""), "") | V219: =IF(F219="WIP", IF(COUNTIF(G219:R219, "WIP")=1, 1, ""), "") | W219: =IF(OR(F219="WIP",F219="Pending for CS"), IF(COUNTIFS(G219:R219,"<>Completed",G219:R219,"<>NA")=0,"GTG",""), "")
B220: 2002769 | C220: SBI General Insurance Company Ltd | D220: S002-1217-SS-2025 | E220: 4 | F220: =IF(MIS_Backend_Data!O219="", "", MIS_Backend_Data!O219) -> NI | G220: =IF(MIS_Backend_Data!T219="", "", MIS_Backend_Data!T219) -> NI | H220: =IF(MIS_Backend_Data!X219="", "", MIS_Backend_Data!X219) -> NA | I220: =IF(MIS_Backend_Data!AC219="", "", MIS_Backend_Data!AC219) -> NI | J220: =IF(MIS_Backend_Data!AB219="", "", MIS_Backend_Data!AB219) -> NA | K220: =IF(MIS_Backend_Data!AG219="", "", MIS_Backend_Data!AG219) -> NI | L220: =IF(MIS_Backend_Data!AI219="", "", MIS_Backend_Data!AI219) -> NA | M220: =IF(MIS_Backend_Data!AK219="", "", MIS_Backend_Data!AK219) -> NA | N220: =IF(MIS_Backend_Data!AM219="", "", MIS_Backend_Data!AM219) -> NA | O220: =IF(MIS_Backend_Data!AO219="", "", MIS_Backend_Data!AO219) -> NA | P220: =IF(MIS_Backend_Data!AS219="", "", MIS_Backend_Data!AS219) -> NI | Q220: =IF(MIS_Backend_Data!AX219="", "", MIS_Backend_Data!AX219) -> NI | R220: =IF(MIS_Backend_Data!BB219="", "", MIS_Backend_Data!BB219) -> NA | S220: =IF(MIS_Backend_Data!AW219="", "", MIS_Backend_Data!AW219) -> NA | T220: =IF(MIS_Backend_Data!N219="Dispatch","Completed","NA") -> NA | U220: =IF(F220="WIP", IF(COUNTIF(G220:R220, "WIP")=2, 2, ""), "") | V220: =IF(F220="WIP", IF(COUNTIF(G220:R220, "WIP")=1, 1, ""), "") | W220: =IF(OR(F220="WIP",F220="Pending for CS"), IF(COUNTIFS(G220:R220,"<>Completed",G220:R220,"<>NA")=0,"GTG",""), "")
B221: 2755247 | C221: SBI General Insurance Company Ltd | D221: S002-1217-SS-2025 | E221: 4 | F221: =IF(MIS_Backend_Data!O220="", "", MIS_Backend_Data!O220) -> NI | G221: =IF(MIS_Backend_Data!T220="", "", MIS_Backend_Data!T220) -> NI | H221: =IF(MIS_Backend_Data!X220="", "", MIS_Backend_Data!X220) -> NA | I221: =IF(MIS_Backend_Data!AC220="", "", MIS_Backend_Data!AC220) -> NI | J221: =IF(MIS_Backend_Data!AB220="", "", MIS_Backend_Data!AB220) -> NA | K221: =IF(MIS_Backend_Data!AG220="", "", MIS_Backend_Data!AG220) -> NA | L221: =IF(MIS_Backend_Data!AI220="", "", MIS_Backend_Data!AI220) -> NA | M221: =IF(MIS_Backend_Data!AK220="", "", MIS_Backend_Data!AK220) -> NA | N221: =IF(MIS_Backend_Data!AM220="", "", MIS_Backend_Data!AM220) -> NA | O221: =IF(MIS_Backend_Data!AO220="", "", MIS_Backend_Data!AO220) -> NA | P221: =IF(MIS_Backend_Data!AS220="", "", MIS_Backend_Data!AS220) -> NI | Q221: =IF(MIS_Backend_Data!AX220="", "", MIS_Backend_Data!AX220) -> NI | R221: =IF(MIS_Backend_Data!BB220="", "", MIS_Backend_Data!BB220) -> NA | S221: =IF(MIS_Backend_Data!AW220="", "", MIS_Backend_Data!AW220) -> NA | T221: =IF(MIS_Backend_Data!N220="Dispatch","Completed","NA") -> NA | U221: =IF(F221="WIP", IF(COUNTIF(G221:R221, "WIP")=2, 2, ""), "") | V221: =IF(F221="WIP", IF(COUNTIF(G221:R221, "WIP")=1, 1, ""), "") | W221: =IF(OR(F221="WIP",F221="Pending for CS"), IF(COUNTIFS(G221:R221,"<>Completed",G221:R221,"<>NA")=0,"GTG",""), "")
B222: 2769290 | C222: SBI General Insurance Company Ltd | D222: S002-1217-SS-2025 | E222: 4 | F222: =IF(MIS_Backend_Data!O221="", "", MIS_Backend_Data!O221) -> NI | G222: =IF(MIS_Backend_Data!T221="", "", MIS_Backend_Data!T221) -> NI | H222: =IF(MIS_Backend_Data!X221="", "", MIS_Backend_Data!X221) -> NA | I222: =IF(MIS_Backend_Data!AC221="", "", MIS_Backend_Data!AC221) -> NI | J222: =IF(MIS_Backend_Data!AB221="", "", MIS_Backend_Data!AB221) -> NA | K222: =IF(MIS_Backend_Data!AG221="", "", MIS_Backend_Data!AG221) -> NI | L222: =IF(MIS_Backend_Data!AI221="", "", MIS_Backend_Data!AI221) -> NA | M222: =IF(MIS_Backend_Data!AK221="", "", MIS_Backend_Data!AK221) -> NA | N222: =IF(MIS_Backend_Data!AM221="", "", MIS_Backend_Data!AM221) -> NA | O222: =IF(MIS_Backend_Data!AO221="", "", MIS_Backend_Data!AO221) -> NA | P222: =IF(MIS_Backend_Data!AS221="", "", MIS_Backend_Data!AS221) -> NI | Q222: =IF(MIS_Backend_Data!AX221="", "", MIS_Backend_Data!AX221) -> NI | R222: =IF(MIS_Backend_Data!BB221="", "", MIS_Backend_Data!BB221) -> NA | S222: =IF(MIS_Backend_Data!AW221="", "", MIS_Backend_Data!AW221) -> NA | T222: =IF(MIS_Backend_Data!N221="Dispatch","Completed","NA") -> NA | U222: =IF(F222="WIP", IF(COUNTIF(G222:R222, "WIP")=2, 2, ""), "") | V222: =IF(F222="WIP", IF(COUNTIF(G222:R222, "WIP")=1, 1, ""), "") | W222: =IF(OR(F222="WIP",F222="Pending for CS"), IF(COUNTIFS(G222:R222,"<>Completed",G222:R222,"<>NA")=0,"GTG",""), "")
... B227: 2025214761 | C227: Indusind General Insurance Co Ltd | D227: R001-1225-SS-2026 | E227: 0 | F227: =IF(MIS_Backend_Data!O226="", "", MIS_Backend_Data!O226) -> NI | G227: =IF(MIS_Backend_Data!T226="", "", MIS_Backend_Data!T226) -> NI | H227: =IF(MIS_Backend_Data!X226="", "", MIS_Backend_Data!X226) -> NA | I227: =IF(MIS_Backend_Data!AC226="", "", MIS_Backend_Data!AC226) -> NI | J227: =IF(MIS_Backend_Data!AB226="", "", MIS_Backend_Data!AB226) -> NA | K227: =IF(MIS_Backend_Data!AG226="", "", MIS_Backend_Data!AG226) -> NI | L227: =IF(MIS_Backend_Data!AI226="", "", MIS_Backend_Data!AI226) -> NA | M227: =IF(MIS_Backend_Data!AK226="", "", MIS_Backend_Data!AK226) -> NA | N227: =IF(MIS_Backend_Data!AM226="", "", MIS_Backend_Data!AM226) -> NA | O227: =IF(MIS_Backend_Data!AO226="", "", MIS_Backend_Data!AO226) -> NA | P227: =IF(MIS_Backend_Data!AS226="", "", MIS_Backend_Data!AS226) -> NI | Q227: =IF(MIS_Backend_Data!AX226="", "", MIS_Backend_Data!AX226) -> NI | R227: =IF(MIS_Backend_Data!BB226="", "", MIS_Backend_Data!BB226) -> NA | S227: =IF(MIS_Backend_Data!AW226="", "", MIS_Backend_Data!AW226) -> NA | T227: =IF(MIS_Backend_Data!N226="Dispatch","Completed","NA") -> NA | U227: =IF(F227="WIP", IF(COUNTIF(G227:R227, "WIP")=2, 2, ""), "") | V227: =IF(F227="WIP", IF(COUNTIF(G227:R227, "WIP")=1, 1, ""), "") | W227: =IF(OR(F227="WIP",F227="Pending for CS"), IF(COUNTIFS(G227:R227,"<>Completed",G227:R227,"<>NA")=0,"GTG",""), "")
F228: =IF(MIS_Backend_Data!O227="", "", MIS_Backend_Data!O227) | G228: =IF(MIS_Backend_Data!T227="", "", MIS_Backend_Data!T227) | H228: =IF(MIS_Backend_Data!X227="", "", MIS_Backend_Data!X227) | I228: =IF(MIS_Backend_Data!AC227="", "", MIS_Backend_Data!AC227) | J228: =IF(MIS_Backend_Data!AB227="", "", MIS_Backend_Data!AB227) | K228: =IF(MIS_Backend_Data!AG227="", "", MIS_Backend_Data!AG227) | L228: =IF(MIS_Backend_Data!AI227="", "", MIS_Backend_Data!AI227) | M228: =IF(MIS_Backend_Data!AK227="", "", MIS_Backend_Data!AK227) | N228: =IF(MIS_Backend_Data!AM227="", "", MIS_Backend_Data!AM227) | O228: =IF(MIS_Backend_Data!AO227="", "", MIS_Backend_Data!AO227) | P228: =IF(MIS_Backend_Data!AS227="", "", MIS_Backend_Data!AS227) | Q228: =IF(MIS_Backend_Data!AX227="", "", MIS_Backend_Data!AX227) | R228: =IF(MIS_Backend_Data!BB227="", "", MIS_Backend_Data!BB227) | S228: =IF(MIS_Backend_Data!AW227="", "", MIS_Backend_Data!AW227) | T228: =IF(MIS_Backend_Data!N227="Dispatch","Completed","NA") -> NA | U228: =IF(F228="WIP", IF(COUNTIF(G228:R228, "WIP")=2, 2, ""), "") | V228: =IF(F228="WIP", IF(COUNTIF(G228:R228, "WIP")=1, 1, ""), "") | W228: =IF(OR(F228="WIP",F228="Pending for CS"), IF(COUNTIFS(G228:R228,"<>Completed",G228:R228,"<>NA")=0,"GTG",""), "")
F229: =IF(MIS_Backend_Data!O228="", "", MIS_Backend_Data!O228) | G229: =IF(MIS_Backend_Data!T228="", "", MIS_Backend_Data!T228) | H229: =IF(MIS_Backend_Data!X228="", "", MIS_Backend_Data!X228) | I229: =IF(MIS_Backend_Data!AC228="", "", MIS_Backend_Data!AC228) | J229: =IF(MIS_Backend_Data!AB228="", "", MIS_Backend_Data!AB228) | K229: =IF(MIS_Backend_Data!AG228="", "", MIS_Backend_Data!AG228) | L229: =IF(MIS_Backend_Data!AI228="", "", MIS_Backend_Data!AI228) | M229: =IF(MIS_Backend_Data!AK228="", "", MIS_Backend_Data!AK228) | N229: =IF(MIS_Backend_Data!AM228="", "", MIS_Backend_Data!AM228) | O229: =IF(MIS_Backend_Data!AO228="", "", MIS_Backend_Data!AO228) | P229: =IF(MIS_Backend_Data!AS228="", "", MIS_Backend_Data!AS228) | Q229: =IF(MIS_Backend_Data!AX228="", "", MIS_Backend_Data!AX228) | R229: =IF(MIS_Backend_Data!BB228="", "", MIS_Backend_Data!BB228) | S229: =IF(MIS_Backend_Data!AW228="", "", MIS_Backend_Data!AW228) | T229: =IF(MIS_Backend_Data!N228="Dispatch","Completed","NA") -> NA | U229: =IF(F229="WIP", IF(COUNTIF(G229:R229, "WIP")=2, 2, ""), "") | V229: =IF(F229="WIP", IF(COUNTIF(G229:R229, "WIP")=1, 1, ""), "") | W229: =IF(OR(F229="WIP",F229="Pending for CS"), IF(COUNTIFS(G229:R229,"<>Completed",G229:R229,"<>NA")=0,"GTG",""), "")
F230: =IF(MIS_Backend_Data!O229="", "", MIS_Backend_Data!O229) | G230: =IF(MIS_Backend_Data!T229="", "", MIS_Backend_Data!T229) | H230: =IF(MIS_Backend_Data!X229="", "", MIS_Backend_Data!X229) | I230: =IF(MIS_Backend_Data!AC229="", "", MIS_Backend_Data!AC229) | J230: =IF(MIS_Backend_Data!AB229="", "", MIS_Backend_Data!AB229) | K230: =IF(MIS_Backend_Data!AG229="", "", MIS_Backend_Data!AG229) | L230: =IF(MIS_Backend_Data!AI229="", "", MIS_Backend_Data!AI229) | M230: =IF(MIS_Backend_Data!AK229="", "", MIS_Backend_Data!AK229) | N230: =IF(MIS_Backend_Data!AM229="", "", MIS_Backend_Data!AM229) | O230: =IF(MIS_Backend_Data!AO229="", "", MIS_Backend_Data!AO229) | P230: =IF(MIS_Backend_Data!AS229="", "", MIS_Backend_Data!AS229) | Q230: =IF(MIS_Backend_Data!AX229="", "", MIS_Backend_Data!AX229) | R230: =IF(MIS_Backend_Data!BB229="", "", MIS_Backend_Data!BB229) | S230: =IF(MIS_Backend_Data!AW229="", "", MIS_Backend_Data!AW229) | T230: =IF(MIS_Backend_Data!N229="Dispatch","Completed","NA") -> NA | U230: =IF(F230="WIP", IF(COUNTIF(G230:R230, "WIP")=2, 2, ""), "") | V230: =IF(F230="WIP", IF(COUNTIF(G230:R230, "WIP")=1, 1, ""), "") | W230: =IF(OR(F230="WIP",F230="Pending for CS"), IF(COUNTIFS(G230:R230,"<>Completed",G230:R230,"<>NA")=0,"GTG",""), "")
F231: =IF(MIS_Backend_Data!O230="", "", MIS_Backend_Data!O230) | G231: =IF(MIS_Backend_Data!T230="", "", MIS_Backend_Data!T230) | H231: =IF(MIS_Backend_Data!X230="", "", MIS_Backend_Data!X230) | I231: =IF(MIS_Backend_Data!AC230="", "", MIS_Backend_Data!AC230) | J231: =IF(MIS_Backend_Data!AB230="", "", MIS_Backend_Data!AB230) | K231: =IF(MIS_Backend_Data!AG230="", "", MIS_Backend_Data!AG230) | L231: =IF(MIS_Backend_Data!AI230="", "", MIS_Backend_Data!AI230) | M231: =IF(MIS_Backend_Data!AK230="", "", MIS_Backend_Data!AK230) | N231: =IF(MIS_Backend_Data!AM230="", "", MIS_Backend_Data!AM230) | O231: =IF(MIS_Backend_Data!AO230="", "", MIS_Backend_Data!AO230) | P231: =IF(MIS_Backend_Data!AS230="", "", MIS_Backend_Data!AS230) | Q231: =IF(MIS_Backend_Data!AX230="", "", MIS_Backend_Data!AX230) | R231: =IF(MIS_Backend_Data!BB230="", "", MIS_Backend_Data!BB230) | S231: =IF(MIS_Backend_Data!AW230="", "", MIS_Backend_Data!AW230) | T231: =IF(MIS_Backend_Data!N230="Dispatch","Completed","NA") -> NA | U231: =IF(F231="WIP", IF(COUNTIF(G231:R231, "WIP")=2, 2, ""), "") | V231: =IF(F231="WIP", IF(COUNTIF(G231:R231, "WIP")=1, 1, ""), "") | W231: =IF(OR(F231="WIP",F231="Pending for CS"), IF(COUNTIFS(G231:R231,"<>Completed",G231:R231,"<>NA")=0,"GTG",""), "")
F232: =IF(MIS_Backend_Data!O231="", "", MIS_Backend_Data!O231) | G232: =IF(MIS_Backend_Data!T231="", "", MIS_Backend_Data!T231) | H232: =IF(MIS_Backend_Data!X231="", "", MIS_Backend_Data!X231) | I232: =IF(MIS_Backend_Data!AC231="", "", MIS_Backend_Data!AC231) | J232: =IF(MIS_Backend_Data!AB231="", "", MIS_Backend_Data!AB231) | K232: =IF(MIS_Backend_Data!AG231="", "", MIS_Backend_Data!AG231) | L232: =IF(MIS_Backend_Data!AI231="", "", MIS_Backend_Data!AI231) | M232: =IF(MIS_Backend_Data!AK231="", "", MIS_Backend_Data!AK231) | N232: =IF(MIS_Backend_Data!AM231="", "", MIS_Backend_Data!AM231) | O232: =IF(MIS_Backend_Data!AO231="", "", MIS_Backend_Data!AO231) | P232: =IF(MIS_Backend_Data!AS231="", "", MIS_Backend_Data!AS231) | Q232: =IF(MIS_Backend_Data!AX231="", "", MIS_Backend_Data!AX231) | R232: =IF(MIS_Backend_Data!BB231="", "", MIS_Backend_Data!BB231) | S232: =IF(MIS_Backend_Data!AW231="", "", MIS_Backend_Data!AW231) | T232: =IF(MIS_Backend_Data!N231="Dispatch","Completed","NA") -> NA | U232: =IF(F232="WIP", IF(COUNTIF(G232:R232, "WIP")=2, 2, ""), "") | V232: =IF(F232="WIP", IF(COUNTIF(G232:R232, "WIP")=1, 1, ""), "") | W232: =IF(OR(F232="WIP",F232="Pending for CS"), IF(COUNTIFS(G232:R232,"<>Completed",G232:R232,"<>NA")=0,"GTG",""), "")
F233: =IF(MIS_Backend_Data!O232="", "", MIS_Backend_Data!O232) | G233: =IF(MIS_Backend_Data!T232="", "", MIS_Backend_Data!T232) | H233: =IF(MIS_Backend_Data!X232="", "", MIS_Backend_Data!X232) | I233: =IF(MIS_Backend_Data!AC232="", "", MIS_Backend_Data!AC232) | J233: =IF(MIS_Backend_Data!AB232="", "", MIS_Backend_Data!AB232) | K233: =IF(MIS_Backend_Data!AG232="", "", MIS_Backend_Data!AG232) | L233: =IF(MIS_Backend_Data!AI232="", "", MIS_Backend_Data!AI232) | M233: =IF(MIS_Backend_Data!AK232="", "", MIS_Backend_Data!AK232) | N233: =IF(MIS_Backend_Data!AM232="", "", MIS_Backend_Data!AM232) | O233: =IF(MIS_Backend_Data!AO232="", "", MIS_Backend_Data!AO232) | P233: =IF(MIS_Backend_Data!AS232="", "", MIS_Backend_Data!AS232) | Q233: =IF(MIS_Backend_Data!AX232="", "", MIS_Backend_Data!AX232) | R233: =IF(MIS_Backend_Data!BB232="", "", MIS_Backend_Data!BB232) | S233: =IF(MIS_Backend_Data!AW232="", "", MIS_Backend_Data!AW232) | T233: =IF(MIS_Backend_Data!N232="Dispatch","Completed","NA") -> NA | U233: =IF(F233="WIP", IF(COUNTIF(G233:R233, "WIP")=2, 2, ""), "") | V233: =IF(F233="WIP", IF(COUNTIF(G233:R233, "WIP")=1, 1, ""), "") | W233: =IF(OR(F233="WIP",F233="Pending for CS"), IF(COUNTIFS(G233:R233,"<>Completed",G233:R233,"<>NA")=0,"GTG",""), "")
F234: =IF(MIS_Backend_Data!O233="", "", MIS_Backend_Data!O233) | G234: =IF(MIS_Backend_Data!T233="", "", MIS_Backend_Data!T233) | H234: =IF(MIS_Backend_Data!X233="", "", MIS_Backend_Data!X233) | I234: =IF(MIS_Backend_Data!AC233="", "", MIS_Backend_Data!AC233) | J234: =IF(MIS_Backend_Data!AB233="", "", MIS_Backend_Data!AB233) | K234: =IF(MIS_Backend_Data!AG233="", "", MIS_Backend_Data!AG233) | L234: =IF(MIS_Backend_Data!AI233="", "", MIS_Backend_Data!AI233) | M234: =IF(MIS_Backend_Data!AK233="", "", MIS_Backend_Data!AK233) | N234: =IF(MIS_Backend_Data!AM233="", "", MIS_Backend_Data!AM233) | O234: =IF(MIS_Backend_Data!AO233="", "", MIS_Backend_Data!AO233) | P234: =IF(MIS_Backend_Data!AS233="", "", MIS_Backend_Data!AS233) | Q234: =IF(MIS_Backend_Data!AX233="", "", MIS_Backend_Data!AX233) | R234: =IF(MIS_Backend_Data!BB233="", "", MIS_Backend_Data!BB233) | S234: =IF(MIS_Backend_Data!AW233="", "", MIS_Backend_Data!AW233) | T234: =IF(MIS_Backend_Data!N233="Dispatch","Completed","NA") -> NA | U234: =IF(F234="WIP", IF(COUNTIF(G234:R234, "WIP")=2, 2, ""), "") | V234: =IF(F234="WIP", IF(COUNTIF(G234:R234, "WIP")=1, 1, ""), "") | W234: =IF(OR(F234="WIP",F234="Pending for CS"), IF(COUNTIFS(G234:R234,"<>Completed",G234:R234,"<>NA")=0,"GTG",""), "")
F235: =IF(MIS_Backend_Data!O234="", "", MIS_Backend_Data!O234) | G235: =IF(MIS_Backend_Data!T234="", "", MIS_Backend_Data!T234) | H235: =IF(MIS_Backend_Data!X234="", "", MIS_Backend_Data!X234) | I235: =IF(MIS_Backend_Data!AC234="", "", MIS_Backend_Data!AC234) | J235: =IF(MIS_Backend_Data!AB234="", "", MIS_Backend_Data!AB234) | K235: =IF(MIS_Backend_Data!AG234="", "", MIS_Backend_Data!AG234) | L235: =IF(MIS_Backend_Data!AI234="", "", MIS_Backend_Data!AI234) | M235: =IF(MIS_Backend_Data!AK234="", "", MIS_Backend_Data!AK234) | N235: =IF(MIS_Backend_Data!AM234="", "", MIS_Backend_Data!AM234) | O235: =IF(MIS_Backend_Data!AO234="", "", MIS_Backend_Data!AO234) | P235: =IF(MIS_Backend_Data!AS234="", "", MIS_Backend_Data!AS234) | Q235: =IF(MIS_Backend_Data!AX234="", "", MIS_Backend_Data!AX234) | R235: =IF(MIS_Backend_Data!BB234="", "", MIS_Backend_Data!BB234) | S235: =IF(MIS_Backend_Data!AW234="", "", MIS_Backend_Data!AW234) | T235: =IF(MIS_Backend_Data!N234="Dispatch","Completed","NA") -> NA | U235: =IF(F235="WIP", IF(COUNTIF(G235:R235, "WIP")=2, 2, ""), "") | V235: =IF(F235="WIP", IF(COUNTIF(G235:R235, "WIP")=1, 1, ""), "") | W235: =IF(OR(F235="WIP",F235="Pending for CS"), IF(COUNTIFS(G235:R235,"<>Completed",G235:R235,"<>NA")=0,"GTG",""), "")
F236: =IF(MIS_Backend_Data!O235="", "", MIS_Backend_Data!O235) | G236: =IF(MIS_Backend_Data!T235="", "", MIS_Backend_Data!T235) | H236: =IF(MIS_Backend_Data!X235="", "", MIS_Backend_Data!X235) | I236: =IF(MIS_Backend_Data!AC235="", "", MIS_Backend_Data!AC235) | J236: =IF(MIS_Backend_Data!AB235="", "", MIS_Backend_Data!AB235) | K236: =IF(MIS_Backend_Data!AG235="", "", MIS_Backend_Data!AG235) | L236: =IF(MIS_Backend_Data!AI235="", "", MIS_Backend_Data!AI235) | M236: =IF(MIS_Backend_Data!AK235="", "", MIS_Backend_Data!AK235) | N236: =IF(MIS_Backend_Data!AM235="", "", MIS_Backend_Data!AM235) | O236: =IF(MIS_Backend_Data!AO235="", "", MIS_Backend_Data!AO235) | P236: =IF(MIS_Backend_Data!AS235="", "", MIS_Backend_Data!AS235) | Q236: =IF(MIS_Backend_Data!AX235="", "", MIS_Backend_Data!AX235) | R236: =IF(MIS_Backend_Data!BB235="", "", MIS_Backend_Data!BB235) | S236: =IF(MIS_Backend_Data!AW235="", "", MIS_Backend_Data!AW235) | T236: =IF(MIS_Backend_Data!N235="Dispatch","Completed","NA") -> NA | U236: =IF(F236="WIP", IF(COUNTIF(G236:R236, "WIP")=2, 2, ""), "") | V236: =IF(F236="WIP", IF(COUNTIF(G236:R236, "WIP")=1, 1, ""), "") | W236: =IF(OR(F236="WIP",F236="Pending for CS"), IF(COUNTIFS(G236:R236,"<>Completed",G236:R236,"<>NA")=0,"GTG",""), "")
F237: =IF(MIS_Backend_Data!O236="", "", MIS_Backend_Data!O236) | G237: =IF(MIS_Backend_Data!T236="", "", MIS_Backend_Data!T236) | H237: =IF(MIS_Backend_Data!X236="", "", MIS_Backend_Data!X236) | I237: =IF(MIS_Backend_Data!AC236="", "", MIS_Backend_Data!AC236) | J237: =IF(MIS_Backend_Data!AB236="", "", MIS_Backend_Data!AB236) | K237: =IF(MIS_Backend_Data!AG236="", "", MIS_Backend_Data!AG236) | L237: =IF(MIS_Backend_Data!AI236="", "", MIS_Backend_Data!AI236) | M237: =IF(MIS_Backend_Data!AK236="", "", MIS_Backend_Data!AK236) | N237: =IF(MIS_Backend_Data!AM236="", "", MIS_Backend_Data!AM236) | O237: =IF(MIS_Backend_Data!AO236="", "", MIS_Backend_Data!AO236) | P237: =IF(MIS_Backend_Data!AS236="", "", MIS_Backend_Data!AS236) | Q237: =IF(MIS_Backend_Data!AX236="", "", MIS_Backend_Data!AX236) | R237: =IF(MIS_Backend_Data!BB236="", "", MIS_Backend_Data!BB236) | S237: =IF(MIS_Backend_Data!AW236="", "", MIS_Backend_Data!AW236) | T237: =IF(MIS_Backend_Data!N236="Dispatch","Completed","NA") -> NA | U237: =IF(F237="WIP", IF(COUNTIF(G237:R237, "WIP")=2, 2, ""), "") | V237: =IF(F237="WIP", IF(COUNTIF(G237:R237, "WIP")=1, 1, ""), "") | W237: =IF(OR(F237="WIP",F237="Pending for CS"), IF(COUNTIFS(G237:R237,"<>Completed",G237:R237,"<>NA")=0,"GTG",""), "")
F238: =IF(MIS_Backend_Data!O237="", "", MIS_Backend_Data!O237) | G238: =IF(MIS_Backend_Data!T237="", "", MIS_Backend_Data!T237) | H238: =IF(MIS_Backend_Data!X237="", "", MIS_Backend_Data!X237) | I238: =IF(MIS_Backend_Data!AC237="", "", MIS_Backend_Data!AC237) | J238: =IF(MIS_Backend_Data!AB237="", "", MIS_Backend_Data!AB237) | K238: =IF(MIS_Backend_Data!AG237="", "", MIS_Backend_Data!AG237) | L238: =IF(MIS_Backend_Data!AI237="", "", MIS_Backend_Data!AI237) | M238: =IF(MIS_Backend_Data!AK237="", "", MIS_Backend_Data!AK237) | N238: =IF(MIS_Backend_Data!AM237="", "", MIS_Backend_Data!AM237) | O238: =IF(MIS_Backend_Data!AO237="", "", MIS_Backend_Data!AO237) | P238: =IF(MIS_Backend_Data!AS237="", "", MIS_Backend_Data!AS237) | Q238: =IF(MIS_Backend_Data!AX237="", "", MIS_Backend_Data!AX237) | R238: =IF(MIS_Backend_Data!BB237="", "", MIS_Backend_Data!BB237) | S238: =IF(MIS_Backend_Data!AW237="", "", MIS_Backend_Data!AW237) | T238: =IF(MIS_Backend_Data!N237="Dispatch","Completed","NA") -> NA | U238: =IF(F238="WIP", IF(COUNTIF(G238:R238, "WIP")=2, 2, ""), "") | V238: =IF(F238="WIP", IF(COUNTIF(G238:R238, "WIP")=1, 1, ""), "") | W238: =IF(OR(F238="WIP",F238="Pending for CS"), IF(COUNTIFS(G238:R238,"<>Completed",G238:R238,"<>NA")=0,"GTG",""), "")
F239: =IF(MIS_Backend_Data!O238="", "", MIS_Backend_Data!O238) | G239: =IF(MIS_Backend_Data!T238="", "", MIS_Backend_Data!T238) | H239: =IF(MIS_Backend_Data!X238="", "", MIS_Backend_Data!X238) | I239: =IF(MIS_Backend_Data!AC238="", "", MIS_Backend_Data!AC238) | J239: =IF(MIS_Backend_Data!AB238="", "", MIS_Backend_Data!AB238) | K239: =IF(MIS_Backend_Data!AG238="", "", MIS_Backend_Data!AG238) | L239: =IF(MIS_Backend_Data!AI238="", "", MIS_Backend_Data!AI238) | M239: =IF(MIS_Backend_Data!AK238="", "", MIS_Backend_Data!AK238) | N239: =IF(MIS_Backend_Data!AM238="", "", MIS_Backend_Data!AM238) | O239: =IF(MIS_Backend_Data!AO238="", "", MIS_Backend_Data!AO238) | P239: =IF(MIS_Backend_Data!AS238="", "", MIS_Backend_Data!AS238) | Q239: =IF(MIS_Backend_Data!AX238="", "", MIS_Backend_Data!AX238) | R239: =IF(MIS_Backend_Data!BB238="", "", MIS_Backend_Data!BB238) | S239: =IF(MIS_Backend_Data!AW238="", "", MIS_Backend_Data!AW238) | T239: =IF(MIS_Backend_Data!N238="Dispatch","Completed","NA") -> NA | U239: =IF(F239="WIP", IF(COUNTIF(G239:R239, "WIP")=2, 2, ""), "") | V239: =IF(F239="WIP", IF(COUNTIF(G239:R239, "WIP")=1, 1, ""), "") | W239: =IF(OR(F239="WIP",F239="Pending for CS"), IF(COUNTIFS(G239:R239,"<>Completed",G239:R239,"<>NA")=0,"GTG",""), "")
... F500: =IF(MIS_Backend_Data!O499="", "", MIS_Backend_Data!O499) | G500: =IF(MIS_Backend_Data!T499="", "", MIS_Backend_Data!T499) | H500: =IF(MIS_Backend_Data!X499="", "", MIS_Backend_Data!X499) | I500: =IF(MIS_Backend_Data!AC499="", "", MIS_Backend_Data!AC499) | J500: =IF(MIS_Backend_Data!AB499="", "", MIS_Backend_Data!AB499) | K500: =IF(MIS_Backend_Data!AG499="", "", MIS_Backend_Data!AG499) | L500: =IF(MIS_Backend_Data!AI499="", "", MIS_Backend_Data!AI499) | M500: =IF(MIS_Backend_Data!AK499="", "", MIS_Backend_Data!AK499) | N500: =IF(MIS_Backend_Data!AM499="", "", MIS_Backend_Data!AM499) | O500: =IF(MIS_Backend_Data!AO499="", "", MIS_Backend_Data!AO499) | P500: =IF(MIS_Backend_Data!AS499="", "", MIS_Backend_Data!AS499) | Q500: =IF(MIS_Backend_Data!AX499="", "", MIS_Backend_Data!AX499) | R500: =IF(MIS_Backend_Data!BB499="", "", MIS_Backend_Data!BB499) | S500: =IF(MIS_Backend_Data!AW499="", "", MIS_Backend_Data!AW499) | T500: =IF(MIS_Backend_Data!N499="Dispatch","Completed","NA") -> NA | U500: =IF(F500="WIP", IF(COUNTIF(G500:R500, "WIP")=2, 2, ""), "") | V500: =IF(F500="WIP", IF(COUNTIF(G500:R500, "WIP")=1, 1, ""), "") | W500: =IF(OR(F500="WIP",F500="Pending for CS"), IF(COUNTIFS(G500:R500,"<>Completed",G500:R500,"<>NA")=0,"GTG",""), "")

Sheet MIS_Backend_Data
A1: S | N | B1: {=_xlfn._xlws.FILTER( _xlfn.CHOOSECOLS(CRN!B:I, 6,5,2,4,7,8), CRN!E:E <> "" )} -> CLAIM NUMBER | C1: CLIENT NAME | D1: CATEGORY | E1: CRN | F1: CASE RECIPET DATE | G1: RECIPET MONTH | H1: COMPLETION DATE | I1: COMPLETION MONTH | J1: CASE DUE DATE | K1: TAT | L1: SLA | M1: CASE TYPE | N1: INVESTIGATION REPORT | O1: FULL CASE STATUS | P1: SCOPE OF WORK | Q1: CLAIMANT NAME | R1: CLAIMANT ADDRESS | S1: CLAIMANT DISTRICT | T1: CLAIMANT STATUS | U1: INCOME DETAILS | V1: INCOME ADDRESS | W1: DISTRICT | X1: INCOME STATUS | Y1: INSURED NAME | Z1: INSURED ADDRESS | AA1: INSURED DISTRICT | AB1: 132 NOTICE | AC1: INSURED STATUS | AD1: DRIVER NAME | AE1: DRIVER ADDRESS | AF1: DRIVER DISTRICT | AG1: DRIVER STATUS | AH1: DL | AI1: DL STATUS | AJ1: RC | AK1: RC STATUS | AL1: PERMIT | AM1: PERMIT STATUS | AN1: FITNESS | AO1: FITNESS STATUS | AP1: DISTRICT | AQ1: SPOT LOCATION | AR1: SPOT DISTRICT | AS1: SPOT STATUS | AT1: FIR NUMBER | AU1: POLICE STATION | AV1: District | AW1: RTI | AX1: CHARGESHEET STATUS | AY1: HOSPITAL NAME | AZ1: HOSPITAL ADDRESS | BA1: HOSPITAL DISTRICT | BB1: HOSPITAL STATUS | BC1: DISPATCH DATE | BD1: DISPACTH STATUS | BE1: CASE NOTES
A2: 1 | B2: C2264103101203-00 | C2: Magma HDI General Insurance Company Ltd | D2: MACT | E2: M002-1001-SS-2025 | F2: 45873 | G2: Aug-25 | H2: 46025 | I2: =TEXT(H2,("mmm-yy")) -> Jan-26 | J2: =IF(F2="", "", IF(OR(M2="WC Claim", M2="Partial Case"), WORKDAY(F2, 15), IF(OR(M2="Medical Verification", M2="Full Case"), WORKDAY(F2, 30), ""))) -> 45915 | K2: =IF(F2="", "", IF(ISNUMBER(H2), H2 - F2, TODAY() - F2)) -> 152 | L2: =IF(K2="", "", IF(OR(M2="Partial Case", M2="Medical Verification", M2="WC Claim"), IF(K2<=15, "WT", "AT"), IF(K2<30, "WT", "AT") ) ) -> AT | M2: Full Case | N2: Dispatch | O2: Completed | Q2: Shrimati Parvatibai Balu Kamble | R2: Pokhari, nandgaon, Nashik | S2: Nashik | T2: Completed | U2: NA | X2: NA | Y2: Inderdeep Construction Company | Z2: First Floor, 32/01, Cristal Pride, Hari Ghat, App. AVM Automoblie, Kalyan - 421003 | AA2: Kalyan | AB2: NA | AC2: Completed | AD2: Munnala Rajaram Saroj | AF2: NA | AG2: NA | AH2: NA | AI2: NA | AJ2: NA | AK2: NA | AL2: NA | AM2: NA | AN2: NA | AO2: NA | AP2: NA | AQ2: On Nandgaon to Chalisgaon road, In the vicinity of Gangadhari village, Opp D K Industries. | AR2: Jalgaon | AS2: Completed | AT2: Nashik | AU2: NA | AV2: NA | AW2: NA | AX2: Completed | AY2: Gramin Hospital | BB2: NA | BD2: Pending | BE2: Spot/ Claimant/ Insured
A3: 2 | B3: C2264191100006-00 | C3: Magma HDI General Insurance Company Ltd | D3: MACT | E3: M002-1002-SS-2025 | F3: 45873 | G3: Aug-25 | H3: - | J3: =IF(F3="", "", IF(OR(M3="WC Claim", M3="Partial Case"), WORKDAY(F3, 15), IF(OR(M3="Medical Verification", M3="Full Case"), WORKDAY(F3, 30), ""))) | K3: =IF(F3="", "", IF(ISNUMBER(H3), H3 - F3, TODAY() - F3)) -> 154 | L3: =IF(K3="", "", IF(OR(M3="Partial Case", M3="Medical Verification", M3="WC Claim"), IF(K3<=15, "WT", "AT"), IF(K3<30, "WT", "AT") ) ) -> AT | M3: Connected Case | N3: Open | O3: WIP | Q3: Chandrabhaga Shivaji Pawar | R3: Bhilcot, Malegaon, Nashik. | S3: Nashik | T3: WIP | U3: NA | X3: NA | Y3: Momin Navid Akhtar Mohmd Shahid | Z3: Naya Islampura, Malegaon, Nashik 423202 | AA3: Nashik | AB3: NA | AC3: WIP | AD3: NA | AF3: Mukhtar Shaikh | AG3: NA | AH3: NA | AI3: NA | AJ3: NA | AK3: NA | AL3: NA | AM3: NA | AN3: NA | AO3: NA | AP3: NA | AQ3: On Hatane to Tokane road, Near Pravin Thokes Veetbatti, In the visinity of Hatane village. | AR3: Washim | AS3: WIP | AT3: Nashik | AU3: NA | AV3: NA | AW3: NA | AX3: Completed | AY3: Gramin Hospital | BB3: NA | BE3: Chargesheet
A4: 3 | B4: C2264103101217-04 | C4: Magma HDI General Insurance Company Ltd | D4: MACT | E4: M002-1003-SS-2025 | F4: 45876 | G4: Aug-25 | H4: 46014 | I4: =IF(ISBLANK(H4), "", TEXT(H4, "mmm-yy")) -> Dec-25 | J4: =IF(F4="", "", IF(OR(M4="WC Claim", M4="Partial Case"), WORKDAY(F4, 15), IF(OR(M4="Medical Verification", M4="Full Case"), WORKDAY(F4, 30), ""))) -> 45918 | K4: =IF(F4="", "", IF(ISNUMBER(H4), H4 - F4, TODAY() - F4)) -> 138 | L4: =IF(K4="", "", IF(OR(M4="Partial Case", M4="Medical Verification", M4="WC Claim"), IF(K4<=15, "WT", "AT"), IF(K4<30, "WT", "AT") ) ) -> AT | M4: Full Case | N4: Dispatch | O4: Completed | Q4: Balu Motiram Wagh | R4: Rajapur, Yevla, Nashik. (Nandgaon Depo) | S4: Nashik | T4: Completed | U4: NA | X4: NA | Y4: Shayan Raies Sayyad | Z4: 114/1 B, Sarvade Nagar, Near Iqbal Kirana Marchant, Mulegaon Road, Uttar Solapur, 413006. | AA4: Solapur | AB4: NA | AC4: Completed | AD4: Sagar Ankush Bhosale | AF4: NA | AG4: Completed | AH4: NA | AI4: NA | AJ4: NA | AK4: NA | AL4: NA | AM4: NA | AN4: NA | AO4: NA | AP4: NA | AQ4: On Sindhkhed Raja Road, Next of Vakhari Fhata, Jalna Navha Road. | AR4: Jalna | AS4: Completed | AT4: Nashik | AU4: NA | AV4: NA | AW4: NA | AX4: Completed | AY4: Vira Medicity Hosp | BB4: NA | BE4: Claimant/ Spot/ Insured / Driver / Chargesheet
A5: 4 | B5: MTP-N-2526-002724 | C5: Generali Central Insurance Company Limited | D5: MACT | E5: F001-1004-SS-2025 | F5: 45890 | G5: Aug-25 | H5: 45918 | I5: =IF(ISBLANK(H5), "", TEXT(H5, "mmm-yy")) -> Sep-25 | J5: =IF(F5="", "", IF(OR(M5="WC Claim", M5="Partial Case"), WORKDAY(F5, 15), IF(OR(M5="Medical Verification", M5="Full Case"), WORKDAY(F5, 30), ""))) -> 45932 | K5: =IF(F5="", "", IF(ISNUMBER(H5), H5 - F5, TODAY() - F5)) -> 28 | L5: =IF(K5="", "", IF(OR(M5="Partial Case", M5="Medical Verification", M5="WC Claim"), IF(K5<=15, "WT", "AT"), IF(K5<30, "WT", "AT") ) ) -> WT | M5: Full Case | N5: Dispatch | O5: Completed | Q5: Popat Baburao Ghule | R5: Paregaon Terfe Khed, Pune | S5: Pune | T5: Completed | U5: Yes | X5: NA | Y5: Salim Ajgarali Sayyad | Z5: Rajguru Nagar, Pune. | AA5: Pune | AB5: NA | AC5: Completed | AD5: NA | AF5: NA | AG5: Completed | AH5: Yes | AI5: WIP | AJ5: WIP | AK5: WIP | AL5: NA | AM5: NA | AN5: NA | AO5: NA | AP5: NA | AQ5: On Pune Nashik Highway, Near Pancharatne Hotel, Jaidwadi, Khed, Pune. | AR5: Pune | AS5: Completed | AT5: NA | AU5: NA | AV5: NA | AW5: NA | AX5: NA | BB5: Completed
A6: 5 | B6: MTP-N-2526-002725 | C6: Generali Central Insurance Company Limited | D6: MACT | E6: F001-1005-SS-2025 | F6: 45890 | G6: Aug-25 | H6: 45918 | I6: =IF(ISBLANK(H6), "", TEXT(H6, "mmm-yy")) -> Sep-25 | J6: =IF(F6="", "", IF(OR(M6="WC Claim", M6="Partial Case"), WORKDAY(F6, 15), IF(OR(M6="Medical Verification", M6="Full Case"), WORKDAY(F6, 30), ""))) -> 45932 | K6: =IF(F6="", "", IF(ISNUMBER(H6), H6 - F6, TODAY() - F6)) -> 28 | L6: =IF(K6="", "", IF(OR(M6="Partial Case", M6="Medical Verification", M6="WC Claim"), IF(K6<=15, "WT", "AT"), IF(K6<30, "WT", "AT") ) ) -> WT | M6: Full Case | N6: Dispatch | O6: Completed | Q6: Ramdas Baban Thorat | R6: Khed-Pune | S6: Pune | T6: Completed | U6: NA | X6: NA | Y6: NA | Z6: NA | AA6: NA | AB6: NA | AC6: NA | AD6: NA | AF6: NA | AG6: NA | AH6: NA | AI6: NA | AJ6: NA | AK6: NA | AL6: NA | AM6: NA | AN6: NA | AO6: NA | AP6: NA | AQ6: NA | AR6: NA | AS6: STOP | AV6: NA | AX6: NA | BB6: NA
